Workbook

Sheet MAR 2026
C10: DEPOSITOS | F10: SAQUES | I10: BALANÇO | J10: GERAL
A11: DATA | B11: Total (BRL) | C11: Deps Sum | D11: Number of Deposits | E11: Ticket | F11: W/D Sum | G11: Number of W/D | H11: Ticket | I11: NETCASH | J11: REGISTROS | K11: FTD | L11: UAP | M11: FTD AMOUNT. | N11: CASINO PAYOUT | O11: Sportsbook Turnover | P11: TURNOVER CASSINO | Q11: Casino GGR | R11: Total NGR | S11: Casino GGR %
A12: 46023 | B12: =C12*6.2 -> 29548.952 | C12: 4765.96 | D12: 366 | E12: =B12/$D$12 -> 80.734842 | F12: 3255.66 | G12: 80 | H12: =F12/G12 -> 40.69575 | I12: =C12-F12 -> 1510.3 | J12: 396 | K12: 116 | L12: 315 | N12: 43211.2 | O12: 852.25 | P12: 43245.69 | Q12: 34.49 | R12: -89.11 | S12: =R12/P12 -> -0.0020605522
A13: =A12+1 -> 46024 | B13: =C13*6.2 -> 20633.042 | C13: 3327.91 | D13: 323 | E13: =B13/$D$12 -> 56.374432 | F13: 2899.92 | G13: 66 | H13: =F13/G13 -> 43.938182 | I13: =C13-F13 -> 427.99 | J13: 409 | K13: 112 | L13: 308 | N13: 38629.47 | O13: 579.88 | P13: 38283.35 | Q13: -346.12 | R13: -210.15 | S13: =R13/P13 -> -0.0054893315
A14: =A13+1 -> 46025 | B14: =C14*6.2 -> 26181.05 | C14: 4222.75 | D14: 319 | E14: =B14/$D$12 -> 71.532923 | F14: 4750.3 | G14: 61 | H14: =F14/G14 -> 77.87377 | I14: =C14-F14 -> -527.55 | J14: 291 | K14: 102 | L14: 336 | N14: 47724.59 | O14: 500.73 | P14: 48474.54 | Q14: 749.95 | R14: 613.23 | S14: =R14/P14 -> 0.012650558
A15: =A14+1 -> 46026 | B15: =C15*6.2 -> 50149.32 | C15: 8088.6 | D15: 286 | E15: =B15/$D$12 -> 137.02 | F15: 3799.72 | G15: 61 | H15: =F15/G15 -> 62.290492 | I15: =C15-F15 -> 4288.88 | J15: 161 | K15: 63 | L15: 250 | N15: 55781.85 | O15: 364.63 | P15: 60416.35 | Q15: 4634.5 | R15: 4928.64 | S15: =R15/P15 -> 0.081577917
A16: =A15+1 -> 46027 | B16: =C16*6.2 -> 20125.51 | C16: 3246.05 | D16: 177 | E16: =B16/$D$12 -> 54.987732 | F16: 4932.73 | G16: 55 | H16: =F16/G16 -> 89.686 | I16: =C16-F16 -> -1686.68 | J16: 95 | K16: 16 | L16: 196 | N16: 43811.91 | O16: 1020.3 | P16: 40842.78 | Q16: -2969.13 | R16: -2857.22 | S16: =R16/P16 -> -0.06995655
A17: =A16+1 -> 46028 | B17: =C17*6.2 -> 41831.09 | C17: 6746.95 | D17: 248 | E17: =B17/$D$12 -> 114.2926 | F17: 4947.28 | G17: 57 | H17: =F17/G17 -> 86.794386 | I17: =C17-F17 -> 1799.67 | J17: 68 | K17: 15 | L17: 217 | N17: 54267.78 | O17: 583.65 | P17: 51324.33 | Q17: -2943.45 | R17: -2646.28 | S17: =R17/P17 -> -0.051559952
A18: =A17+1 -> 46029 | B18: =C18*6.2 -> 33563.08 | C18: 5413.4 | D18: 241 | E18: =B18/$D$12 -> 91.702404 | F18: 6579.12 | G18: 70 | H18: =F18/G18 -> 93.987429 | I18: =C18-F18 -> -1165.72 | J18: 68 | K18: 15 | L18: 187 | N18: 63619.04 | O18: 713.43 | P18: 64140.01 | Q18: 520.97 | R18: 72.22 | S18: =R18/P18 -> 0.0011259743
A19: =A18+1 -> 46030 | B19: =C19*6.2 -> 27896.714 | C19: 4499.47 | D19: 213 | E19: =B19/$D$12 -> 76.22053 | F19: 3349.1 | G19: 64 | H19: =F19/G19 -> 52.329687 | I19: =C19-F19 -> 1150.37 | J19: 177 | K19: 22 | L19: 195 | N19: 49359.44 | O19: 1228.12 | P19: 51221.92 | Q19: 1862.48 | R19: 2256.11 | S19: =R19/P19 -> 0.044045791
A20: =A19+1 -> 46031 | B20: =C20*6.2 -> 28969.562 | C20: 4672.51 | D20: 173 | E20: =B20/$D$12 -> 79.151809 | F20: 3568.21 | G20: 55 | H20: =F20/G20 -> 64.876545 | I20: =C20-F20 -> 1104.3 | J20: 58 | K20: 5 | L20: 164 | N20: 38079.49 | O20: 854.43 | P20: 40800.73 | Q20: 2721.24 | R20: 2456.29 | S20: =R20/P20 -> 0.060202109
A21: =A20+1 -> 46032 | B21: =C21*6.2 -> 37893.408 | C21: 6111.84 | D21: 225 | E21: =B21/$D$12 -> 103.5339 | F21: 5111.32 | G21: 64 | H21: =F21/G21 -> 79.864375 | I21: =C21-F21 -> 1000.52 | J21: 128 | K21: 58 | L21: 220 | N21: 43326.97 | O21: 1956.29 | P21: 47404.75 | Q21: 4077.78 | R21: 4190.64 | S21: =R21/P21 -> 0.088401268
A22: =A21+1 -> 46033 | B22: =C22*6.2 -> 27264.81 | C22: 4397.55 | D22: 233 | E22: =B22/$D$12 -> 74.494016 | F22: 4495.81 | G22: 56 | H22: =F22/G22 -> 80.282321 | I22: =C22-F22 -> -98.26 | J22: 168 | K22: 77 | L22: 275 | N22: 37086.39 | O22: 977.88 | P22: 36489.56 | Q22: -596.83 | R22: -369.38 | S22: =R22/P22 -> -0.010122895
A23: =A22+1 -> 46034 | B23: =C23*6.2 -> 39939.594 | C23: 6441.87 | D23: 225 | E23: =B23/$D$12 -> 109.12457 | F23: 4420.8 | G23: 56 | H23: =F23/G23 -> 78.942857 | I23: =C23-F23 -> 2021.07 | J23: 130 | K23: 49 | L23: 266 | N23: 54171.44 | O23: 526.24 | P23: 50675.13 | Q23: -3496.31 | R23: -3151.64 | S23: =R23/P23 -> -0.062193032
A24: =A23+1 -> 46035 | B24: =C24*6.2 -> 30704.632 | C24: 4952.36 | D24: 243 | E24: =B24/$D$12 -> 83.892437 | F24: 5598.09 | G24: 55 | H24: =F24/G24 -> 101.78345 | I24: =C24-F24 -> -645.73 | J24: 72 | K24: 31 | L24: 220 | N24: 59583.52 | O24: 803.16 | P24: 65311.15 | Q24: 5727.63 | R24: 5724.34 | S24: =R24/P24 -> 0.087647209
... A34: =A33+1 -> 46045 | B34: =C34*6.2 -> 76711.174 | C34: 12372.77 | D34: 555 | E34: =B34/$D$12 -> 209.59337 | F34: 11732.72 | G34: 87 | H34: =F34/G34 -> 134.85885 | I34: =C34-F34 -> 640.05 | J34: 792 | K34: 286 | L34: 459 | N34: 78921.53 | O34: 708.02 | P34: 82260.99 | Q34: 3339.46 | R34: 3353.23 | S34: =R34/P34 -> 0.040763307
A35: =A34+1 -> 46046 | E35: =B35/$D$12 -> 0 | H35: =F35/G35 -> #DIV/0! | I35: =C35-F35 -> 0 | S35: =R35/P35 -> #DIV/0!
A36: =A35+1 -> 46047 | B36: =C36*6.2 -> 0 | E36: =B36/$D$12 -> 0 | H36: =F36/G36 -> #DIV/0! | I36: =C36-F36 -> 0 | S36: =R36/P36 -> #DIV/0!
A37: =A36+1 -> 46048 | B37: =C37*6.2 -> 0 | E37: =B37/$D$12 -> 0 | H37: =F37/G37 -> #DIV/0! | I37: =C37-F37 -> 0 | S37: =R37/P37 -> #DIV/0!
A38: =A37+1 -> 46049 | B38: =C38*6.2 -> 0 | E38: =B38/$D$12 -> 0 | H38: =F38/G38 -> #DIV/0! | I38: =C38-F38 -> 0 | S38: =R38/P38 -> #DIV/0!
A39: =A38+1 -> 46050 | B39: =C39*6.2 -> 0 | E39: =B39/$D$12 -> 0 | H39: =F39/G39 -> #DIV/0! | I39: =C39-F39 -> 0 | S39: =R39/P39 -> #DIV/0!
A40: =A39+1 -> 46051 | B40: =C40*6.2 -> 0 | E40: =B40/$D$12 -> 0 | H40: =F40/G40 -> #DIV/0! | I40: =C40-F40 -> 0 | S40: =R40/P40 -> #DIV/0!
A41: =A40+1 -> 46052 | B41: =C41*6.2 -> 0 | E41: =B41/$D$12 -> 0 | H41: =F41/G41 -> #DIV/0! | I41: =C41-F41 -> 0 | S41: =R41/P41 -> #DIV/0!
A42: =A41+1 -> 46053 | B42: =C42*6.2 -> 0 | E42: =B42/$D$12 -> 0 | H42: =F42/G42 -> #DIV/0! | I42: =C42-F42 -> 0 | S42: =R42/P42 -> #DIV/0!
A43: TOTAL | B43: =sum(B12:B42) -> 879624.32 | C43: =sum(C12:C42) -> 141874.89 | D43: =sum(D12:D42) -> 6301 | E43: =B43/D43 -> 139.60075 | F43: =sum(F12:F42) -> 101640.94 | G43: =sum(G12:G42) -> 1447 | H43: =F43/G43 -> 70.242529 | I43: =sum(I12:I42) -> 40233.95 | J43: =sum(J12:J42) -> 5098 | K43: =sum(K12:K42) -> 1786 | L43: =sum(L12:L42) -> 5943 | M43: =SUM(M12:M42) -> 0 | N43: =SUM(N12:N42)*6.2 -> 7083352.8 | O43: =SUM(O12:O42)*6.2 -> 145008.58 | P43: =SUM(P12:P42)*6.2 -> 7304726.4 | Q43: =SUM(Q12:Q42)*6.2 -> 221373.67 | R43: =SUM(R12:R42)*6.2 -> 227786.95 | S43: =Q43/P43 -> 0.030305538
C44: DEPOSITOS | D44: QTD. DEP | E44: TICKET DEPOSITOS | F44: SAQUES | G44: QTD. SAQUE | H44: TICKET SAQUE | I44: NETCASH LIQUIDO | J44: CONVERSÃO FTD | M44: REDEP. | N44: INATIVOS | O44: CHURN | P44: LTV | Q44: TX. GETWAY | R44: PLAT. FEE 15% | S44: MEDIA %
I45: =I43-Q45 -> 23552.441 | J45: =K43/J43 -> 0.35033346 | N45: =J43-K43 -> 3312 | O45: =N45/J43 -> 0.64966654 | P45: =Q43/K43 -> 123.94942 | Q45: =(B43+F43)*0.017 -> 16681.509 | R45: 35000

Sheet WALLET
I1: CAIXA WALLET
A2: DESCRIÇÃO | B2: DATA | C2: $ | D2: R$ | E2: PTAX | F2: OBS SITUAÇÃO | G2: OBS SITUAÇÃO
A4: SAQUES DIGITO VIA CRIPTOATIVOS | B4: 45980 | C4: 371.0575 | G4: EFETUADO
A5: SAQUES DIGITO VIA CRIPTOATIVOS | B5: 45980 | C5: 9259.2593 | G5: EFETUADO | I5: CAIXA WALLET CRIPTO ATUALMENTE | J5: VALOR
A6: SAQUES DIGITO VIA CRIPTOATIVOS | B6: 45989 | C6: 4454.9426 | G6: EFETUADO | I6: USDT | J6: =SUM(C42:C48) -> 22679.385
A7: SAQUES DIGITO VIA CRIPTOATIVOS | B7: 45992 | C7: 9259.2593 | G7: EFETUADO | I7: LAST PTAX | J7: 5.39
A8: SAQUES WALLET | B8: 45992 | C8: -10012 | D8: =PAGAMENTOS!C20 -> -54075.6 | E8: =D8/C8 -> 5.4010787 | F8: Pagamento Fluxrise (reembolso trafego affbr) | G8: EFETUADO | I8: VALOR R$ | J8: =J6*J7 -> 122241.88
A9: SAQUES DIGITO VIA CRIPTOATIVOS | B9: 45999 | C9: 9157.5092 | G9: EFETUADO
A10: SAQUES DIGITO VIA CRIPTOATIVOS | B10: 46003 | C10: 4578.7546 | G10: EFETUADO
A11: SAQUES DIGITO VIA CRIPTOATIVOS | B11: 46008 | C11: 4504.5045 | G11: EFETUADO
A12: SAQUES WALLET | B12: =PAGAMENTOS!B24 -> 46011 | C12: -28000 | D12: =PAGAMENTOS!C24 -> -152320 | E12: =D12/C12 -> 5.44 | F12: Saques e distribuicao | G12: EFETUADO
A13: SAQUES DIGITO VIA CRIPTOATIVOS | B13: 46013 | C13: 7168.4588 | G13: EFETUADO
A14: SAQUES DIGITO VIA CRIPTOATIVOS | B14: 46014 | C14: 1773.0496 | G14: EFETUADO
A15: SAQUES DIGITO VIA CRIPTOATIVOS | B15: 46017 | C15: 5357.1429 | G15: EFETUADO
A16: SAQUES WALLET | B16: 46017 | C16: -5806.69 | F16: Fatura GGR | G16: EFETUADO
A17: SAQUES WALLET | B17: 46017 | C17: -12043 | D17: =C17*5.54 -> -66718.22 | E17: 5.54 | F17: Saques e distribuicao | G17: EFETUADO
A18: SAQUES DIGITO VIA CRIPTOATIVOS | B18: 46022 | C18: 5415.1625 | G18: EFETUADO
A19: SAQUES DIGITO VIA CRIPTOATIVOS | B19: 46029 | C19: 10110.294 | G19: EFETUADO
A20: SAQUES DIGITO VIA CRIPTOATIVOS | B20: 46030 | C20: 4587.156 | G20: EFETUADO
A21: SAQUES DIGITO VIA CRIPTOATIVOS | B21: 46036 | C21: 4595.5882 | G21: EFETUADO
A22: SAQUES WALLET | B22: 46036 | C22: =SUM(C18:C21)*-1 -> -24708.201 | E22: 5.39 | F22: Saques e distribuicao_Sheet Saque 14.01 | G22: EFETUADO
A23: SAQUES DIGITO VIA CRIPTOATIVOS | B23: 46038 | C23: 4604.0516 | G23: EFETUADO
A24: SAQUES DIGITO VIA CRIPTOATIVOS | B24: =B23+3 -> 46041 | C24: 7366.4825 | G24: EFETUADO
A25: SAQUES DIGITO VIA CRIPTOATIVOS | B25: =B24+3 -> 46044 | C25: 3731.3433 | G25: EFETUADO
A26: SAQUES DIGITO VIA CRIPTOATIVOS | B26: =B25+1 -> 46045 | C26: 4672.8972 | G26: EFETUADO
A27: SAQUES DIGITO VIA CRIPTOATIVOS | B27: =B26+3 -> 46048 | C27: 7476.6355 | G27: EFETUADO
A28: PAGAMENTO VIA UST DIRETA | B28: =B27 -> 46048 | C28: -1172 | D28: =E28*C28 -> -6797.6 | E28: 5.8 | F28: Pagamento Julia 7.020,00 BRL | G28: EFETUADO
A29: PAGAMENTO VIA UST DIRETA | B29: =B28 -> 46048 | C29: -10000 | D29: =E29*C29 -> -58000 | E29: 5.8 | F29: VALOR USADO AFFBR | G29: EFETUADO
A30: SAQUES DIGITO VIA CRIPTOATIVOS | B30: =B28+1 -> 46049 | C30: 3738.3178 | G30: EFETUADO
A31: PAGAMENTO VIA UST DIRETA | B31: =B30 -> 46049 | C31: -822 | D31: =E31*C31 -> -4767.6 | E31: 5.8 | F31: Setup + plano starter blacktrack | G31: EFETUADO
A32: SAQUES DIGITO VIA CRIPTOATIVOS | B32: =B31+2 -> 46051 | C32: 3787.8788 | G32: EFETUADO
A33: SAQUES DIGITO VIA CRIPTOATIVOS | B33: =B32+1 -> 46052 | C33: 4699.2481 | G33: EFETUADO
A34: PAGAMENTO VIA UST DIRETA | B34: 46053 | C34: -10518 | F34: Invoice em Euros para Phoenix | G34: EFETUADO
A35: SAQUES DIGITO VIA CRIPTOATIVOS | B35: 05/02/0226 | C35: 4690.4315 | G35: EFETUADO
A36: SAQUES DIGITO VIA CRIPTOATIVOS | B36: 46063 | C36: 1893.9394 | G36: EFETUADO
A37: SAQUES DIGITO VIA CRIPTOATIVOS | B37: =B36+1 -> 46064 | C37: 7935.9261 | G37: EFETUADO
A38: SAQUES DIGITO VIA CRIPTOATIVOS | B38: =B37+1 -> 46065 | C38: 1423.4405 | G38: EFETUADO
A39: SAQUES DIGITO VIA CRIPTOATIVOS | B39: =B38+4 -> 46069 | C39: 1192.1626 | G39: EFETUADO
A40: SAQUES DIGITO VIA CRIPTOATIVOS | B40: =B39+3 -> 46072 | C40: 4655.4935 | G40: EFETUADO
A41: SAQUES DIGITO VIA CRIPTOATIVOS | B41: =B40+4 -> 46076 | C41: 9433.9623 | G41: EFETUADO
A42: SAQUES DIGITO VIA CRIPTOATIVOS | B42: =B41+1 -> 46077 | C42: 4716.9811 | G42: EFETUADO
A43: SAQUES DIGITO VIA CRIPTOATIVOS | B43: =B42 -> 46077 | C43: 2350.0949 | G43: EFETUADO
A44: SAQUES DIGITO VIA CRIPTOATIVOS | B44: =B43+2 -> 46079 | C44: 4752.8517 | G44: EFETUADO
A45: SAQUES DIGITO VIA CRIPTOATIVOS | B45: =B44+1 -> 46080 | C45: 4734.8485 | G45: EFETUADO
A46: SAQUES DIGITO VIA CRIPTOATIVOS | B46: =B45+5 -> 46085 | C46: 3731.3433 | G46: EFETUADO
A47: SAQUES DIGITO VIA CRIPTOATIVOS | B47: =B46+1 -> 46086 | C47: 1339.6803 | G47: EFETUADO
A48: SAQUES DIGITO VIA CRIPTOATIVOS | B48: =B47+5 -> 46091 | C48: 1053.5849 | G48: EFETUADO
A49: SAQUES DIGITO VIA CRIPTOATIVOS | B49: =B48+2 -> 46093 | C49: 1660.4478 | G49: EFETUADO
A50: SAQUES DIGITO VIA CRIPTOATIVOS | B50: =B49+1 -> 46094 | C50: 551.4706 | G50: EFETUADO
A51: SAQUES DIGITO VIA CRIPTOATIVOS | B51: =B50+3 -> 46097 | C51: 3710.5751 | G51: EFETUADO
A52: SAQUES DIGITO VIA CRIPTOATIVOS | B52: =B51+1 -> 46098 | C52: 1310.8614 | G52: EFETUADO
A53: SAQUES DIGITO VIA CRIPTOATIVOS | B53: =B52+1 -> 46099 | C53: 12195.122 | G53: EFETUADO
A54: SAQUES DIGITO VIA CRIPTOATIVOS | B54: =B53+1 -> 46100 | C54: 4096.8343 | G54: EFETUADO

Sheet FEV 2026
C10: DEPOSITOS | F10: SAQUES | I10: BALANÇO | J10: GERAL
A11: DATA | B11: Total (BRL) | C11: Deps Sum | D11: Number of Deposits | E11: Ticket | F11: W/D Sum | G11: Number of W/D | H11: Ticket | I11: NETCASH | J11: REGISTROS | K11: FTD | L11: UAP | M11: FTD AMOUNT. | N11: CASINO PAYOUT | O11: Sportsbook Turnover | P11: CASINO TURNOVER | Q11: Casino GGR | R11: Total NGR | S11: Casino GGR %
A12: 46054 | B12: =C12*6.2 -> 26576.052 | C12: 4286.46 | D12: 221 | E12: =B12/$D$12 -> 120.25363 | F12: 4717.05 | G12: 63 | H12: =F12/G12 -> 74.87381 | I12: =C12-F12 -> -430.59 | J12: 134 | K12: 45 | L12: 268 | N12: 47342.97 | O12: 893.33 | P12: 47823.9 | Q12: 480.93 | R12: 294.13 | S12: =R12/P12 -> 0.0061502721
A13: =A12+1 -> 46055 | B13: =C13*6.2 -> 33848.466 | C13: 5459.43 | D13: 265 | E13: =B13/$D$12 -> 153.16048 | F13: 3526.51 | G13: 65 | H13: =F13/G13 -> 54.254 | I13: =C13-F13 -> 1932.92 | J13: 104 | K13: 34 | L13: 227 | N13: 39515.92 | O13: 975.8 | P13: 41912.21 | Q13: 2396.29 | R13: 2511.83 | S13: =R13/P13 -> 0.059930746
A14: =A13+1 -> 46056 | B14: =C14*6.2 -> 29323.334 | C14: 4729.57 | D14: 301 | E14: =B14/$D$12 -> 132.68477 | F14: 3090.58 | G14: 74 | H14: =F14/G14 -> 41.764595 | I14: =C14-F14 -> 1638.99 | J14: 178 | K14: 41 | L14: 235 | N14: 45165.31 | O14: 682.99 | P14: 46257.71 | Q14: 1092.4 | R14: 1306.62 | S14: =R14/P14 -> 0.028246534
A15: =A14+1 -> 46057 | B15: =C15*6.2 -> 35744.426 | C15: 5765.23 | D15: 269 | E15: =B15/$D$12 -> 161.73948 | F15: 4745.47 | G15: 75 | H15: =F15/G15 -> 63.272933 | I15: =C15-F15 -> 1019.76 | J15: 147 | K15: 35 | L15: 210 | N15: 38256.55 | O15: 546.44 | P15: 38768.09 | Q15: 511.54 | R15: 378.42 | S15: =R15/P15 -> 0.0097611206
A16: =A15+1 -> 46058 | B16: =C16*6.2 -> 41932.398 | C16: 6763.29 | D16: 337 | E16: =B16/$D$12 -> 189.73936 | F16: 5967.93 | G16: 92 | H16: =F16/G16 -> 64.868804 | I16: =C16-F16 -> 795.36 | J16: 123 | K16: 40 | L16: 256 | N16: 53284.85 | O16: 1303.51 | P16: 50177.04 | Q16: -3107.81 | R16: -2312.69 | S16: =R16/P16 -> -0.046090602
A17: =A16+1 -> 46059 | B17: =C17*6.2 -> 40987.642 | C17: 6610.91 | D17: 264 | E17: =B17/$D$12 -> 185.46444 | F17: 6516.06 | G17: 99 | H17: =F17/G17 -> 65.818788 | I17: =C17-F17 -> 94.85 | J17: 95 | K17: 29 | L17: 256 | N17: 54524.97 | O17: 825.55 | P17: 56484.26 | Q17: 1959.29 | R17: 2363.7 | S17: =R17/P17 -> 0.041847056
A18: =A17+1 -> 46060 | B18: =C18*6.2 -> 32434.494 | C18: 5231.37 | D18: 280 | E18: =B18/$D$12 -> 146.76242 | F18: 3455.54 | G18: 93 | H18: =F18/G18 -> 37.156344 | I18: =C18-F18 -> 1775.83 | J18: 108 | K18: 43 | L18: 226 | N18: 63645.18 | O18: 256.22 | P18: 61845.77 | Q18: -1799.41 | R18: -1844.11 | S18: =R18/P18 -> -0.029817884
A19: =A18+1 -> 46061 | B19: =C19*6.2 -> 19035.302 | C19: 3070.21 | D19: 207 | E19: =B19/$D$12 -> 86.132588 | F19: 5208.74 | G19: 68 | H19: =F19/G19 -> 76.599118 | I19: =C19-F19 -> -2138.53 | J19: 148 | K19: 48 | L19: 188 | N19: 30990.32 | O19: 243.34 | P19: 30061.58 | Q19: -928.74 | R19: -1038.37 | S19: =R19/P19 -> -0.034541431
A20: =A19+1 -> 46062 | B20: =C20*6.2 -> 39440.122 | C20: 6361.31 | D20: 363 | E20: =B20/$D$12 -> 178.46209 | F20: 5412.76 | G20: 145 | H20: =F20/G20 -> 37.329379 | I20: =C20-F20 -> 948.55 | J20: 267 | K20: 92 | L20: 264 | N20: 62212.89 | O20: 268.08 | P20: 64822.43 | Q20: 2609.54 | R20: 2623.22 | S20: =R20/P20 -> 0.040467783
A21: =A20+1 -> 46063 | B21: =C21*6.2 -> 62923.614 | C21: 10148.97 | D21: 366 | E21: =B21/$D$12 -> 284.72224 | F21: 4293.33 | G21: 79 | H21: =F21/G21 -> 54.345949 | I21: =C21-F21 -> 5855.64 | J21: 317 | K21: 108 | L21: 308 | N21: 102052.3 | O21: 783.77 | P21: 109405.77 | Q21: 7353.47 | R21: 7774.25 | S21: =R21/P21 -> 0.071058866
A22: =A21+1 -> 46064 | B22: =C22*6.2 -> 51598.508 | C22: 8322.34 | D22: 343 | E22: =B22/$D$12 -> 233.47741 | F22: 3768.86 | G22: 68 | H22: =F22/G22 -> 55.424412 | I22: =C22-F22 -> 4553.48 | J22: 323 | K22: 107 | L22: 314 | N22: 62449.1 | O22: 779.06 | P22: 64617.9 | Q22: 2168.8 | R22: 1951.48 | S22: =R22/P22 -> 0.030200301
A23: =A22+1 -> 46065 | B23: =C23*6.2 -> 22340.584 | C23: 3603.32 | D23: 335 | E23: =B23/$D$12 -> 101.08862 | F23: 5655.99 | G23: 71 | H23: =F23/G23 -> 79.661831 | I23: =C23-F23 -> -2052.67 | J23: 234 | K23: 84 | L23: 327 | N23: 53599.39 | O23: 438.34 | P23: 55485.01 | Q23: 1885.62 | R23: 1977.8 | S23: =R23/P23 -> 0.035645664
A24: =A23+1 -> 46066 | B24: =C24*6.2 -> 30301.694 | C24: 4887.37 | D24: 366 | E24: =B24/$D$12 -> 137.11174 | F24: 5054.21 | G24: 62 | H24: =F24/G24 -> 81.519516 | I24: =C24-F24 -> -166.84 | J24: 325 | K24: 89 | L24: 338 | N24: 54992.96 | O24: 408.98 | P24: 57463.65 | Q24: 2470.69 | R24: 2326.35 | S24: =R24/P24 -> 0.040483854
... A39: =A38+1 -> 46081 | B39: =C39*6.2 -> 28714.742 | C39: 4631.41 | D39: 347 | E39: =B39/$D$12 -> 129.93096 | F39: 3076.73 | G39: 69 | H39: =F39/G39 -> 44.59029 | I39: =C39-F39 -> 1554.68 | J39: 334 | K39: 116 | L39: 324 | N39: 57207 | O39: 904.57 | P39: 60330.55 | Q39: 3123.55 | R39: 2905.43 | S39: =R39/P39 -> 0.04815852
A40: TOTAL | B40: =sum(B12:B39) -> 973022.11 | C40: =sum(C12:C39) -> 156939.05 | D40: =sum(D12:D39) -> 8756 | E40: =B40/D40 -> 111.12633 | F40: =937493-258258.65 -> 679234.35 | G40: =sum(G12:G39) -> 1881 | H40: =F40/G40 -> 361.10279 | I40: =B40-F40 -> 293787.76 | J40: =sum(J12:J39) -> 6550 | K40: =sum(K12:K39) -> 2298 | L40: =sum(L12:L39) -> 7809 | M40: =SUM(M12:M39) -> 0 | N40: =SUM(N12:N39)*6.2 -> 8732781.7 | O40: =SUM(O12:O39)*6.2 -> 96822.238 | P40: =SUM(P12:P39)*6.2 -> 9082871.7 | Q40: =SUM(Q12:Q39)*6.2 -> 350089.94 | R40: =SUM(R12:R39)*6.2 -> 362707.25 | S40: =Q40/P40 -> 0.038543971
C41: DEPOSITOS | D41: QTD. DEP | E41: TICKET DEPOSITOS | F41: SAQUES | G41: QTD. SAQUE | H41: TICKET SAQUE | I41: NETCASH LIQUIDO | J41: CONVERSÃO FTD | M41: REDEP. | N41: INATIVOS | O41: CHURN | P41: LTV | Q41: TX. GETWAY | R41: PLAT. FEE 15% | S41: MEDIA %
I42: =I40-Q42 -> 279154.73 | J42: =K40/J40 -> 0.35083969 | N42: =J40-K40 -> 4252 | O42: =N42/J40 -> 0.64916031 | P42: =Q40/K40 -> 152.34549 | Q42: =(C40+F40)*0.0175 -> 14633.034 | R42: =Q40*0.15 -> 52513.492

Sheet JAN 2026
C10: DEPOSITOS | F10: SAQUES | I10: BALANÇO | J10: GERAL
A11: DATA | B11: Total (BRL) | C11: Deps Sum | D11: Number of Deposits | E11: Ticket | F11: W/D Sum | G11: Number of W/D | H11: Ticket | I11: NETCASH | J11: REGISTROS | K11: FTD | L11: UAP | M11: FTD AMOUNT. | N11: CASINO PAYOUT | O11: Sportsbook Turnover | P11: TURNOVER CASSINO | Q11: Casino GGR | R11: comparativo | S11: Total NGR | T11: Casino GGR %
A12: 46023 | B12: =C12*6.2 -> 31989.396 | C12: 5159.58 | D12: 314 | E12: =B12/$D$12 -> 101.87706 | F12: 4440.07 | G12: 186 | H12: =F12/G12 -> 23.871344 | I12: =C12-F12 -> 719.51 | J12: 169 | K12: 146 | L12: 264 | N12: 33031.4 | O12: 0 | P12: 28251.67 | Q12: -4779.73 | R12: -4779.73 | S12: -4779.73 | T12: -16.92
A13: =A12+1 -> 46024 | B13: =C13*6.2 -> 36552.906 | C13: 5895.63 | D13: 285 | E13: =B13/$D$12 -> 116.41053 | F13: 8231.05 | G13: 142 | H13: =F13/G13 -> 57.965141 | I13: =C13-F13 -> -2335.42 | J13: 98 | K13: 67 | L13: 221 | N13: 43702.4 | O13: 0 | P13: 42664.33 | Q13: -1038.07 | R13: -1038.07 | S13: -1038.07 | T13: -2.43
A14: =A13+1 -> 46025 | B14: =C14*6.2 -> 29237.34 | C14: 4715.7 | D14: 215 | E14: =B14/$D$12 -> 93.112548 | F14: 3740.79 | G14: 84 | H14: =F14/G14 -> 44.533214 | I14: =C14-F14 -> 974.91 | J14: 45 | K14: 21 | L14: 151 | N14: 69435.32 | O14: 0 | P14: 88139.28 | Q14: 18703.96 | R14: 18703.96 | S14: 18703.96 | T14: 21.22
A15: =A14+1 -> 46026 | B15: =C15*6.2 -> 25910.606 | C15: 4179.13 | D15: 207 | E15: =B15/$D$12 -> 82.517854 | F15: 3253.16 | G15: 60 | H15: =F15/G15 -> 54.219333 | I15: =C15-F15 -> 925.97 | J15: 44 | K15: 20 | L15: 155 | N15: 27115.72 | O15: 4.64 | P15: 29494.14 | Q15: 2381.42 | R15: 2381.42 | S15: 2381.42 | T15: 8.06
A16: =A15+1 -> 46027 | B16: =C16*6.2 -> 28393.21 | C16: 4579.55 | D16: 213 | E16: =B16/$D$12 -> 90.424236 | F16: 2183.49 | G16: 63 | H16: =F16/G16 -> 34.658571 | I16: =C16-F16 -> 2396.06 | J16: 111 | K16: 18 | L16: 155 | N16: 26098.77 | O16: 34.97 | P16: 27151.21 | Q16: 1041.43 | R16: 1041.43 | S16: 1041.43 | T16: 3.88
A17: =A16+1 -> 46028 | B17: =C17*6.2 -> 85272.692 | C17: 13753.66 | D17: 259 | E17: =B17/$D$12 -> 271.56908 | F17: 6315.92 | G17: 95 | H17: =F17/G17 -> 66.483368 | I17: =C17-F17 -> 7437.74 | J17: 112 | K17: 21 | L17: 170 | N17: 137606.99 | O17: 50.32 | P17: 140995.74 | Q17: 3401.67 | R17: 3401.67 | S17: 3401.67 | T17: 2.4
A18: =A17+1 -> 46029 | B18: =C18*6.2 -> 38023.36 | C18: 6132.8 | D18: 240 | E18: =B18/$D$12 -> 121.0935 | F18: 4349.96 | G18: 98 | H18: =F18/G18 -> 44.387347 | I18: =C18-F18 -> 1782.84 | J18: 88 | K18: 23 | L18: 179 | N18: 54503.98 | O18: 24.36 | P18: 61606.9 | Q18: 7082.21 | R18: 7082.21 | S18: 7082.21 | T18: 11.53
A19: =A18+1 -> 46030 | B19: =C19*6.2 -> 51031.146 | C19: 8230.83 | D19: 263 | E19: =B19/$D$12 -> 162.51957 | F19: 4576.62 | G19: 94 | H19: =F19/G19 -> 48.687447 | I19: =C19-F19 -> 3654.21 | J19: 54 | K19: 27 | L19: 228 | N19: 47683.17 | O19: 5.25 | P19: 52063.86 | Q19: 4385.94 | R19: 4385.94 | S19: 4385.94 | T19: 8.41
A20: =A19+1 -> 46031 | B20: =C20*6.2 -> 38627.054 | C20: 6230.17 | D20: 343 | E20: =B20/$D$12 -> 123.0161 | F20: 4494.78 | G20: 133 | H20: =F20/G20 -> 33.795338 | I20: =C20-F20 -> 1735.39 | J20: 229 | K20: 76 | L20: 272 | N20: 35571.63 | O20: 3.33 | P20: 36714.61 | Q20: 1146.49 | R20: 1146.49 | S20: 1146.49 | T20: 3.11
A21: =A20+1 -> 46032 | B21: =C21*6.2 -> 36583.038 | C21: 5900.49 | D21: 362 | E21: =B21/$D$12 -> 116.50649 | F21: 6580.79 | G21: 125 | H21: =F21/G21 -> 52.64632 | I21: =C21-F21 -> -680.3 | J21: 137 | K21: 56 | L21: 248 | N21: 42414.3 | O21: 6.21 | P21: 43409.29 | Q21: 960.66 | R21: 960.66 | S21: 960.66 | T21: 2.29
A22: =A21+1 -> 46033 | B22: =C22*6.2 -> 29779.84 | C22: 4803.2 | D22: 255 | E22: =B22/$D$12 -> 94.840255 | F22: 3453.06 | G22: 77 | H22: =F22/G22 -> 44.844935 | I22: =C22-F22 -> 1350.14 | J22: 85 | K22: 15 | L22: 180 | N22: 30378.54 | O22: 31.93 | P22: 32421.86 | Q22: 2054.59 | R22: 2054.59 | S22: 2054.59 | T22: 6.3
A23: =A22+1 -> 46034 | B23: =C23*6.2 -> 31115.63 | C23: 5018.65 | D23: 264 | E23: =B23/$D$12 -> 99.094363 | F23: 4559.21 | G23: 66 | H23: =F23/G23 -> 69.078939 | I23: =C23-F23 -> 459.44 | J23: 96 | K23: 13 | L23: 184 | N23: 37369.71 | O23: 79.97 | P23: 39379 | Q23: 2084.35 | R23: 2084.35 | S23: 2084.35 | T23: 5.1
A24: =A23+1 -> 46035 | B24: =C24*6.2 -> 34605.486 | C24: 5581.53 | D24: 299 | E24: =B24/$D$12 -> 110.20855 | F24: 5464.85 | G24: 136 | H24: =F24/G24 -> 40.182721 | I24: =C24-F24 -> 116.68 | J24: 201 | K24: 91 | L24: 268 | N24: 40219.28 | O24: 30.25 | P24: 41602.15 | Q24: 1408.32 | R24: 1408.32 | S24: 1408.32 | T24: 3.32
... A42: =A41+1 -> 46053 | B42: =C42*6.2 -> 24090.658 | C42: 3885.59 | D42: 309 | E42: =B42/$D$12 -> 76.721841 | F42: 4392.34 | G42: 63 | H42: =F42/G42 -> 69.719683 | I42: =C42-F42 -> -506.75 | J42: 171 | K42: 57 | L42: 259 | N42: 107805.27 | O42: 476.68 | P42: 73716.51 | Q42: -34054.07 | R42: -34054.07 | S42: -34054.07 | T42: 2.8
A43: TOTAL | B43: 1268028 | C43: =sum(C12:C42) -> 208887.42 | D43: =sum(D12:D42) -> 9691 | E43: =B43/D43 -> 130.84594 | F43: 945498 | G43: =sum(G12:G42) -> 3233 | H43: =F43/G43 -> 292.45221 | I43: =B43-F43 -> 322530 | J43: =sum(J12:J42) -> 6070 | K43: =sum(K12:K42) -> 1701 | L43: =sum(L12:L42) -> 7459 | M43: =SUM(M12:M42) -> 0 | N43: =SUM(N12:N42)*6.2 -> 10287345 | O43: =SUM(O12:O42)*6.2 -> 125425.19 | P43: =SUM(P12:P42)*6.2 -> 17156473 | Q43: =SUM(Q12:Q42)*6.2 -> 6910338 | R43: =sum(R11:R42)*6.2 -> 446776.59 | S43: =SUM(S12:S42)*6.2 -> 6910338 | T43: =Q43/P43 -> 0.40278314
C44: DEPOSITOS | D44: QTD. DEP | E44: TICKET DEPOSITOS | F44: SAQUES | G44: QTD. SAQUE | H44: TICKET SAQUE | I44: NETCASH LIQUIDO | J44: CONVERSÃO FTD | M44: REDEP. | N44: INATIVOS | O44: CHURN | P44: LTV | Q44: TX. GETWAY | S44: PLAT. FEE 15% | T44: MEDIA %
I45: =I43-Q45 -> 284900.06 | J45: =K43/J43 -> 0.28023064 | N45: =J43-K43 -> 4369 | O45: =N45/J43 -> 0.71976936 | P45: =Q43/K43 -> 4062.515 | Q45: =(B43+F43)*0.017 -> 37629.942 | S45: 35000

Sheet DEZ 2025
C10: DEPOSITOS | F10: SAQUES | I10: BALANÇO | J10: GERAL
A11: DATA | B11: Total (BRL) | C11: Total (EURO) | D11: QTD | E11: Ticket | F11: Total (EURO) | G11: QTD | H11: Ticket | I11: NETCASH | J11: REGISTROS | K11: FTD | L11: UAP | M11: FTD AMOUNT. | N11: WINS | O11: TURNOVER SPTBS | P11: TURNOVER CASSINO | Q11: GGR | R11: NGR | S11: GGR%
A12: 45992 | B12: =C12*6 -> 40756.14 | C12: 6792.69 | D12: 317 | E12: =C12/D12 -> 21.428044 | F12: 5529.34 | G12: 86 | H12: =F12/G12 -> 64.294651 | I12: =C12-F12 -> 1263.35 | J12: 107 | K12: 47 | L12: 226 | N12: 53201.24 | P12: 48164.98 | Q12: -5036.26 | R12: -5083.49 | S12: -10.46
A13: =A12+1 -> 45993 | B13: =C13*6 -> 43916.4 | C13: 7319.4 | D13: 279 | E13: =C13/D13 -> 26.234409 | F13: 8897.53 | G13: 100 | H13: =F13/G13 -> 88.9753 | I13: =C13-F13 -> -1578.13 | J13: 98 | K13: 52 | L13: 240 | N13: 62513.87 | P13: 63163.32 | Q13: 649.45 | R13: 745.28 | S13: 1.03
A14: =A13+1 -> 45994 | B14: =C14*6 -> 47063.76 | C14: 7843.96 | D14: 294 | E14: =C14/D14 -> 26.680136 | F14: 4720.75 | G14: 89 | H14: =F14/G14 -> 53.042135 | I14: =C14-F14 -> 3123.21 | J14: 103 | K14: 41 | L14: 235 | N14: 57513.65 | P14: 64089.54 | Q14: 6575.89 | R14: 6334.3 | S14: 10.26
A15: =A14+1 -> 45995 | B15: =C15*6 -> 31916.58 | C15: 5319.43 | D15: 238 | E15: =C15/D15 -> 22.350546 | F15: 5622.08 | G15: 101 | H15: =F15/G15 -> 55.664158 | I15: =C15-F15 -> -302.65 | J15: 85 | K15: 31 | L15: 196 | N15: 34562.38 | P15: 34413.03 | Q15: -149.35 | R15: -72.12 | S15: -0.43
A16: =A15+1 -> 45996 | B16: =C16*6 -> 37990.14 | C16: 6331.69 | D16: 287 | E16: =C16/D16 -> 22.061638 | F16: 4496.57 | G16: 82 | H16: =F16/G16 -> 54.83622 | I16: =C16-F16 -> 1835.12 | J16: 92 | K16: 46 | L16: 247 | N16: 39278 | P16: 45879.09 | Q16: 6601.09 | R16: 6908.98 | S16: 14.39
A17: =A16+1 -> 45997 | B17: =C17*6 -> 51438.54 | C17: 8573.09 | D17: 395 | E17: =C17/D17 -> 21.704025 | F17: 5844.07 | G17: 117 | H17: =F17/G17 -> 49.949316 | I17: =C17-F17 -> 2729.02 | J17: 84 | K17: 41 | L17: 269 | N17: 71313.79 | P17: 75896.56 | Q17: 4582.77 | R17: 4590.37 | S17: 6.04
A18: =A17+1 -> 45998 | B18: =C18*6 -> 43127.76 | C18: 7187.96 | D18: 328 | E18: =C18/D18 -> 21.914512 | F18: 4621.32 | G18: 116 | H18: =F18/G18 -> 39.838966 | I18: =C18-F18 -> 2566.64 | J18: 97 | K18: 40 | L18: 228 | N18: 60198.97 | P18: 63673.17 | Q18: 3474.2 | R18: 3540.79 | S18: 5.46
A19: =A18+1 -> 45999 | B19: =C19*6 -> 41197.92 | C19: 6866.32 | D19: 318 | E19: =C19/D19 -> 21.592201 | F19: 4920.58 | G19: 114 | H19: =F19/G19 -> 43.162982 | I19: =C19-F19 -> 1945.74 | J19: 84 | K19: 28 | L19: 204 | N19: 61172.31 | P19: 65848.11 | Q19: 4675.8 | R19: 4676.05 | S19: 7.1
A20: =A19+1 -> 46000 | B20: =C20*6 -> 43665 | C20: 7277.5 | D20: 327 | E20: =C20/D20 -> 22.255352 | F20: 5750.19 | G20: 118 | H20: =F20/G20 -> 48.730424 | I20: =C20-F20 -> 1527.31 | J20: 107 | K20: 33 | L20: 205 | N20: 51721.14 | P20: 53084.72 | Q20: 1363.58 | R20: 1372.06 | S20: 2.57
A21: =A20+1 -> 46001 | B21: =C21*6 -> 65058.48 | C21: 10843.08 | D21: 613 | E21: =C21/D21 -> 17.688548 | F21: 9061.2 | G21: 354 | H21: =F21/G21 -> 25.59661 | I21: =C21-F21 -> 1781.88 | J21: 327 | K21: 270 | L21: 449 | N21: 67250.11 | P21: 68784.34 | Q21: 1534.23 | R21: 1532.1 | S21: 2.23
A22: =A21+1 -> 46002 | B22: =C22*6 -> 32403 | C22: 5400.5 | D22: 342 | E22: =C22/D22 -> 15.790936 | F22: 4079.44 | G22: 150 | H22: =F22/G22 -> 27.196267 | I22: =C22-F22 -> 1321.06 | J22: 117 | K22: 89 | L22: 229 | N22: 61966.63 | P22: 63009.14 | Q22: 1042.51 | R22: 1068.93 | S22: 1.65
A23: =A22+1 -> 46003 | B23: =C23*6 -> 33351.18 | C23: 5558.53 | D23: 276 | E23: =C23/D23 -> 20.139601 | F23: 5064.8 | G23: 82 | H23: =F23/G23 -> 61.765854 | I23: =C23-F23 -> 493.73 | J23: 87 | K23: 33 | L23: 197 | N23: 50746.21 | P23: 50865.7 | Q23: 119.49 | R23: 32.93 | S23: 0.23
A24: =A23+1 -> 46004 | B24: =C24*6 -> 32402.28 | C24: 5400.38 | D24: 265 | E24: =C24/D24 -> 20.378792 | F24: 2529 | G24: 74 | H24: =F24/G24 -> 34.175676 | I24: =C24-F24 -> 2871.38 | J24: 101 | K24: 33 | L24: 169 | N24: 31041.14 | P24: 32563.86 | Q24: 1522.72 | R24: 1530.62 | S24: 4.68
... A42: =A41+1 -> 46022 | B42: =C42*6 -> 24330.6 | C42: 4055.1 | D42: 367 | E42: =C42/D42 -> 11.049319 | F42: 3432.25 | G42: 227 | H42: =F42/G42 -> 15.120044 | I42: =C42-F42 -> 622.85 | J42: 217 | K42: 180 | L42: 325 | N42: 34295.9 | P42: 36517.05 | Q42: 2221.15 | R42: 2221.15 | S42: 6.08
A43: TOTAL | B43: =sum(B12:B42) -> 1177954.7 | C43: =sum(C12:C42) -> 196325.78 | D43: =sum(D12:D42) -> 10781 | E43: =B43/D43 -> 109.2621 | F43: =sum(F12:F42)*6 -> 931567.5 | G43: =sum(G12:G42) -> 3989 | H43: =F43/G43 -> 233.53409 | I43: =B43-F43 -> 246387.18 | J43: =sum(J12:J42) -> 4772 | K43: =sum(K12:K42) -> 2312 | L43: =sum(L12:L42) -> 7430 | M43: =SUM(M12:M42) -> 0 | N43: =SUM(N12:N42)*6 -> 9382561.6 | O43: =SUM(O12:O42) -> 0 | P43: =SUM(P12:P42)*6 -> 9639402.8 | Q43: =SUM(Q12:Q42)*6 -> 256841.22 | R43: =SUM(R12:R42)*6 -> 260123.94 | S43: =Q43/P43 -> 0.026644931
C44: DEPOSITOS | D44: QTD. DEP | E44: TICKET DEPOSITOS | F44: SAQUES | G44: QTD. SAQUE | H44: TICKET SAQUE | I44: NETCASH LIQUIDO | J44: CONVERSÃO FTD | M44: REDEP. | N44: INATIVOS | O44: CHURN | P44: LTV | Q44: TX. GETWAY | R44: PLAT. FEE 15% | S44: MEDIA %
I45: =I43-Q45 -> 226649.05 | J45: =K43/J43 -> 0.48449288 | N45: =J43-K43 -> 2460 | O45: =N45/J43 -> 0.51550712 | P45: =Q43/K43 -> 111.09049 | Q45: =(C43+F43)*0.0175 -> 19738.132 | R45: =Q43*0.15 -> 38526.183

Sheet NOV 2025
B10: DEPOSITOS | E10: SAQUES | H10: BALANÇO | I10: GERAL
A11: DATA | B11: Total | C11: QTD | D11: Ticket | E11: Total | F11: QTD | G11: Ticket | H11: NETCASH | I11: REGISTROS | J11: FTD | K11: UAP | L11: FTD AMOUNT. | M11: WINS | N11: TURNOVER SPTBS | O11: TURNOVER CASSINO | P11: GGR | Q11: NGR | R11: GGR%
A12: 45962 | B12: 0 | C12: 0 | D12: 0 | E12: 0 | F12: 0 | G12: 0 | H12: =B12-E12 -> 0 | I12: 0 | J12: 0 | K12: 0 | M12: 0 | N12: 0 | O12: 0 | P12: 0 | Q12: 0 | R12: 0
A13: 45963 | B13: 0 | C13: 0 | D13: 0 | E13: 0 | F13: 0 | G13: 0 | H13: =B13-E13 -> 0 | I13: 0 | J13: 0 | K13: 0 | M13: 0 | N13: 0 | O13: 0 | P13: 0 | Q13: 0 | R13: 0
A14: 45964 | B14: 0 | C14: 0 | D14: 0 | E14: 0 | F14: 0 | G14: 0 | H14: =B14-E14 -> 0 | I14: 0 | J14: 0 | K14: 0 | M14: 0 | N14: 0 | O14: 0 | P14: 0 | Q14: 0 | R14: 0
A15: 45965 | B15: 0 | C15: 0 | D15: 0 | E15: 0 | F15: 0 | G15: 0 | H15: =B15-E15 -> 0 | I15: 0 | J15: 0 | K15: 0 | M15: 0 | N15: 0 | O15: 0 | P15: 0 | Q15: 0 | R15: 0
A16: 45966 | B16: 0 | C16: 0 | D16: 0 | E16: 0 | F16: 0 | G16: 0 | H16: =B16-E16 -> 0 | I16: 0 | J16: 0 | K16: 0 | M16: 0 | N16: 0 | O16: 0 | P16: 0 | Q16: 0 | R16: 0
A17: 45967 | B17: 0 | C17: 0 | D17: 0 | E17: 0 | F17: 0 | G17: 0 | H17: =B17-E17 -> 0 | I17: 3 | J17: 0 | K17: 0 | M17: 0 | N17: 0 | O17: 0 | P17: 0 | Q17: 0 | R17: 0
A18: 45968 | B18: 0 | C18: 0 | D18: 0 | E18: 0 | F18: 0 | G18: 0 | H18: =B18-E18 -> 0 | I18: 0 | J18: 0 | K18: 0 | M18: 0 | N18: 0 | O18: 0 | P18: 0 | Q18: 0 | R18: 0
A19: 45969 | B19: 0 | C19: 0 | D19: 0 | E19: 0 | F19: 0 | G19: 0 | H19: =B19-E19 -> 0 | I19: 0 | J19: 0 | K19: 0 | M19: 0 | N19: 0 | O19: 0 | P19: 0 | Q19: 0 | R19: 0
A20: 45970 | B20: 0 | C20: 0 | D20: 0 | E20: 0 | F20: 0 | G20: 0 | H20: =B20-E20 -> 0 | I20: 0 | J20: 0 | K20: 0 | M20: 0 | N20: 0 | O20: 0 | P20: 0 | Q20: 0 | R20: 0
A21: 45971 | B21: 1.62 | C21: 1 | D21: =B21/C21 -> 1.62 | E21: 0 | F21: 0 | G21: 0 | H21: =B21-E21 -> 1.62 | I21: 2 | J21: 1 | K21: 1 | M21: 0.27 | N21: 0 | O21: 1.45 | P21: 1.18 | Q21: 1.18 | R21: =P21/O21 -> 0.8137931
A22: 45972 | B22: 8.08 | C22: 1 | D22: =B22/C22 -> 8.08 | E22: 0 | F22: 0 | G22: 0 | H22: =B22-E22 -> 8.08 | I22: 1 | J22: 1 | K22: 2 | M22: 2.52 | N22: 0 | O22: 5.74 | P22: 3.22 | Q22: 3.22 | R22: =P22/O22 -> 0.56097561
A23: 45973 | B23: 8.16 | C23: 1 | D23: =B23/C23 -> 8.16 | E23: 8.16 | F23: 1 | G23: =E23/F23 -> 8.16 | H23: =B23-E23 -> 0 | I23: 0 | J23: 1 | K23: 1 | M23: 0 | N23: 0 | O23: 0 | P23: 0 | Q23: 0 | R23: 0
A24: 45974 | B24: 757.39 | C24: 24 | D24: =B24/C24 -> 31.557917 | E24: 84.09 | F24: 6 | G24: =E24/F24 -> 14.015 | H24: =B24-E24 -> 673.3 | I24: 63 | J24: 21 | K24: 24 | M24: 662.64 | N24: 0.32 | O24: 836.12 | P24: 173.41 | Q24: 173.41 | R24: =P24/O24 -> 0.20739846
A25: 45975 | B25: 2329 | C25: 132 | D25: =B25/C25 -> 17.643939 | E25: 1160.98 | F25: 34 | G25: =E25/F25 -> 34.146471 | H25: =B25-E25 -> 1168.02 | I25: 149 | J25: 89 | K25: 107 | M25: 12741.91 | N25: 0 | O25: 13494.74 | P25: 752.83 | Q25: 752.83 | R25: =P25/O25 -> 0.055786921
A26: 45976 | B26: 3422.51 | C26: 135 | D26: =B26/C26 -> 25.351926 | E26: 1507.79 | F26: 54 | G26: =E26/F26 -> 27.922037 | H26: =B26-E26 -> 1914.72 | I26: 198 | J26: 61 | K26: 119 | M26: 24479.78 | N26: 0.33 | O26: 25028.3 | P26: 548.85 | Q26: 548.85 | R26: =P26/O26 -> 0.021929176
A27: 45977 | B27: 2143.37 | C27: 121 | D27: =B27/C27 -> 17.713802 | E27: 2339.73 | F27: 61 | G27: =E27/F27 -> 38.35623 | H27: =B27-E27 -> -196.36 | I27: 213 | J27: 41 | K27: 97 | M27: 25368.96 | N27: 0.33 | O27: 25014.45 | P27: -354.18 | Q27: -354.18 | R27: =P27/O27 -> -0.014159016
A28: 45978 | B28: 4068.43 | C28: 135 | D28: =B28/C28 -> 30.136519 | E28: 981.97 | F28: 30 | G28: =E28/F28 -> 32.732333 | H28: =B28-E28 -> 3086.46 | I28: 594 | J28: 45 | K28: 109 | M28: 27429.48 | N28: 0 | O28: 30109.94 | P28: 2680.46 | Q28: 2680.46 | R28: =P28/O28 -> 0.089022429
A29: 45979 | B29: 2695.35 | C29: 142 | D29: =B29/C29 -> 18.981338 | E29: 1714.28 | F29: 29 | G29: =E29/F29 -> 59.113103 | H29: =B29-E29 -> 981.07 | I29: 1834 | J29: 51 | K29: 124 | M29: 24154.73 | N29: 0 | O29: 19441.5 | P29: -4713.23 | Q29: -4713.23 | R29: =P29/O29 -> -0.2424314
A30: 45980 | B30: 12279.56 | C30: 275 | D30: =B30/C30 -> 44.652945 | E30: 5688.93 | F30: 79 | G30: =E30/F30 -> 72.011772 | H30: =B30-E30 -> 6590.63 | I30: 170 | J30: 119 | K30: 202 | M30: 142239.07 | N30: 8.49 | O30: 134164.65 | P30: -8065.93 | Q30: -8065.93 | R30: =P30/O30 -> -0.060119637
A31: 45981 | B31: 5538.09 | C31: 297 | D31: =B31/C31 -> 18.646768 | E31: 5301.62 | F31: 74 | G31: =E31/F31 -> 71.643514 | H31: =B31-E31 -> 236.47 | I31: 246 | J31: 106 | K31: 238 | M31: 41833.7 | N31: 30.15 | O31: 43983.77 | P31: 2173.01 | Q31: 2173.01 | R31: =P31/O31 -> 0.049404815
A32: 45982 | B32: 7116.61 | C32: 280 | D32: =B32/C32 -> 25.416464 | E32: 3770.01 | F32: 63 | G32: =E32/F32 -> 59.841429 | H32: =B32-E32 -> 3346.6 | I32: 165 | J32: 86 | K32: 250 | M32: 103868.96 | N32: 193.69 | O32: 103498.33 | P32: -441.96 | Q32: -441.96 | R32: =P32/O32 -> -0.0042702138
A33: 45983 | B33: 6364.03 | C33: 272 | D33: =B33/C33 -> 23.397169 | E33: 7828.72 | F33: 95 | G33: =E33/F33 -> 82.407579 | H33: =B33-E33 -> -1464.69 | I33: 153 | J33: 72 | K33: 219 | M33: 53234.61 | N33: 85.21 | O33: 51964.26 | P33: -1303.91 | Q33: -1303.91 | R33: =P33/O33 -> -0.025092439
A34: 45984 | B34: 6019.5 | C34: 280 | D34: =B34/C34 -> 21.498214 | E34: 4421.31 | F34: 75 | G34: =E34/F34 -> 58.9508 | H34: =B34-E34 -> 1598.19 | I34: 164 | J34: 74 | K34: 218 | M34: 50556.74 | N34: 39.46 | O34: 52435.27 | P34: 1915.49 | Q34: 1915.49 | R34: =P34/O34 -> 0.036530564
A35: 45985 | B35: 5127.05 | C35: 238 | D35: =B35/C35 -> 21.542227 | E35: 3960.47 | F35: 72 | G35: =E35/F35 -> 55.006528 | H35: =B35-E35 -> 1166.58 | I35: 110 | J35: 58 | K35: 193 | M35: 67579.47 | N35: 35.39 | O35: 77457.58 | P35: 9902.36 | Q35: 9902.36 | R35: =P35/O35 -> 0.12784236
A36: 45986 | B36: 3615.65 | C36: 228 | D36: =B36/C36 -> 15.858114 | E36: 3369.64 | F36: 76 | G36: 0 | H36: =B36-E36 -> 246.01 | I36: 101 | J36: 46 | K36: 189 | M36: 39380.5 | N36: 43.01 | O36: 37689.22 | P36: -1661.22 | Q36: -1661.22 | R36: =P36/O36 -> -0.044076794
A37: 45987 | B37: 6152.03 | C37: 260 | D37: =B37/C37 -> 23.661654 | E37: 6258.37 | F37: 82 | G37: =E37/F37 -> 76.321585 | H37: =B37-E37 -> -106.34 | I37: 150 | J37: 66 | K37: 227 | M37: 68537.56 | N37: 237.57 | O37: 75941.24 | P37: 7392.28 | Q37: 7392.28 | R37: =P37/O37 -> 0.097342103
A38: 45988 | B38: 7434.24 | C38: 274 | D38: =B38/C38 -> 27.132263 | E38: 5677.77 | F38: 87 | G38: =E38/F38 -> 65.261724 | H38: =B38-E38 -> 1756.47 | I38: 114 | J38: 49 | K38: 221 | M38: 84041.73 | N38: 117.55 | O38: 83405.64 | P38: -677.83 | Q38: -677.83 | R38: =P38/O38 -> -0.0081269084
A39: 45989 | B39: 7383.33 | C39: 286 | D39: =B39/C39 -> 25.815839 | E39: 4875.26 | F39: 84 | G39: =E39/F39 -> 58.03881 | H39: =B39-E39 -> 2508.07 | I39: 120 | J39: 56 | K39: 210 | M39: 62695.32 | N39: 21.13 | O39: 67587.68 | P39: 4913.2 | Q39: 4913.2 | R39: =P39/O39 -> 0.072693722
A40: 45990 | B40: 6801.93 | C40: 358 | D40: =B40/C40 -> 18.999804 | E40: 5554.01 | F40: 108 | G40: =E40/F40 -> 51.426019 | H40: =B40-E40 -> 1247.92 | I40: 122 | J40: 60 | K40: 252 | M40: 43800.44 | N40: 181.25 | O40: 44385.37 | P40: 664.74 | Q40: 664.74 | R40: =P40/O40 -> 0.014976556
A41: 45991 | B41: 5848.8 | C41: 275 | D41: =B41/C41 -> 21.268364 | E41: 3281.94 | F41: 68 | G41: =E41/F41 -> 48.263824 | H41: =B41-E41 -> 2566.86 | I41: 96 | J41: 45 | K41: 187 | M41: 39022.52 | N41: 46.78 | O41: 41583.82 | P41: 2565.52 | Q41: 2565.52 | R41: =P41/O41 -> 0.06169515
A43: TOTAL | B43: 590870.05 | C43: =sum(C12:C42) -> 4015 | D43: =B43/C43 -> 147.16564 | E43: 427478.16 | F43: =sum(F12:F42) -> 1178 | G43: =E43/F43 -> 362.88469 | H43: =B43-E43 -> 163391.89 | I43: =sum(I12:I42) -> 4768 | J43: =sum(J12:J42) -> 1148 | K43: =sum(K12:K42) -> 3190 | L43: =SUM(L12:L42) -> 0 | M43: =SUM(M12:M42)*6 -> 5469785.5 | N43: =SUM(N12:N42)*6 -> 6243.96 | O43: =SUM(O12:O42)*6 -> 5568174.4 | P43: =SUM(P12:P42)*6 -> 98809.74 | Q43: =SUM(Q12:Q42)*6 -> 98809.74 | R43: =P43/O43 -> 0.017745446
B44: DEPOSITOS | C44: QTD. DEP | D44: TICKET DEPOSITOS | E44: SAQUES | F44: QTD. SAQUE | G44: TICKET SAQUE | H44: NETCASH LIQUIDO | I44: CONVERSÃO FTD | K44: UAP | L44: REDEP. | M44: INATIVOS | N44: CHURN | O44: LTV | P44: TX. GETWAY | Q44: PLAT. FEE 15% | R44: MEDIA %
H45: =H43-P45 -> 144246.94 | I45: =J43/I43 -> 0.24077181 | M45: =I43-J43 -> 3620 | N45: =M45/I43 -> 0.75922819 | O45: =P43/J43 -> 86.071202 | P45: =(B43+E43)*0.0188 -> 19144.946 | Q45: =P43*0.18 -> 17785.753

Sheet DEZEMBRO
A9: TERMÔMETRO
B10: DEPOSITOS | E10: SAQUES | H10: BALANÇO | I10: GERAL | R10: Sportsbook | AA10: Cassino
A11: DATA | B11: Total | C11: QTD | D11: Ticket | E11: Total | F11: QTD | G11: Ticket | H11: Netcash Real | I11: REGISTROS | J11: FTD | K11: UAP | L11: UAP BASE | M11: TURNOVER | N11: GGR | O11: NGR | P11: GGR% | R11: UAP | S11: Número de Bets | T11: TURNOVER | U11: Média de Aposta por Usuário | V11: Ticket | W11: GGR | X11: NGR | Y11: GGR% | AA11: UAP | AB11: Número de Giros | AC11: TURNOVER | AD11: Vezes de start nos jogos por usuário | AE11: Ticket | AF11: GGR | AG11: NGR | AH11: GGR% | AK11: TICKET MÉDIO | AL11: NOVOS CLIENTES | AM11: CLIENTES INATIVOS | AN11: FTD (Priméiro depósito) | AO11: UAP (Clientes Recorrentes) | AP11: CHURN (taxa de Inativos) | AQ11: ARPUR (Receita média por usuário) | AR11: CAC. (Custo Aquisição) | AS11: Total Ações | AT11: Total Investido
A12: 45261 | B12: =33387.63*5.37 -> 179291.57 | C12: 3585 | D12: =B12/C12 -> 50.011596 | E12: =27143.35*5.37 -> 145759.79 | F12: 575 | G12: =E12/F12 -> 253.49529 | H12: =B12-E12 -> 33531.784 | I12: 1063 | J12: 740 | K12: 2306 | L12: =K12-J12 -> 1566 | M12: =216660*5.37 -> 1163464.2 | N12: =194.57*5.37 -> 1044.8409 | O12: =N12 -> 1044.8409 | P12: =O12/M12 -> 0.00089804302 | R12: 64 | S12: 297 | T12: =3491.31*5.37 -> 18748.335 | U12: =S12/R12 -> 4.640625 | V12: =T12/S12 -> 63.125706 | W12: =104.24*5.37 -> 559.7688 | X12: =W12 -> 559.7688 | Y12: =X12/T12 -> 0.029856988 | AA12: 2277 | AB12: 630663 | AC12: =213168.93*5.37 -> 1144717.2 | AD12: =AB12/AA12 -> 276.97101 | AE12: =AC12/AB12 -> 1.8151012 | AF12: =90.33*5.37 -> 485.0721 | AG12: =AF12 -> 485.0721 | AH12: =AF12/AC12 -> 0.00042374843 | AK12: =D43 -> 51.939878 | AL12: =I43 -> 25804 | AM12: =AL12-AN12 -> 9111 | AN12: =J43 -> 16693 | AO12: =K43 -> 1823.2903 | AP12: =AM12/AL12 -> 0.35308479 | AQ12: =N43/K43 -> 458.285 | AR12: =AS12/AN12 -> #REF! | AS12: ='CUSTOS 2023'!AS5 -> #REF! | AT12: ='CUSTOS 2023'!AS3 -> #REF!
A13: 45262 | B13: 155298.5 | C13: 3423 | D13: =B13/C13 -> 45.369121 | E13: 176433.24 | F13: 630 | G13: =E13/F13 -> 280.05276 | H13: =B13-E13 -> -21134.74 | I13: 949 | J13: =712-31 -> 681 | K13: 2295 | L13: =K13-J13 -> 1614 | M13: 2573500.6 | N13: -277420.18 | O13: =N13 -> -277420.18 | P13: =O13/M13 -> -0.10779876 | R13: 103 | S13: 391 | T13: 23109.05 | U13: =S13/R13 -> 3.7961165 | V13: =T13/S13 -> 59.10243 | W13: -2222.96 | X13: =W13 -> -2222.96 | Y13: =X13/T13 -> -0.096194348 | AA13: 2235 | AB13: 661167 | AC13: 2550391.6 | AD13: =AB13/AA13 -> 295.82416 | AE13: =AC13/AB13 -> 3.8574091 | AF13: -275197.22 | AG13: =AF13 -> -275197.22 | AH13: =AF13/AC13 -> -0.10790391
A14: 45263 | B14: 119493.82 | C14: 2655 | D14: =B14/C14 -> 45.007089 | E14: 133247.37 | F14: 468 | G14: =E14/F14 -> 284.7166 | H14: =B14-E14 -> -13753.55 | I14: 588 | J14: 434 | K14: 1801 | L14: =K14-J14 -> 1367 | M14: 2917958.2 | N14: 74918.37 | O14: =N14 -> 74918.37 | P14: =O14/M14 -> 0.025674929 | R14: 122 | S14: 506 | T14: 18822.86 | U14: =S14/R14 -> 4.147541 | V14: =T14/S14 -> 37.199328 | W14: 1196.46 | X14: =W14 -> 1196.46 | Y14: =X14/T14 -> 0.063564198 | AA14: 1735 | AB14: 535573 | AC14: 2899135.3 | AD14: =AB14/AA14 -> 308.68761 | AE14: =AC14/AB14 -> 5.4131469 | AF14: 73721.91 | AG14: =AF14 -> 73721.91 | AH14: =AF14/AC14 -> 0.02542893 | AK14: NETCASH | AL14: RETENÇÃO STARS
A15: 45264 | B15: 125915.53 | C15: 2416 | D15: =B15/C15 -> 52.117355 | E15: 111151.31 | F15: 449 | G15: =E15/F15 -> 247.55303 | H15: =B15-E15 -> 14764.22 | I15: 577 | J15: 395 | K15: 1634 | L15: =K15-J15 -> 1239 | M15: 1085732.2 | N15: 20537.86 | O15: =N15 -> 20537.86 | P15: =O15/M15 -> 0.018916138 | R15: 54 | S15: 261 | T15: 11140.33 | U15: =S15/R15 -> 4.8333333 | V15: =T15/S15 -> 42.683257 | W15: -747 | X15: =W15 -> -747 | Y15: =X15/T15 -> -0.067053669 | AA15: 1602 | AB15: 469900 | AC15: 1074591.9 | AD15: =AB15/AA15 -> 293.32085 | AE15: =AC15/AB15 -> 2.2868522 | AF15: 21285.2 | AG15: =AF15 -> 21285.2 | AH15: =AF15/AC15 -> 0.019807707 | AK15: =B43-E43 -> 689268.06 | AL15: =(B43+E43)*0.0143 -> 120267.1
A16: 45265 | B16: 131848.64 | C16: 2746 | D16: =B16/C16 -> 48.0148 | E16: 134904.2 | F16: 498 | G16: =E16/F16 -> 270.89197 | H16: =B16-E16 -> -3055.56 | I16: 530 | J16: 355 | K16: 1692 | L16: =K16-J16 -> 1337 | M16: 858783.97 | N16: 67758.21 | O16: =N16 -> 67758.21 | P16: =O16/M16 -> 0.07890018 | R16: 65 | S16: 286 | T16: 15156.7 | U16: =S16/R16 -> 4.4 | V16: =T16/S16 -> 52.995455 | W16: 1175.58 | X16: =W16 -> 1175.58 | Y16: =X16/T16 -> 0.077561738 | AA16: 1654 | AB16: 489487 | AC16: 843627.26 | AD16: =AB16/AA16 -> 295.94135 | AE16: =AC16/AB16 -> 1.7234927 | AF16: 66582.26 | AG16: =AF16 -> 66582.26 | AH16: =AF16/AC16 -> 0.078923789
A17: 45266 | B17: 128534.64 | C17: 3009 | D17: =B17/C17 -> 42.71673 | E17: 88810.38 | F17: 503 | G17: =E17/F17 -> 176.56139 | H17: =B17-E17 -> 39724.26 | I17: 703 | J17: 436 | K17: 1868 | L17: =K17-J17 -> 1432 | M17: 967983.01 | N17: 34681.67 | O17: =N17 -> 34681.67 | P17: =O17/M17 -> 0.0358288 | R17: 190 | S17: 716 | T17: 26360.33 | U17: =S17/R17 -> 3.7684211 | V17: =T17/S17 -> 36.816103 | W17: 4495.92 | X17: =W17 -> 4495.92 | Y17: =X17/T17 -> 0.17055629 | AA17: 1749 | AB17: 491192 | AC17: 941622.68 | AD17: =AB17/AA17 -> 280.84162 | AE17: =AC17/AB17 -> 1.9170155 | AF17: 30185.75 | AG17: =AF17 -> 30185.75 | AH17: =AF17/AC17 -> 0.032057161
A18: 45267 | B18: 145783.42 | C18: 2995 | D18: =B18/C18 -> 48.675599 | E18: 97841.25 | F18: 520 | G18: =E18/F18 -> 188.15625 | H18: =B18-E18 -> 47942.17 | I18: 814 | J18: 499 | K18: 1933 | L18: =K18-J18 -> 1434 | M18: 860362.14 | N18: 32495.19 | O18: =N18 -> 32495.19 | P18: =O18/M18 -> 0.0377692 | R18: 114 | S18: 373 | T18: 7996.63 | U18: =S18/R18 -> 3.2719298 | V18: =T18/S18 -> 21.438686 | W18: 696.82 | X18: =W18 -> 696.82 | Y18: =X18/T18 -> 0.087139207 | AA18: 1871 | AB18: 513660 | AC18: 852365.91 | AD18: =AB18/AA18 -> 274.53768 | AE18: =AC18/AB18 -> 1.6593971 | AF18: 31798.37 | AG18: =AF18 -> 31798.37 | AH18: =AF18/AC18 -> 0.037306009
A19: 45268 | B19: 146450.32 | C19: 2763 | D19: =B19/C19 -> 53.004097 | E19: 183876.71 | F19: 495 | G19: =E19/F19 -> 371.4681 | H19: =B19-E19 -> -37426.39 | I19: 650 | J19: 400 | K19: 1732 | L19: =K19-J19 -> 1332 | M19: 1171742.2 | N19: 14661.7 | O19: =N19 -> 14661.7 | P19: =O19/M19 -> 0.012512735 | R19: 60 | S19: 282 | T19: 11241.54 | U19: =S19/R19 -> 4.7 | V19: =T19/S19 -> 39.863617 | W19: 84.91 | X19: =W19 -> 84.91 | Y19: =X19/T19 -> 0.0075532356 | AA19: 1696 | AB19: 504169 | AC19: 1160500.7 | AD19: =AB19/AA19 -> 297.26946 | AE19: =AC19/AB19 -> 2.3018089 | AF19: 14576.79 | AG19: =AF19 -> 14576.79 | AH19: =AF19/AC19 -> 0.012560777
A20: 45269 | B20: 187564.39 | C20: 3146 | D20: =B20/C20 -> 59.619959 | E20: 141817.91 | F20: 483 | G20: =E20/F20 -> 293.61886 | H20: =B20-E20 -> 45746.48 | I20: 729 | J20: 559 | K20: 1904 | L20: =K20-J20 -> 1345 | M20: 1210098.1 | N20: 36626.36 | O20: =N20 -> 36626.36 | P20: =O20/M20 -> 0.030267264 | R20: 78 | S20: 333 | T20: 10407.8 | U20: =S20/R20 -> 4.2692308 | V20: =T20/S20 -> 31.254655 | W20: 543.28 | X20: =W20 -> 543.28 | Y20: =X20/T20 -> 0.052199312 | AA20: 1863 | AB20: 539434 | AC20: 1199690.3 | AD20: =AB20/AA20 -> 289.55126 | AE20: =AC20/AB20 -> 2.2239798 | AF20: 36083.08 | AG20: =AF20 -> 36083.08 | AH20: =AF20/AC20 -> 0.030076995
A21: 45270 | B21: 106983.99 | C21: 2293 | D21: =B21/C21 -> 46.656777 | E21: 93920.49 | F21: 403 | G21: =E21/F21 -> 233.05333 | H21: =B21-E21 -> 13063.5 | I21: 456 | J21: 302 | K21: 1432 | L21: =K21-J21 -> 1130 | M21: 888147.45 | N21: 33638.67 | O21: =N21 -> 33638.67 | P21: =O21/M21 -> 0.037875096 | R21: 54 | S21: 255 | T21: 17218.62 | U21: =S21/R21 -> 4.7222222 | V21: =T21/S21 -> 67.524 | W21: -576.89 | X21: =W21 -> -576.89 | Y21: =X21/T21 -> -0.033503846 | AA21: 1400 | AB21: 433888 | AC21: 870928.83 | AD21: =AB21/AA21 -> 309.92 | AE21: =AC21/AB21 -> 2.0072665 | AF21: 34215.56 | AG21: =AF21 -> 34215.56 | AH21: =AF21/AC21 -> 0.039286287
A22: 45271 | B22: 135274.02 | C22: 2339 | D22: =B22/C22 -> 57.834126 | E22: 103078.61 | F22: 375 | G22: =E22/F22 -> 274.87629 | H22: =B22-E22 -> 32195.41 | I22: 379 | J22: 252 | K22: 1376 | L22: =K22-J22 -> 1124 | M22: 885881.54 | N22: 57195.45 | O22: =N22 -> 57195.45 | P22: =O22/M22 -> 0.064563316 | R22: 43 | S22: 139 | T22: 6014.93 | U22: =S22/R22 -> 3.2325581 | V22: =T22/S22 -> 43.272878 | W22: 160.91 | X22: =W22 -> 160.91 | Y22: =X22/T22 -> 0.026751766 | AA22: 1349 | AB22: 398849 | AC22: 879866.61 | AD22: =AB22/AA22 -> 295.66271 | AE22: =AC22/AB22 -> 2.2060143 | AF22: 57034.54 | AG22: =AF22 -> 57034.54 | AH22: =AF22/AC22 -> 0.064821803
A23: 45272 | B23: 154376.91 | C23: 2611 | D23: =B23/C23 -> 59.125588 | E23: 129232.44 | F23: 477 | G23: =E23/F23 -> 270.92755 | H23: =B23-E23 -> 25144.47 | I23: 573 | J23: 369 | K23: 1605 | L23: =K23-J23 -> 1236 | M23: 888844.04 | N23: 15352.99 | O23: =N23 -> 15352.99 | P23: =O23/M23 -> 0.017272985 | R23: 94 | S23: 354 | T23: 57650.66 | U23: =S23/R23 -> 3.7659574 | V23: =T23/S23 -> 162.85497 | W23: 12243.06 | X23: =W23 -> 12243.06 | Y23: =X23/T23 -> 0.21236635 | AA23: 1557 | AB23: 433236 | AC23: 831193.33 | AD23: =AB23/AA23 -> 278.25048 | AE23: =AC23/AB23 -> 1.9185694 | AF23: 3109.93 | AG23: =AF23 -> 3109.93 | AH23: =AF23/AC23 -> 0.0037415242
A24: 45273 | B24: 131886.74 | C24: 2508 | D24: =B24/C24 -> 52.586419 | E24: 101120.51 | F24: 447 | G24: =E24/F24 -> 226.22038 | H24: =B24-E24 -> 30766.23 | I24: 655 | J24: 439 | K24: 1638 | L24: =K24-J24 -> 1199 | M24: 1189264.9 | N24: 42484.56 | O24: =N24 -> 42484.56 | P24: =O24/M24 -> 0.035723378 | R24: 91 | S24: 375 | T24: 58008.02 | U24: =S24/R24 -> 4.1208791 | V24: =T24/S24 -> 154.68805 | W24: 5175.31 | X24: =W24 -> 5175.31 | Y24: =X24/T24 -> 0.089217146 | AA24: 1583 | AB24: 444606 | AC24: 1131256.9 | AD24: =AB24/AA24 -> 280.86292 | AE24: =AC24/AB24 -> 2.5444031 | AF24: 37309.25 | AG24: =AF24 -> 37309.25 | AH24: =AF24/AC24 -> 0.032980351
A25: 45274 | B25: 133448.64 | C25: 2506 | D25: =B25/C25 -> 53.251652 | E25: 106357.82 | F25: 445 | G25: =E25/F25 -> 239.00634 | H25: =B25-E25 -> 27090.82 | I25: 622 | J25: 394 | K25: 1579 | L25: =K25-J25 -> 1185 | M25: 993111.09 | N25: 30506.36 | O25: =N25 -> 30506.36 | P25: =O25/M25 -> 0.030717973 | R25: 59 | S25: 315 | T25: 73235.88 | U25: =S25/R25 -> 5.3389831 | V25: =T25/S25 -> 232.49486 | W25: 2400.16 | X25: =W25 -> 2400.16 | Y25: =X25/T25 -> 0.032773007 | AA25: 1541 | AB25: 474608 | AC25: 919875.21 | AD25: =AB25/AA25 -> 307.98702 | AE25: =AC25/AB25 -> 1.9381789 | AF25: 28106.2 | AG25: =AF25 -> 28106.2 | AH25: =AF25/AC25 -> 0.030554362
A26: 45275 | B26: 135367.2 | C26: 2504 | D26: =B26/C26 -> 54.060383 | E26: 104060.7 | F26: 436 | G26: =E26/F26 -> 238.67133 | H26: =B26-E26 -> 31306.5 | I26: 587 | J26: 408 | K26: 1540 | L26: =K26-J26 -> 1132 | M26: 940311.27 | N26: 51918.64 | O26: =N26 -> 51918.64 | P26: =O26/M26 -> 0.055214312 | R26: 54 | S26: 266 | T26: 83169.94 | U26: =S26/R26 -> 4.9259259 | V26: =T26/S26 -> 312.66895 | W26: 16257.81 | X26: =W26 -> 16257.81 | Y26: =X26/T26 -> 0.195477 | AA26: 1514 | AB26: 438572 | AC26: 857141.33 | AD26: =AB26/AA26 -> 289.67768 | AE26: =AC26/AB26 -> 1.9543914 | AF26: 35660.83 | AG26: =AF26 -> 35660.83 | AH26: =AF26/AC26 -> 0.041604376
A27: 45276 | B27: 123656.44 | C27: 2301 | D27: =B27/C27 -> 53.740304 | E27: 86153.1 | F27: 401 | G27: =E27/F27 -> 214.84564 | H27: =B27-E27 -> 37503.34 | I27: 379 | J27: 203 | K27: 1486 | L27: =K27-J27 -> 1283 | M27: 1005762.1 | N27: 33580.81 | O27: =N27 -> 33580.81 | P27: =O27/M27 -> 0.033388422 | R27: 66 | S27: 305 | T27: 68651.87 | U27: =S27/R27 -> 4.6212121 | V27: =T27/S27 -> 225.0881 | W27: -1804.68 | X27: =W27 -> -1804.68 | Y27: =X27/T27 -> -0.026287412 | AA27: 1445 | AB27: 445255 | AC27: 937110.25 | AD27: =AB27/AA27 -> 308.13495 | AE27: =AC27/AB27 -> 2.1046597 | AF27: 35385.49 | AG27: =AF27 -> 35385.49 | AH27: =AF27/AC27 -> 0.037760221
... A42: 45291 | B42: 149860.84 | C42: 2867 | D42: =B42/C42 -> 52.270959 | E42: 123328 | F42: 507 | G42: =E42/F42 -> 243.25049 | H42: =B42-E42 -> 26532.84 | I42: 1184 | J42: 724 | K42: 2092 | L42: =K42-J42 -> 1368 | M42: 1155114.9 | N42: 26681.48 | O42: =N42 -> 26681.48 | P42: =O42/M42 -> 0.023098551 | R42: 83 | S42: 287 | T42: 100912.81 | U42: =S42/R42 -> 3.4578313 | V42: =T42/S42 -> 351.61258 | W42: -390.18 | X42: =W42 -> -390.18 | Y42: =X42/T42 -> -0.0038665061 | AA42: 2049 | AB42: 586551 | AC42: 1054202.1 | AD42: =AB42/AA42 -> 286.26208 | AE42: =AC42/AB42 -> 1.7972897 | AF42: 27071.66 | AG42: =AF42 -> 27071.66 | AH42: =AF42/AC42 -> 0.025679763
A43: TOTAL | B43: =SUM(B12:B42) -> 4549777.5 | C43: =SUM(C11:C42) -> 87597 | D43: =B43/C43 -> 51.939878 | E43: =SUM(E12:E42) -> 3860509.4 | F43: =SUM(F12:F42) -> 15296 | G43: =E43/F43 -> 252.38686 | H43: =B43-E43 -> 689268.06 | I43: =SUM(I12:I42) -> 25804 | J43: =SUM(J12:J42) -> 16693 | K43: =AVERAGE(K12:K42) -> 1823.2903 | L43: =AVERAGE(L12:L42) -> 1284.8065 | M43: =SUM(M12:M41) -> 34484861 | N43: =SUM(N12:N42) -> 835586.6 | O43: =AVERAGE(O12:O42) -> 26954.406 | P43: =N43/M43 -> 0.024230534 | R43: =SUM(R11:R42) -> 2544 | S43: =SUM(S11:S42) -> 10388 | T43: =SUM(T12:T42) -> 1567045.5 | U43: =S43/R43 -> 4.0833333 | V43: =T43/S43 -> 150.85151 | W43: =SUM(W12:W42) -> 91661.589 | X43: =SUM(X12:X41) -> 92051.769 | Y43: =W43/T43 -> 0.058493254 | AA43: =SUM(AA12:AA42) -> 55125 | AB43: =SUM(AB12:AB42) -> 15453562 | AC43: =SUM(AC12:AC42) -> 34072932 | AD43: =AVERAGE(AD12:AD40) -> 281.70743 | AE43: =AC43/AB43 -> 2.2048594 | AF43: =SUM(AF12:AF42) -> 743924.92 | AG43: =SUM(AG12:AG41) -> 716853.26 | AH43: =AG43/AC43 -> 0.02103879
A44: NETCASH BRUTO | B44: DEPOSITOS | C44: QTD. DEP | D44: TICKET DEP. | E44: SAQUES | F44: QTD. SAQ | G44: TICKET SAQ. | H44: NETCASH REAL | I44: CONVERSÃO FTD | K44: MEDIA UAP | L44: BASE UAP | M44: TURNOVER | N44: GGR TOTAL | O44: MEDIA GGR | P44: MEDIA % | R44: LTV Sportingbook | S44: =V43*U43*1 -> 615.977 | AA44: LTV Cassino | AB44: =AB45*AD43*1 -> 621.12529
A45: =B43-E43+'CUSTOS 2023'!AS94+'CUSTOS 2023'!AS66-'CUSTOS 2023'!AS80 -> #REF! | I45: =J43/I43 -> 0.64691521 | R45: TICKET MÉDIO Sportingbook | S45: =V43 -> 150.85151 | AA45: TICKET MÉDIO Cassino | AB45: =AE43 -> 2.2048594

Sheet NOVEMBRO
A9: TERMÔMETRO
B10: DEPOSITOS | E10: SAQUES | I10: GERAL | R10: Sportsbook | AA10: Cassino
A11: DATA | B11: Total | C11: QTD | D11: Ticket | E11: Total | F11: QTD | G11: Ticket | H11: Netcash Real | I11: REGISTROS | J11: FTD | K11: UAP | L11: UAP BASE | M11: TURNOVER | N11: GGR | O11: NGR | P11: GGR% | R11: UAP | S11: Número de Bets | T11: TURNOVER | U11: Média de Aposta por Usuário | V11: Ticket | W11: GGR | X11: NGR | Y11: GGR% | AA11: UAP | AB11: Número de Giros | AC11: TURNOVER | AD11: Vezes de start nos jogos por usuário | AE11: Ticket | AF11: GGR | AG11: NGR | AH11: GGR% | AK11: TICKET MÉDIO | AL11: NOVOS CLIENTES | AM11: CLIENTES INATIVOS | AN11: FTD (Priméiro depósito) | AO11: UAP (Clientes Recorrentes) | AP11: CHURN (taxa de Inativos) | AQ11: ARPUR (Receita média por usuário) | AR11: CAC. (Custo Aquisição) | AS11: Total Ações | AT11: Total Investido
A12: 45231 | B12: 124242.92 | C12: 2255 | D12: =B12/C12 -> 55.096639 | E12: 80719.97 | F12: 405 | G12: =E12/F12 -> 199.30857 | H12: =B12-E12 -> 43522.95 | I12: 749 | J12: 510 | K12: 1501 | L12: =K12-J12 -> 991 | M12: 679550.71 | N12: =W12+AF12 -> 33894.06 | O12: =N12 -> 33894.06 | P12: =O12/M12 -> 0.049877161 | R12: 114 | S12: 397 | T12: 25236.27 | U12: =S12/R12 -> 3.4824561 | V12: =T12/S12 -> 63.567431 | W12: -4311.72 | X12: =W12 -> -4311.72 | Y12: =X12/T12 -> -0.17085409 | AA12: 1428 | AB12: 396731 | AC12: 654314.26 | AD12: =AB12/AA12 -> 277.82283 | AE12: =AC12/AB12 -> 1.6492643 | AF12: 38205.78 | AG12: =AF12 -> 38205.78 | AH12: =AF12/AC12 -> 0.058390566 | AK12: =D42 -> 52.770186 | AL12: =I42 -> 21408 | AM12: =AL12-AN12 -> 6562 | AN12: =J42 -> 14846 | AO12: =K42 -> 1666.4333 | AP12: =AM12/AL12 -> 0.30652093 | AQ12: =N42/K42 -> 536.44 | AR12: =AS12/AN12 -> #REF! | AS12: ='CUSTOS 2023'!AN5 -> #REF! | AT12: ='CUSTOS 2023'!AN3 -> #REF!
A13: 45232 | B13: 101923.32 | C13: 2019 | D13: =B13/C13 -> 50.48208 | E13: 79407.03 | F13: 366 | G13: =E13/F13 -> 216.9591 | H13: =B13-E13 -> 22516.29 | I13: 477 | J13: 351 | K13: 1346 | L13: =K13-J13 -> 995 | M13: 772747.23 | N13: =W13+AF13 -> 19474.84 | O13: =N13 -> 19474.84 | P13: =O13/M13 -> 0.025202083 | R13: 78 | S13: 257 | T13: 35215.68 | U13: =S13/R13 -> 3.2948718 | V13: =T13/S13 -> 137.02599 | W13: -3126.48 | X13: -3791.25 | Y13: =X13/T13 -> -0.10765801 | AA13: 1298 | AB13: 371122 | AC13: 737531.55 | AD13: =AB13/AA13 -> 285.91834 | AE13: =AC13/AB13 -> 1.9873022 | AF13: 22601.32 | AG13: 22601.32 | AH13: =AF13/AC13 -> 0.030644547
A14: 45233 | B14: 80070.16 | C14: 1961 | D14: =B14/C14 -> 40.83129 | E14: 70772.88 | F14: 339 | G14: =E14/F14 -> 208.76956 | H14: =B14-E14 -> 9297.28 | I14: 803 | J14: 441 | K14: 1311 | L14: =K14-J14 -> 870 | M14: 850446.23 | N14: =W14+AF14 -> 17587.48 | O14: =N14 -> 17587.48 | P14: =O14/M14 -> 0.020680296 | R14: 70 | S14: 265 | T14: 24355.6 | U14: =S14/R14 -> 3.7857143 | V14: =T14/S14 -> 91.907925 | W14: 11721.65 | X14: 8439.9 | Y14: =X14/T14 -> 0.34652811 | AA14: 1274 | AB14: 353891 | AC14: 826090.63 | AD14: =AB14/AA14 -> 277.77943 | AE14: =AC14/AB14 -> 2.3343081 | AF14: 5865.83 | AG14: 5865.83 | AH14: =AF14/AC14 -> 0.00710071 | AK14: NETCASH | AL14: RETENÇÃO STARS | AM14: RETIRADAS MÊS
A15: 45234 | B15: 99700 | C15: 2322 | D15: =B15/C15 -> 42.937123 | E15: 67990 | F15: 363 | G15: =E15/F15 -> 187.30028 | H15: =B15-E15 -> 31710 | I15: 481 | J15: 476 | K15: 1456 | L15: =K15-J15 -> 980 | M15: 579669.59 | N15: =W15+AF15 -> 29183.23 | O15: =N15 -> 29183.23 | P15: =O15/M15 -> 0.050344594 | R15: 118 | S15: 455 | T15: 12488.36 | U15: =S15/R15 -> 3.8559322 | V15: =T15/S15 -> 27.446945 | W15: 5211.78 | X15: =W15 -> 5211.78 | Y15: =X15/T15 -> 0.41733102 | AA15: 1378 | AB15: 381650 | AC15: 567181.23 | AD15: =AB15/AA15 -> 276.95936 | AE15: =AC15/AB15 -> 1.4861293 | AF15: 23971.45 | AG15: =AF15 -> 23971.45 | AH15: =AF15/AC15 -> 0.042264181 | AK15: =B42-E42 -> 831255.1 | AL15: =(B42+E42)*0.0143 -> 101004.76 | AM15: =120.84+384.9+150571+75600+100572+109933+101174+60000+100813 -> 699168.74
A16: 45235 | B16: 91946.74 | C16: 1747 | D16: =B16/C16 -> 52.631219 | E16: 61238.83 | F16: 280 | G16: =E16/F16 -> 218.71011 | H16: =B16-E16 -> 30707.91 | I16: 509 | J16: 326 | K16: 1218 | L16: =K16-J16 -> 892 | M16: 580278.48 | N16: -9994.78 | O16: =N16 -> -9994.78 | P16: =O16/M16 -> -0.017224109 | R16: 105 | S16: 386 | T16: 5696.3 | U16: =S16/R16 -> 3.6761905 | V16: =T16/S16 -> 14.757254 | W16: 568 | X16: 562.82 | Y16: =X16/T16 -> 0.098804487 | AA16: 1154 | AB16: 344529 | AC16: 574582.18 | AD16: =AB16/AA16 -> 298.55199 | AE16: =AC16/AB16 -> 1.6677324 | AF16: -10563.52 | AG16: -10655.53 | AH16: =AF16/AC16 -> -0.018384698
A17: 45236 | B17: 127103.41 | C17: 2085 | D17: =B17/C17 -> 60.960868 | E17: 93494.9 | F17: 387 | G17: =E17/F17 -> 241.58889 | H17: =B17-E17 -> 33608.51 | I17: 643 | J17: 413 | K17: 1419 | L17: =K17-J17 -> 1006 | M17: 738229.46 | N17: 49909.16 | O17: =N17 -> 49909.16 | P17: =O17/M17 -> 0.067606568 | R17: 79 | S17: 186 | T17: 6882.18 | U17: =S17/R17 -> 2.3544304 | V17: =T17/S17 -> 37.000968 | W17: 2963.02 | X17: =W17 -> 2963.02 | Y17: =X17/T17 -> 0.43053509 | AA17: 1379 | AB17: 407876 | AC17: 731346.94 | AD17: =AB17/AA17 -> 295.77665 | AE17: =AC17/AB17 -> 1.793062 | AF17: 46946.14 | AG17: =AF17 -> 46946.14 | AH17: =AF17/AC17 -> 0.06419134
A18: 45237 | B18: 189036.76 | C18: 2504 | D18: =B18/C18 -> 75.493914 | E18: 127352.97 | F18: 441 | G18: =E18/F18 -> 288.78224 | H18: =B18-E18 -> 61683.79 | I18: 616 | J18: 424 | K18: 1607 | L18: =K18-J18 -> 1183 | M18: 1137346.1 | N18: 14587.56 | O18: =N18 -> 14587.56 | P18: =O18/M18 -> 0.012825964 | R18: 96 | S18: 286 | T18: 5468.06 | U18: =S18/R18 -> 2.9791667 | V18: =T18/S18 -> 19.119091 | W18: -1309.38 | X18: -1387.68 | Y18: =X18/T18 -> -0.25377922 | AA18: 1554 | AB18: 433994 | AC18: 1131878 | AD18: =AB18/AA18 -> 279.27542 | AE18: =AC18/AB18 -> 2.60805 | AF18: 15896.94 | AG18: 15855.35 | AH18: =AF18/AC18 -> 0.014044746
A19: 45238 | B19: 147042.65 | C19: 2611 | D19: =B19/C19 -> 56.316603 | E19: 143417.43 | F19: 478 | G19: =E19/F19 -> 300.03646 | H19: =B19-E19 -> 3625.22 | I19: 699 | J19: 473 | K19: 1804 | L19: =K19-J19 -> 1331 | M19: 1592581.3 | N19: -35061.04 | O19: =N19 -> -35061.04 | P19: =O19/M19 -> -0.022015228 | R19: 152 | S19: 476 | T19: 50319.12 | U19: =S19/R19 -> 3.1315789 | V19: =T19/S19 -> 105.71244 | W19: 820.47 | X19: =W19 -> 820.47 | Y19: =X19/T19 -> 0.016305333 | AA19: 1719 | AB19: 410063 | AC19: 1542262.1 | AD19: =AB19/AA19 -> 238.54741 | AE19: =AC19/AB19 -> 3.7610371 | AF19: -35881.51 | AG19: =AF19 -> -35881.51 | AH19: =AF19/AC19 -> -0.023265507
A20: 45239 | B20: 141465.27 | C20: 2417 | D20: =B20/C20 -> 58.52928 | E20: 108360.66 | F20: 411 | G20: =E20/F20 -> 263.65124 | H20: =B20-E20 -> 33104.61 | I20: 767 | J20: 428 | K20: 1638 | L20: =K20-J20 -> 1210 | M20: 1312010.7 | N20: 148974.56 | O20: =N20 -> 148974.56 | P20: =O20/M20 -> 0.11354676 | R20: 150 | S20: 464 | T20: 33465.28 | U20: =S20/R20 -> 3.0933333 | V20: =T20/S20 -> 72.123448 | W20: 15255.44 | X20: =W20 -> 15255.44 | Y20: =X20/T20 -> 0.45585873 | AA20: 1558 | AB20: 414505 | AC20: 1278545.4 | AD20: =AB20/AA20 -> 266.04942 | AE20: =AC20/AB20 -> 3.0845115 | AF20: 133719.12 | AG20: =AF20 -> 133719.12 | AH20: =AF20/AC20 -> 0.10458691
A21: 45240 | B21: 160623.86 | C21: 2787 | D21: =B21/C21 -> 57.633247 | E21: 97541.12 | F21: 466 | G21: =E21/F21 -> 209.31571 | H21: =B21-E21 -> 63082.74 | I21: 1063 | J21: 677 | K21: 1871 | L21: =K21-J21 -> 1194 | M21: 918204.65 | N21: 40573.04 | O21: =N21 -> 40573.04 | P21: =O21/M21 -> 0.044187361 | R21: 79 | S21: 256 | T21: 8752.87 | U21: =S21/R21 -> 3.2405063 | V21: =T21/S21 -> 34.190898 | W21: 435.53 | X21: =W21 -> 435.53 | Y21: =X21/T21 -> 0.049758536 | AA21: 1823 | AB21: 445127 | AC21: 909451.78 | AD21: =AB21/AA21 -> 244.17279 | AE21: =AC21/AB21 -> 2.0431288 | AF21: 40137.51 | AG21: =AF21 -> 40137.51 | AH21: =AF21/AC21 -> 0.044133742
A22: 45241 | B22: 126226.53 | C22: 2574 | D22: =B22/C22 -> 49.039056 | E22: 100944.8 | F22: 520 | G22: =E22/F22 -> 194.12462 | H22: =B22-E22 -> 25281.73 | I22: 671 | J22: 532 | K22: 1808 | L22: =K22-J22 -> 1276 | M22: 878672.97 | N22: 38827.5 | O22: =N22 -> 38827.5 | P22: =O22/M22 -> 0.044188795 | R22: 111 | S22: 473 | T22: 15153.96 | U22: =S22/R22 -> 4.2612613 | V22: =T22/S22 -> 32.03797 | W22: -386.95 | X22: =W22 -> -386.95 | Y22: =X22/T22 -> -0.02553458 | AA22: 1747 | AB22: 430542 | AC22: 863519.01 | AD22: =AB22/AA22 -> 246.44648 | AE22: =AC22/AB22 -> 2.0056557 | AF22: 39214.45 | AG22: =AF22 -> 39214.45 | AH22: =AF22/AC22 -> 0.045412376
A23: 45242 | B23: 105430.29 | C23: 2128 | D23: =B23/C23 -> 49.544309 | E23: 88068.91 | F23: 435 | G23: =E23/F23 -> 202.45726 | H23: =B23-E23 -> 17361.38 | I23: 620 | J23: 386 | K23: 1474 | L23: =K23-J23 -> 1088 | M23: 732955.46 | N23: 15679.26 | O23: =N23 -> 15679.26 | P23: =O23/M23 -> 0.021391832 | R23: 177 | S23: 690 | T23: 40066.9 | U23: =S23/R23 -> 3.8983051 | V23: =T23/S23 -> 58.067971 | W23: -4921.9 | X23: =W23 -> -4921.9 | Y23: =X23/T23 -> -0.12284205 | AA23: 1380 | AB23: 376889 | AC23: 692888.56 | AD23: =AB23/AA23 -> 273.10797 | AE23: =AC23/AB23 -> 1.838442 | AF23: 20601.16 | AG23: =AF23 -> 20601.16 | AH23: =AF23/AC23 -> 0.029732285
A24: 45243 | B24: 132646.19 | C24: 2121 | D24: =B24/C24 -> 62.539458 | E24: 117779.16 | F24: 372 | G24: =E24/F24 -> 316.61065 | H24: =B24-E24 -> 14867.03 | I24: 438 | J24: 317 | K24: 1421 | L24: =K24-J24 -> 1104 | M24: 773420.72 | N24: 8659.98 | O24: =N24 -> 8659.98 | P24: =O24/M24 -> 0.011196985 | R24: 51 | S24: 198 | T24: 19553.17 | U24: =S24/R24 -> 3.8823529 | V24: =T24/S24 -> 98.753384 | W24: -2676.67 | X24: =W24 -> -2676.67 | Y24: =X24/T24 -> -0.13689187 | AA24: 1395 | AB24: 384403 | AC24: 753867.55 | AD24: =AB24/AA24 -> 275.55771 | AE24: =AC24/AB24 -> 1.9611386 | AF24: 11336.35 | AG24: =AF24 -> 11336.35 | AH24: =AF24/AC24 -> 0.015037589
A25: 45244 | B25: 122185.59 | C25: 2458 | D25: =B25/C25 -> 49.709353 | E25: 134433.75 | F25: 444 | G25: =E25/F25 -> 302.77872 | H25: =B25-E25 -> -12248.16 | I25: 598 | J25: 417 | K25: 1578 | L25: =K25-J25 -> 1161 | M25: 720244.85 | N25: 43018.97 | O25: =N25 -> 43018.97 | P25: =O25/M25 -> 0.059728258 | R25: 58 | S25: 209 | T25: 23565.33 | U25: =S25/R25 -> 3.6034483 | V25: =T25/S25 -> 112.75278 | W25: 1170.64 | X25: =W25 -> 1170.64 | Y25: =X25/T25 -> 0.049676368 | AA25: 1545 | AB25: 419387 | AC25: 696679.52 | AD25: =AB25/AA25 -> 271.4479 | AE25: =AC25/AB25 -> 1.6611853 | AF25: 41848.33 | AG25: =AF25 -> 41848.33 | AH25: =AF25/AC25 -> 0.060068265
A26: 45245 | B26: 118752.61 | C26: 2452 | D26: =B26/C26 -> 48.430918 | E26: 75528.67 | F26: 394 | G26: =E26/F26 -> 191.69713 | H26: =B26-E26 -> 43223.94 | I26: 644 | J26: 495 | K26: 1629 | L26: =K26-J26 -> 1134 | M26: 743969.45 | N26: 31994.18 | O26: =N26 -> 31994.18 | P26: =O26/M26 -> 0.043004696 | R26: 64 | S26: 248 | T26: 21150.27 | U26: =S26/R26 -> 3.875 | V26: =T26/S26 -> 85.283347 | W26: 732.19 | X26: =W26 -> 732.19 | Y26: =X26/T26 -> 0.034618471 | AA26: 1594 | AB26: 428111 | AC26: 722819.18 | AD26: =AB26/AA26 -> 268.57654 | AE26: =AC26/AB26 -> 1.688392 | AF26: 31262.09 | AG26: =AF26 -> 31262.09 | AH26: =AF26/AC26 -> 0.043250222
A27: 45246 | B27: 157556.68 | C27: 2515 | D27: =B27/C27 -> 62.646791 | E27: 99980.22 | F27: 405 | G27: =E27/F27 -> 246.86474 | H27: =B27-E27 -> 57576.46 | I27: 681 | J27: 457 | K27: 1577 | L27: =K27-J27 -> 1120 | M27: 780976.83 | N27: 38751.58 | O27: =N27 -> 38751.58 | P27: =O27/M27 -> 0.049619372 | R27: 107 | S27: 399 | T27: 15844.04 | U27: =S27/R27 -> 3.728972 | V27: =T27/S27 -> 39.709373 | W27: 110.95 | X27: =W27 -> 110.95 | Y27: =X27/T27 -> 0.0070026332 | AA27: 1505 | AB27: 385378 | AC27: 765132.79 | AD27: =AB27/AA27 -> 256.06512 | AE27: =AC27/AB27 -> 1.9854086 | AF27: 38640.63 | AG27: =AF27 -> 38640.63 | AH27: =AF27/AC27 -> 0.050501861
A28: 45247 | B28: 166408.78 | C28: 2696 | D28: =B28/C28 -> 61.724325 | E28: 123256.39 | F28: 476 | G28: =E28/F28 -> 258.942 | H28: =B28-E28 -> 43152.39 | I28: 620 | J28: 457 | K28: 1691 | L28: =K28-J28 -> 1234 | M28: 1046890.8 | N28: -28115.86 | O28: =N28 -> -28115.86 | P28: =O28/M28 -> -0.026856535 | R28: 87 | S28: 399 | T28: 22270.26 | U28: =S28/R28 -> 4.5862069 | V28: =T28/S28 -> 55.815188 | W28: 3085 | X28: =W28 -> 3085 | Y28: =X28/T28 -> 0.13852555 | AA28: 1636 | AB28: 468053 | AC28: 1024660.6 | AD28: =AB28/AA28 -> 286.09597 | AE28: =AC28/AB28 -> 2.1891978 | AF28: -32201.3 | AG28: =AF28 -> -32201.3 | AH28: =AF28/AC28 -> -0.031426309
A29: 45248 | B29: 153948.46 | C29: 2468 | D29: =B29/C29 -> 62.37782 | E29: 143438.53 | F29: 397 | G29: =E29/F29 -> 361.30612 | H29: =B29-E29 -> 10509.93 | I29: 672 | J29: 496 | K29: 1737 | L29: =K29-J29 -> 1241 | M29: 1146365.1 | N29: 26785.87 | O29: =N29 -> 26785.87 | P29: =O29/M29 -> 0.023365916 | R29: 81 | S29: 290 | T29: 18445.24 | U29: =S29/R29 -> 3.5802469 | V29: =T29/S29 -> 63.604276 | W29: 2124.19 | X29: =W29 -> 2124.19 | Y29: =X29/T29 -> 0.11516196 | AA29: 1688 | AB29: 464070 | AC29: 1127919.8 | AD29: =AB29/AA29 -> 274.92299 | AE29: =AC29/AB29 -> 2.430495 | AF29: 24661.68 | AG29: =AF29 -> 24661.68 | AH29: =AF29/AC29 -> 0.021864746
A30: 45249 | B30: 89491.04 | C30: 2219 | D30: =B30/C30 -> 40.329446 | E30: 65898 | F30: 355 | G30: =E30/F30 -> 185.62817 | H30: =B30-E30 -> 23593.04 | I30: 494 | J30: 377 | K30: 1472 | L30: =K30-J30 -> 1095 | M30: 694497.16 | N30: 57004.04 | O30: =N30 -> 57004.04 | P30: =O30/M30 -> 0.082079587 | R30: 53 | S30: 262 | T30: 8735.12 | U30: =S30/R30 -> 4.9433962 | V30: =T30/S30 -> 33.340153 | W30: -1212.44 | X30: =W30 -> -1212.44 | Y30: =X30/T30 -> -0.13880061 | AA30: 1441 | AB30: 416314 | AC30: 685762.04 | AD30: =AB30/AA30 -> 288.90632 | AE30: =AC30/AB30 -> 1.6472231 | AF30: 58216.44 | AG30: =AF30 -> 58216.44 | AH30: =AF30/AC30 -> 0.084893063
... A34: 45253 | B34: 137034.79 | C34: 2514 | D34: =B34/C34 -> 54.508667 | E34: 99332.95 | F34: 398 | G34: =E34/F34 -> 249.58028 | H34: =B34-E34 -> 37701.84 | I34: 883 | J34: 601 | K34: 1687 | L34: =K34-J34 -> 1086 | M34: 826347.47 | N34: 34494.04 | O34: =N34 -> 34494.04 | P34: =O34/M34 -> 0.041742779 | R34: 69 | S34: 234 | T34: 18478.76 | U34: =S34/R34 -> 3.3913043 | V34: =T34/S34 -> 78.96906 | W34: -2107.18 | X34: =W34 -> -2107.18 | Y34: =X34/T34 -> -0.11403254 | AA34: 1645 | AB34: 423269 | AC34: 807868.71 | AD34: =AB34/AA34 -> 257.30638 | AE34: =AC34/AB34 -> 1.9086413 | AF34: 36575.48 | AG34: =AF34 -> 36575.48 | AH34: =AF34/AC34 -> 0.04527404
A35: 45254 | B35: 148336.66 | C35: 3078 | D35: =B35/C35 -> 48.192547 | E35: 113128.6 | F35: 528 | G35: =E35/F35 -> 214.25871 | H35: =B35-E35 -> 35208.06 | I35: 1181 | J35: 819 | K35: 2202 | L35: =K35-J35 -> 1383 | M35: 998755.6 | N35: 35620.27 | O35: =N35 -> 35620.27 | P35: =O35/M35 -> 0.035664651 | R35: 72 | S35: 230 | T35: 18537.78 | U35: =S35/R35 -> 3.1944444 | V35: =T35/S35 -> 80.599043 | W35: 3170.1 | X35: 3170.1 | Y35: =X35/T35 -> 0.17100753 | AA35: 2164 | AB35: 569199 | AC35: 980217.82 | AD35: =AB35/AA35 -> 263.03096 | AE35: =AC35/AB35 -> 1.7221004 | AF35: 32428.07 | AG35: =AF35 -> 32428.07 | AH35: =AF35/AC35 -> 0.033082514
A36: 45255 | B36: 146048.33 | C36: 3321 | D36: =B36/C36 -> 43.977215 | E36: 121237.09 | F36: 548 | G36: =E36/F36 -> 221.23557 | H36: =B36-E36 -> 24811.24 | I36: 947 | J36: 738 | K36: 2182 | L36: =K36-J36 -> 1444 | M36: 952912.23 | N36: 51223.87 | O36: =N36 -> 51223.87 | P36: =O36/M36 -> 0.053755077 | R36: 88 | S36: 394 | T36: 27539.84 | U36: =S36/R36 -> 4.4772727 | V36: =T36/S36 -> 69.898071 | W36: 5566.04 | X36: 5566.04 | Y36: =X36/T36 -> 0.20210865 | AA36: 2128 | AB36: 570532 | AC36: 925372.39 | AD36: =AB36/AA36 -> 268.10714 | AE36: =AC36/AB36 -> 1.6219465 | AF36: 45551.67 | AG36: =AF36 -> 45551.67 | AH36: =AF36/AC36 -> 0.049225231
A37: 45256 | B37: 104408.65 | C37: 2395 | D37: =B37/C37 -> 43.594426 | E37: 77204.19 | F37: 410 | G37: =E37/F37 -> 188.3029 | H37: =B37-E37 -> 27204.46 | I37: 580 | J37: 464 | K37: 1691 | L37: =K37-J37 -> 1227 | M37: 651818.57 | N37: 40922.48 | O37: =N37 -> 40922.48 | P37: =O37/M37 -> 0.06278201 | R37: 101 | S37: 432 | T37: 15399.11 | U37: =S37/R37 -> 4.2772277 | V37: =T37/S37 -> 35.646088 | W37: 2973.23 | X37: 2973.23 | Y37: =X37/T37 -> 0.19307804 | AA37: 1634 | AB37: 409127 | AC37: 636419.46 | AD37: =AB37/AA37 -> 250.38372 | AE37: =AC37/AB37 -> 1.5555548 | AF37: 38310.91 | AG37: =AF37 -> 38310.91 | AH37: =AF37/AC37 -> 0.060197578
A38: 45257 | B38: 91338.92 | C38: 2377 | D38: =B38/C38 -> 38.426134 | E38: 81845.55 | F38: 398 | G38: =E38/F38 -> 205.64209 | H38: =B38-E38 -> 9493.37 | I38: 845 | J38: 470 | K38: 1636 | L38: =K38-J38 -> 1166 | M38: 560045.43 | N38: -7628.96 | O38: =N38 -> -7628.96 | P38: =O38/M38 -> -0.013622038 | R38: 47 | S38: 160 | T38: 8091.22 | U38: =S38/R38 -> 3.4042553 | V38: =T38/S38 -> 50.570125 | W38: 287.96 | X38: =W38 -> 287.96 | Y38: =X38/T38 -> 0.035589194 | AA38: 1612 | AB38: 372335 | AC38: 551954.21 | AD38: =AB38/AA38 -> 230.97705 | AE38: =AC38/AB38 -> 1.4824129 | AF38: -7916.92 | AG38: =AF38 -> -7916.92 | AH38: =AF38/AC38 -> -0.014343436
A39: 45258 | B39: 129934.32 | C39: 2804 | D39: =B39/C39 -> 46.338916 | E39: 138202.41 | F39: 526 | G39: =E39/F39 -> 262.74222 | H39: =B39-E39 -> -8268.09 | I39: 780 | J39: 572 | K39: 1892 | L39: =K39-J39 -> 1320 | M39: 732876.67 | N39: 24748.48 | O39: =N39 -> 24748.48 | P39: =O39/M39 -> 0.033768956 | R39: 84 | S39: 282 | T39: 14375.43 | U39: =S39/R39 -> 3.3571429 | V39: =T39/S39 -> 50.976702 | W39: -7101.08 | X39: =W39 -> -7101.08 | Y39: =X39/T39 -> -0.4939734 | AA39: 1845 | AB39: 501810 | AC39: 718501.24 | AD39: =AB39/AA39 -> 271.98374 | AE39: =AC39/AB39 -> 1.4318193 | AF39: 31850.28 | AG39: =AF39 -> 31850.28 | AH39: =AF39/AC39 -> 0.044328775
A40: 45259 | B40: 166287.63 | C40: 2960 | D40: =B40/C40 -> 56.178253 | E40: 138968.33 | F40: 482 | G40: =E40/F40 -> 288.31604 | H40: =B40-E40 -> 27319.3 | I40: 877 | J40: 589 | K40: 1905 | L40: =K40-J40 -> 1316 | M40: 979748.39 | N40: 30760.21 | O40: =N40 -> 30760.21 | P40: =O40/M40 -> 0.03139603 | R40: 117 | S40: 433 | T40: 15760.52 | U40: =S40/R40 -> 3.7008547 | V40: =T40/S40 -> 36.39843 | W40: -1643.92 | X40: =W40 -> -1643.92 | Y40: =X40/T40 -> -0.1043062 | AA40: 1845 | AB40: 546381 | AC40: 963987.86 | AD40: =AB40/AA40 -> 296.14146 | AE40: =AC40/AB40 -> 1.7643144 | AF40: 32404.13 | AG40: =AF40 -> 32404.13 | AH40: =AF40/AC40 -> 0.033614666
A41: 45260 | B41: 166675.12 | C41: 3282 | D41: =B41/C41 -> 50.784619 | E41: 120195.18 | F41: 469 | G41: =E41/F41 -> 256.2797 | H41: =B41-E41 -> 46479.94 | I41: 959 | J41: 661 | K41: 2160 | L41: =K41-J41 -> 1499 | M41: 1026931.9 | N41: 20514.65 | O41: =N41 -> 20514.65 | P41: =O41/M41 -> 0.019976641 | R41: 94 | S41: 407 | T41: 16741.87 | U41: =S41/R41 -> 4.3297872 | V41: =T41/S41 -> 41.134816 | W41: -50.62 | X41: =W41 -> -50.62 | Y41: =X41/T41 -> -0.0030235571 | AA41: 2118 | AB41: 571197 | AC41: 1010190 | AD41: =AB41/AA41 -> 269.68697 | AE41: =AC41/AB41 -> 1.7685493 | AF41: 20656.27 | AG41: =AF41 -> 20656.27 | AH41: =AF41/AC41 -> 0.020447905
A42: TOTAL | B42: =SUM(B12:B41) -> 3947262.7 | C42: =SUM(C11:C41) -> 74801 | D42: =B42/C42 -> 52.770186 | E42: =SUM(E12:E41) -> 3116007.6 | F42: =SUM(F12:F41) -> 12830 | G42: =E42/F42 -> 242.86887 | H42: =B42-E42 -> 831255.1 | I42: =SUM(I12:I41) -> 21408 | J42: =SUM(J12:J41) -> 14846 | K42: =AVERAGE(K12:K41) -> 1666.4333 | M42: =SUM(M12:M41) -> 26225263 | N42: =SUM(N12:N41) -> 893941.5 | O42: =AVERAGE(O12:O41) -> 29798.05 | P42: =N42/M42 -> 0.034087037 | R42: =SUM(R11:R41) -> 2752 | S42: =SUM(S11:S41) -> 10018 | T42: =SUM(T12:T41) -> 590520.28 | U42: =S42/R42 -> 3.6402616 | V42: =T42/S42 -> 58.945925 | W42: =SUM(W12:W41) -> 33171.92 | X42: =SUM(X12:X41) -> 29141.92 | Y42: =AVERAGE(Y12:Y41) -> 0.046199551 | AA42: =SUM(AA12:AA41) -> 48422 | AB42: =SUM(AB12:AB41) -> 10829761 | AC42: =SUM(AC12:AC41) -> 25634782 | AD42: =AVERAGE(AD12:AD40) -> 271.32511 | AE42: =AC42/AB42 -> 2.3670681 | AF42: =SUM(AF12:AF41) -> 860067.54 | AG42: =SUM(AG12:AG41) -> 859933.94 | AH42: =AVERAGE(AH12:AH41) -> 0.034682952
A43: NETCASH BRUTO | B43: DEPOSITOS | C43: QTD. DEP | D43: TICKET DEP. | E43: SAQUES | F43: QTD. SAQ | G43: TICKET SAQ. | H43: NETCASH REAL | I43: CONVERSÃO FTD | K43: MEDIA UAP | M43: TURNOVER | N43: GGR TOTAL | O43: MEDIA GGR | P43: MEDIA % | R43: LTV Sportingbook | S43: =V42*U42*1 -> 214.57859 | AA43: LTV Cassino | AB43: =AB44*AD42*1 -> 642.24503
A44: =B42-E42+'CUSTOS 2023'!AN94 -> #REF! | I44: =J42/I42 -> 0.69347907 | R44: TICKET MÉDIO Sportingbook | S44: =V42 -> 58.945925 | AA44: TICKET MÉDIO Cassino | AB44: =AE42 -> 2.3670681

Sheet OUTUBRO
A9: TERMÔMETRO | AG9: OUTUBRO
A10: DATA | B10: DEPOSITOS | E10: SAQUES | O10: Sportsbook | X10: Cassino
B11: Total | C11: Quantidade | D11: Ticket | E11: Total | F11: Quantidade | G11: REGISTROS | H11: FTD | I11: UAP | J11: TURNOVER | K11: GGR | L11: NGR | M11: GGR% | O11: UAP | P11: Número de Bets | Q11: TURNOVER | R11: Média de Aposta por Usuário | S11: Ticket | T11: GGR | U11: NGR | V11: GGR% | X11: UAP | Y11: Número de Giros | Z11: TURNOVER | AA11: Vezes de start nos jogos por usuário | AB11: Ticket | AC11: GGR | AD11: NGR | AE11: GGR% | AG11: TICKET MÉDIO | AH11: NOVOS CLIENTES | AI11: CLIENTES INATIVOS | AJ11: FTD (Priméiro depósito) | AK11: UAP (Clientes Recorrentes) | AL11: CHURN (taxa de Inativos) | AM11: ARPUR (Receita média por usuário) | AN11: CAC. (Custo Aquisição) | AO11: Total Ações | AP11: Total Investido
A12: 45200 | B12: 60874.67 | C12: 1381 | D12: =B12/C12 -> 44.080138 | E12: 42313.89 | F12: 206 | G12: 199 | H12: 109 | I12: =O12+X12 -> 876 | J12: =Q12+Z12 -> 432831.46 | K12: =T12+AC12 -> 31217.12 | L12: 31217.12 | M12: 0.0721 | O12: 100 | P12: 361 | Q12: 9531.45 | R12: =P12/O12 -> 3.61 | S12: =Q12/P12 -> 26.402909 | T12: 2314.49 | U12: 2314.49 | V12: 0.2428 | X12: 776 | Y12: 242666 | Z12: 423300.01 | AA12: =Y12/X12 -> 312.71392 | AB12: =Z12/Y12 -> 1.744373 | AC12: 28902.63 | AD12: 28902.63 | AE12: 0.0683 | AG12: =D43 -> 54.094604 | AH12: =G43 -> 15114 | AI12: =AH12-AJ12 -> 8934 | AJ12: =H43 -> 6180 | AK12: =I43 -> 935 | AL12: =AI12/AH12 -> 0.59110758 | AM12: =K43/I43 -> 730.24029 | AN12: =AO12/AJ12 -> #REF! | AO12: ='CUSTOS 2023'!AI5 -> #REF! | AP12: ='CUSTOS 2023'!AI3 -> #REF!
A13: 45201 | B13: 78250.73 | C13: 1141 | D13: =B13/C13 -> 68.580833 | E13: 58436.13 | F13: 170 | G13: 218 | H13: 111 | I13: =O13+X13 -> 764 | J13: =Q13+Z13 -> 487872.82 | K13: =T13+AC13 -> 10345.03 | L13: 10345.03 | M13: 0.0212 | O13: 58 | P13: 201 | Q13: 7642.51 | R13: =P13/O13 -> 3.4655172 | S13: =Q13/P13 -> 38.022438 | T13: 1827.27 | U13: 1827.27 | V13: 0.2391 | X13: 706 | Y13: 199200 | Z13: 480230.31 | AA13: =Y13/X13 -> 282.15297 | AB13: =Z13/Y13 -> 2.4107947 | AC13: 8517.76 | AD13: 8517.76 | AE13: 0.0177
A14: 45202 | B14: 59965.87 | C14: 1319 | D14: =B14/C14 -> 45.463131 | E14: 43054.48 | F14: 232 | G14: 230 | H14: 151 | I14: =O14+X14 -> 856 | J14: =Q14+Z14 -> 460507.31 | K14: =T14+AC14 -> 17592.18 | L14: 17592.18 | M14: 0.0382 | O14: 86 | P14: 328 | Q14: 27218.44 | R14: =P14/O14 -> 3.8139535 | S14: =Q14/P14 -> 82.983049 | T14: -1965.47 | U14: -1965.47 | V14: -0.0722 | X14: 770 | Y14: 215502 | Z14: 433288.87 | AA14: =Y14/X14 -> 279.87273 | AB14: =Z14/Y14 -> 2.0106025 | AC14: 19557.65 | AD14: 19557.65 | AE14: 0.0451 | AG14: NETCASH | AH14: TICKET DEPÓSITO | AI14: CAIXA STARSPAY | AJ14: RETIRADAS MÊS
A15: 45203 | B15: 64141.26 | C15: 1289 | D15: =B15/C15 -> 49.760481 | E15: 45977.46 | F15: 225 | G15: 233 | H15: 105 | I15: =O15+X15 -> 859 | J15: =Q15+Z15 -> 432615.86 | K15: =T15+AC15 -> 23964.11 | L15: 23964.11 | M15: 0.0554 | O15: 89 | P15: 354 | Q15: 11121.02 | R15: =P15/O15 -> 3.9775281 | S15: =Q15/P15 -> 31.415311 | T15: -2079.49 | U15: -2079.49 | V15: -0.187 | X15: 770 | Y15: 192879 | Z15: 421494.84 | AA15: =Y15/X15 -> 250.49221 | AB15: =Z15/Y15 -> 2.1852811 | AC15: 26043.6 | AD15: 26043.6 | AE15: 0.0618 | AG15: =B43-E43 -> 605094.34 | AH15: =D43 -> 54.094604 | AI15: =B43-E43-AJ15 -> 115489.34 | AJ15: =409605+80000 -> 489605
A16: 45204 | B16: 91751.49 | C16: 1295 | D16: =B16/C16 -> 70.850571 | E16: 63893.19 | F16: 219 | G16: 298 | H16: 137 | I16: =O16+X16 -> 895 | J16: =Q16+Z16 -> 625809.58 | K16: =T16+AC16 -> 19326.3 | L16: 19326.3 | M16: 0.0309 | O16: 86 | P16: 428 | Q16: 11960.74 | R16: =P16/O16 -> 4.9767442 | S16: =Q16/P16 -> 27.945654 | T16: -797.15 | U16: -797.15 | V16: -0.0607 | X16: 809 | Y16: 227264 | Z16: 613848.84 | AA16: =Y16/X16 -> 280.91965 | AB16: =Z16/Y16 -> 2.7010386 | AC16: 20123.45 | AD16: 20123.45 | AE16: 0.0328
A17: 45205 | B17: 84790.98 | C17: 1472 | D17: =B17/C17 -> 57.602568 | E17: 52236.44 | F17: 205 | G17: 218 | H17: 142 | I17: =O17+X17 -> 955 | J17: =Q17+Z17 -> 630626.97 | K17: =T17+AC17 -> 17773.45 | L17: 17773.45 | M17: 0.0282 | O17: 65 | P17: 296 | Q17: 11979.02 | R17: =P17/O17 -> 4.5538462 | S17: =Q17/P17 -> 40.469662 | T17: -785.79 | U17: -785.79 | V17: -0.0696 | X17: 890 | Y17: 240120 | Z17: 618647.95 | AA17: =Y17/X17 -> 269.79775 | AB17: =Z17/Y17 -> 2.5764116 | AC17: 18559.24 | AD17: 18559.24 | AE17: 0.03
A18: 45206 | B18: 79309.67 | C18: 1570 | D18: =B18/C18 -> 50.515713 | E18: 56243.06 | F18: 276 | G18: 143 | H18: 119 | I18: =O18+X18 -> 1024 | J18: =Q18+Z18 -> 697891.04 | K18: =T18+AC18 -> 24844.51 | L18: 24844.51 | M18: 0.0356 | O18: 109 | P18: 463 | Q18: 15643.19 | R18: =P18/O18 -> 4.2477064 | S18: =Q18/P18 -> 33.786587 | T18: 3607.9 | U18: 3607.9 | V18: 0.2306 | X18: 915 | Y18: 246188 | Z18: 682247.85 | AA18: =Y18/X18 -> 269.05792 | AB18: =Z18/Y18 -> 2.7712474 | AC18: 21236.61 | AD18: 21236.61 | AE18: 0.0311
A19: 45207 | B19: 66347.58 | C19: 1289 | D19: =B19/C19 -> 51.472133 | E19: 48891.48 | F19: 219 | G19: 149 | H19: 111 | I19: =O19+X19 -> 906 | J19: =Q19+Z19 -> 534905.44 | K19: =T19+AC19 -> 24004.13 | L19: 24004.13 | M19: 0.0449 | O19: 115 | P19: 479 | Q19: 15485 | R19: =P19/O19 -> 4.1652174 | S19: =Q19/P19 -> 32.327766 | T19: -998.2 | U19: -998.2 | V19: -0.0645 | X19: 791 | Y19: 220107 | Z19: 519420.44 | AA19: =Y19/X19 -> 278.26422 | AB19: =Z19/Y19 -> 2.3598543 | AC19: 25002.33 | AD19: 25002.33 | AE19: 0.0481
A20: 45208 | B20: 65479.06 | C20: 1112 | D20: =B20/C20 -> 58.884047 | E20: 47772.94 | F20: 202 | G20: 99 | H20: 65 | I20: =O20+X20 -> 687 | J20: =Q20+Z20 -> 425746.29 | K20: =T20+AC20 -> 31039.76 | L20: 31039.76 | M20: 0.0729 | O20: 44 | P20: 201 | Q20: 24860.73 | R20: =P20/O20 -> 4.5681818 | S20: =Q20/P20 -> 123.68522 | T20: 4801.39 | U20: 4801.39 | V20: 0.1931 | X20: 643 | Y20: 165278 | Z20: 400885.56 | AA20: =Y20/X20 -> 257.04199 | AB20: =Z20/Y20 -> 2.4255228 | AC20: 26238.37 | AD20: 26238.37 | AE20: 0.0655
A21: 45209 | B21: 84710.18 | C21: 1168 | D21: =B21/C21 -> 72.525839 | E21: 78274.04 | F21: 216 | G21: 119 | H21: 81 | I21: =O21+X21 -> 756 | J21: =Q21+Z21 -> 738197.76 | K21: =T21+AC21 -> -994.83 | L21: -994.83 | M21: -0.0013 | O21: 50 | P21: 179 | Q21: 18647.7 | R21: =P21/O21 -> 3.58 | S21: =Q21/P21 -> 104.17709 | T21: 1634.97 | U21: 1634.97 | V21: 0.0877 | X21: 706 | Y21: 169451 | Z21: 719550.06 | AA21: =Y21/X21 -> 240.01558 | AB21: =Z21/Y21 -> 4.2463607 | AC21: -2629.8 | AD21: -2629.8 | AE21: -0.0037
A22: 45210 | B22: 79978.72 | C22: 1452 | D22: =B22/C22 -> 55.081763 | E22: 54649.1 | F22: 259 | G22: 165 | H22: 130 | I22: =O22+X22 -> 983 | J22: =Q22+Z22 -> 688694.27 | K22: =T22+AC22 -> 25327.68 | L22: 25327.68 | M22: 0.0368 | O22: 40 | P22: 155 | Q22: 10544.95 | R22: =P22/O22 -> 3.875 | S22: =Q22/P22 -> 68.031935 | T22: 2392.1 | U22: 2392.1 | V22: 0.2268 | X22: 943 | Y22: 218946 | Z22: 678149.32 | AA22: =Y22/X22 -> 232.18028 | AB22: =Z22/Y22 -> 3.097336 | AC22: 22935.58 | AD22: 22935.58 | AE22: 0.0338
A23: 45211 | B23: 86314.56 | C23: 1518 | D23: =B23/C23 -> 56.860711 | E23: 49285.5 | F23: 244 | G23: 712 | H23: 215 | I23: =O23+X23 -> 1008 | J23: =Q23+Z23 -> 960400.07 | K23: =T23+AC23 -> 31276.27 | L23: 31276.27 | M23: 0.0326 | O23: 117 | P23: 333 | Q23: 13832.52 | R23: =P23/O23 -> 2.8461538 | S23: =Q23/P23 -> 41.539099 | T23: 4221.74 | U23: 4221.74 | V23: 0.3052 | X23: 891 | Y23: 241746 | Z23: 946567.55 | AA23: =Y23/X23 -> 271.31987 | AB23: =Z23/Y23 -> 3.9155459 | AC23: 27054.53 | AD23: 27054.53 | AE23: 0.0286
A24: 45212 | B24: 83313.08 | C24: 1395 | D24: =B24/C24 -> 59.722638 | E24: 78410.45 | F24: 258 | G24: 632 | H24: 149 | I24: =O24+X24 -> 897 | J24: =Q24+Z24 -> 644709.89 | K24: =T24+AC24 -> 23506.76 | L24: 23506.76 | M24: 0.0365 | O24: 83 | P24: 351 | Q24: 40218.26 | R24: =P24/O24 -> 4.2289157 | S24: =Q24/P24 -> 114.58194 | T24: -748.54 | U24: -748.54 | V24: -0.0186 | X24: 814 | Y24: 262325 | Z24: 604491.63 | AA24: =Y24/X24 -> 322.26658 | AB24: =Z24/Y24 -> 2.3043615 | AC24: 24255.3 | AD24: 24255.3 | AE24: 0.0401
A25: 45213 | B25: 72048.93 | C25: 1443 | D25: =B25/C25 -> 49.929958 | E25: 55786.38 | F25: 216 | G25: 682 | H25: 173 | I25: =O25+X25 -> 883 | J25: =Q25+Z25 -> 518710.2 | K25: =T25+AC25 -> 17169.02 | L25: 17169.02 | M25: 0.0331 | O25: 45 | P25: 259 | Q25: 33981.96 | R25: =P25/O25 -> 5.7555556 | S25: =Q25/P25 -> 131.20448 | T25: 787.15 | U25: 787.15 | V25: 0.0232 | X25: 838 | Y25: 256836 | Z25: 484728.24 | AA25: =Y25/X25 -> 306.48687 | AB25: =Z25/Y25 -> 1.8873065 | AC25: 16381.87 | AD25: 16381.87 | AE25: 0.0338
A26: 45214 | B26: 56004.85 | C26: 1162 | D26: =B26/C26 -> 48.196945 | E26: 50243.91 | F26: 189 | G26: 1635 | H26: 112 | I26: =O26+X26 -> 732 | J26: =Q26+Z26 -> 622178.51 | K26: =T26+AC26 -> 16843.37 | L26: 16843.37 | M26: 0.0271 | O26: 59 | P26: 272 | Q26: 26662.96 | R26: =P26/O26 -> 4.6101695 | S26: =Q26/P26 -> 98.025588 | T26: 503.78 | U26: 503.78 | V26: 0.0189 | X26: 673 | Y26: 192247 | Z26: 595515.55 | AA26: =Y26/X26 -> 285.65676 | AB26: =Z26/Y26 -> 3.0976585 | AC26: 16339.59 | AD26: 16339.59 | AE26: 0.0274
A27: 45215 | B27: 74022.74 | C27: 1050 | D27: =B27/C27 -> 70.497848 | E27: 59052.28 | F27: 195 | G27: 1491 | H27: 110 | I27: =O27+X27 -> 717 | J27: =Q27+Z27 -> 576995.23 | K27: =T27+AC27 -> -1118.66 | L27: -1118.66 | M27: -0.0019 | O27: 44 | P27: 185 | Q27: 20015.36 | R27: =P27/O27 -> 4.2045455 | S27: =Q27/P27 -> 108.19114 | T27: -300.16 | U27: -300.16 | V27: -0.015 | X27: 673 | Y27: 174843 | Z27: 556979.87 | AA27: =Y27/X27 -> 259.79643 | AB27: =Z27/Y27 -> 3.1856001 | AC27: -818.5 | AD27: -818.5 | AE27: -0.0015
A28: 45216 | B28: 77321.69 | C28: 1614 | D28: =B28/C28 -> 47.906871 | E28: 70460.17 | F28: 278 | G28: 1994 | H28: 314 | I28: =O28+X28 -> 961 | J28: =Q28+Z28 -> 519404.63 | K28: =T28+AC28 -> 27702.33 | L28: 27702.33 | M28: 0.0533 | O28: 95 | P28: 354 | Q28: 17281.1 | R28: =P28/O28 -> 3.7263158 | S28: =Q28/P28 -> 48.816667 | T28: 4901.37 | U28: 4901.37 | V28: 0.2836 | X28: 866 | Y28: 206184 | Z28: 502123.53 | AA28: =Y28/X28 -> 238.08776 | AB28: =Z28/Y28 -> 2.4353176 | AC28: 22800.96 | AD28: 22800.96 | AE28: 0.0454
A29: 45217 | B29: 100497.32 | C29: 1633 | D29: =B29/C29 -> 61.541531 | E29: 70431.76 | F29: 280 | G29: 672 | H29: 346 | I29: =O29+X29 -> 1129 | J29: =Q29+Z29 -> 730746.15 | K29: -5280.92 | L29: -5280.92 | M29: -0.0072 | O29: 108 | P29: 385 | Q29: 33285.36 | R29: =P29/O29 -> 3.5648148 | S29: =Q29/P29 -> 86.455481 | T29: 883.26 | U29: 883.26 | V29: 0.0265 | X29: 1021 | Y29: 243060 | Z29: 697460.79 | AA29: =Y29/X29 -> 238.06072 | AB29: =Z29/Y29 -> 2.8695005 | AC29: -6164.18 | AD29: -6164.18 | AE29: -0.0088
A30: 45218 | B30: 98140.22 | C30: 1284 | D30: =B30/C30 -> 76.433193 | E30: 68472.19 | F30: 224 | G30: 353 | H30: 197 | I30: =O30+X30 -> 911 | J30: =Q30+Z30 -> 776357.08 | K30: 55373.05 | L30: 55373.05 | M30: 0.0718 | O30: 104 | P30: 400 | Q30: 17146.43 | R30: =P30/O30 -> 3.8461538 | S30: =Q30/P30 -> 42.866075 | T30: -1357.15 | U30: -1357.15 | V30: -0.0792 | X30: 807 | Y30: 21913 | Z30: 759210.65 | AB30: 3.46 | AC30: 57094.88 | AD30: 57094.88 | AE30: 0.0752
A31: 45219 | B31: 120394.23 | C31: 1512 | D31: =B31/C31 -> 79.625813 | E31: 69741.66 | F31: 257 | G31: 404 | H31: 222 | I31: =O31+X31 -> 990 | J31: =Q31+Z31 -> 786291.36 | K31: 60685.12 | L31: 60685.12 | M31: 0.0772 | O31: 61 | P31: 236 | Q31: 23018.37 | R31: =P31/O31 -> 3.8688525 | S31: =Q31/P31 -> 97.535466 | T31: 2721.18 | U31: 2721.18 | V31: 0.1182 | X31: 929 | Y31: 28996 | Z31: 763272.99 | AB31: 2.66 | AC31: 57963.54 | AD31: 57963.54 | AE31: 0.0759
A32: 45220 | B32: 70059.49 | C32: 1493 | D32: =B32/C32 -> 46.925311 | E32: 52002.73 | F32: 250 | G32: 316 | H32: 205 | I32: =O32+X32 -> 971 | J32: =Q32+Z32 -> 487939.46 | K32: 9477.4 | L32: 9477.4 | M32: 0.0194 | O32: 79 | P32: 274 | Q32: 18734.38 | R32: =P32/O32 -> 3.4683544 | S32: =Q32/P32 -> 68.37365 | T32: -3911.13 | U32: -3911.13 | V32: -0.2088 | X32: 892 | Y32: 275050 | Z32: 469205.08 | AA32: =Y32/X32 -> 308.35202 | AB32: =Z32/Y32 -> 1.7058901 | AC32: 13388.53 | AD32: 13388.53 | AE32: 0.0285
A33: 45221 | B33: 54185.03 | C33: 1179 | D33: =B33/C33 -> 45.958465 | E33: 46144.92 | F33: 210 | G33: 154 | H33: 108 | I33: =O33+X33 -> 810 | J33: =Q33+Z33 -> 395282.4 | K33: 28977.53 | L33: 28977.53 | M33: 0.0733 | O33: 107 | P33: 377 | Q33: 14179.85 | R33: =P33/O33 -> 3.5233645 | S33: =Q33/P33 -> 37.612334 | T33: 6085.77 | U33: 6085.77 | V33: 0.4292 | X33: 703 | Y33: 235290 | Z33: 381102.55 | AA33: =Y33/X33 -> 334.69417 | AB33: =Z33/Y33 -> 1.6197142 | AC33: 22891.76 | AD33: 22891.76 | AE33: 0.0601
A34: 45222 | B34: 55870.34 | C34: 1080 | D34: =B34/C34 -> 51.731796 | E34: 44700.93 | F34: 207 | G34: 205 | H34: 128 | I34: =O34+X34 -> 703 | J34: =Q34+Z34 -> 313485.78 | K34: 14014.93 | L34: 14014.93 | M34: 0.0447 | O34: 44 | P34: 172 | Q34: 19582.62 | R34: =P34/O34 -> 3.9090909 | S34: =Q34/P34 -> 113.85244 | T34: 7007.5 | U34: 7007.5 | V34: 0.3578 | X34: 659 | Y34: 180646 | Z34: 293903.16 | AA34: =Y34/X34 -> 274.1214 | AB34: =Z34/Y34 -> 1.6269564 | AC34: 7007.43 | AD34: 7007.43 | AE34: 0.0238
A35: 45223 | B35: 66813.61 | C35: 1058 | D35: =B35/C35 -> 63.15086 | E35: 63969.26 | F35: 197 | G35: 141 | H35: 78 | I35: =O35+X35 -> 687 | J35: =Q35+Z35 -> 454175.56 | K35: 6278.71 | L35: 6278.71 | M35: 0.0138 | O35: 55 | P35: 245 | Q35: 6963.11 | R35: =P35/O35 -> 4.4545455 | S35: =Q35/P35 -> 28.420857 | T35: -2224.13 | U35: -2224.13 | V35: -0.3194 | X35: 632 | Y35: 197016 | Z35: 447212.45 | AA35: =Y35/X35 -> 311.73418 | AB35: =Z35/Y35 -> 2.2699296 | AC35: 8502.84 | AD35: 8502.84 | AE35: 0.019
A36: 45224 | B36: 67328.23 | C36: 1275 | D36: =B36/C36 -> 52.806455 | E36: 36749.48 | F36: 203 | G36: 523 | H36: 262 | I36: =O36+X36 -> 931 | J36: =Q36+Z36 -> 348646.23 | K36: 25849.84 | L36: 25849.84 | M36: 0.0741 | O36: 122 | P36: 596 | Q36: 20883.82 | R36: =P36/O36 -> 4.8852459 | S36: =Q36/P36 -> 35.039966 | T36: -4115.77 | U36: -4115.77 | V36: -0.1971 | X36: 809 | Y36: 189140 | Z36: 327762.41 | AA36: =Y36/X36 -> 233.79481 | AB36: =Z36/Y36 -> 1.732909 | AC36: 29965.61 | AD36: 29965.61 | AE36: 0.0914
A37: 45225 | B37: 57905.77 | C37: 1521 | D37: =B37/C37 -> 38.070855 | E37: 54196.36 | F37: 274 | G37: 722 | H37: 448 | I37: =O37+X37 -> 1077 | J37: =Q37+Z37 -> 371753.08 | K37: 3523.91 | L37: 3523.91 | M37: 0.0095 | O37: 103 | P37: 449 | Q37: 23143.38 | R37: =P37/O37 -> 4.3592233 | S37: =Q37/P37 -> 51.544276 | T37: -8722.67 | U37: -8722.67 | V37: -0.3769 | X37: 974 | Y37: 229227 | Z37: 348609.7 | AA37: =Y37/X37 -> 235.346 | AB37: =Z37/Y37 -> 1.5208056 | AC37: 12246.58 | AD37: 12246.58 | AE37: 0.0351
A38: 45226 | B38: 86095.35 | C38: 1678 | D38: =B38/C38 -> 51.308313 | E38: 48018.56 | F38: 303 | G38: 505 | H38: 358 | I38: =O38+X38 -> 1154 | J38: =Q38+Z38 -> 531265.72 | K38: 26420.96 | L38: 26420.96 | M38: 0.0497 | O38: 86 | P38: 393 | Q38: 32234.68 | R38: =P38/O38 -> 4.5697674 | S38: =Q38/P38 -> 82.022087 | T38: -3175.89 | U38: -3175.89 | V38: -0.0985 | X38: 1068 | Y38: 263066 | Z38: 499031.04 | AA38: =Y38/X38 -> 246.31648 | AB38: =Z38/Y38 -> 1.8969804 | AC38: 29596.85 | AD38: 29596.85 | AE38: 0.0593
A39: 45227 | B39: 74226.68 | C39: 1873 | D39: =B39/C39 -> 39.629834 | E39: 62328.9 | F39: 301 | G39: 547 | H39: 423 | I39: =O39+X39 -> 1282 | J39: =Q39+Z39 -> 538675.75 | K39: 27040.32 | L39: 27040.32 | M39: 0.0502 | O39: 114 | P39: 548 | Q39: 31794.94 | R39: =P39/O39 -> 4.8070175 | S39: =Q39/P39 -> 58.019964 | T39: 8529.9 | U39: 8529.9 | V39: 0.2683 | X39: 1168 | Y39: 299893 | Z39: 506880.81 | AA39: =Y39/X39 -> 256.75771 | AB39: =Z39/Y39 -> 1.6902055 | AC39: 18510.42 | AD39: 18510.42 | AE39: 0.0365
A40: 45228 | B40: 69496.46 | C40: 1544 | D40: =B40/C40 -> 45.010661 | E40: 48529.17 | F40: 293 | G40: 360 | H40: 293 | I40: =O40+X40 -> 1123 | J40: =Q40+Z40 -> 397950.21 | K40: 19030.77 | L40: 19030.77 | M40: 0.0478 | O40: 116 | P40: 526 | Q40: 32802.49 | R40: =P40/O40 -> 4.5344828 | S40: =Q40/P40 -> 62.362148 | T40: 2964.3 | U40: 2964.3 | V40: 0.0904 | X40: 1007 | Y40: 255364 | Z40: 365147.72 | AA40: =Y40/X40 -> 253.58888 | AB40: =Z40/Y40 -> 1.4299107 | AC40: 16066.47 | AD40: 16066.47 | AE40: 0.044
A41: 45229 | B41: 71604.37 | C41: 1686 | D41: =B41/C41 -> 42.46997 | E41: 52909.69 | F41: 287 | G41: 482 | H41: 380 | I41: =O41+X41 -> 1136 | J41: =Q41+Z41 -> 432551.03 | K41: 23366.09 | L41: 23366.09 | M41: 0.054 | O41: 59 | P41: 337 | Q41: 30206.04 | R41: =P41/O41 -> 5.7118644 | S41: =Q41/P41 -> 89.632166 | T41: 8844.52 | U41: 8844.52 | V41: 0.2928 | X41: 1077 | Y41: 280980 | Z41: 402344.99 | AA41: =Y41/X41 -> 260.89136 | AB41: =Z41/Y41 -> 1.4319346 | AC41: 14521.57 | AD41: 14521.57 | AE41: 0.0361
A42: 45230 | B42: 96683.53 | C42: 2029 | D42: =B42/C42 -> 47.650828 | E42: 75655.84 | F42: 355 | G42: 513 | H42: 398 | I42: 1322 | J42: 623839.79 | K42: 48198.43 | L42: 48198.43 | M42: 0.0773 | O42: 72 | P42: 297 | Q42: 13608.34 | R42: =P42/O42 -> 4.125 | S42: =Q42/P42 -> 45.819327 | T42: 4991.64 | U42: 4991.64 | V42: 0.3668 | X42: 1275 | Y42: 362793 | Z42: 610231.45 | AA42: =Y42/X42 -> 284.54353 | AB42: =Z42/Y42 -> 1.6820376 | AC42: 43206.79 | AD42: 43206.79 | AE42: 0.0708
A43: TOTAL | B43: =SUM(B12:B42) -> 2353926.7 | C43: =SUM(C12:C42) -> 43515 | D43: =B43/C43 -> 54.094604 | E43: =SUM(E12:E42) -> 1748832.4 | F43: =SUM(F12:F42) -> 7176 | G43: =SUM(G12:G42) -> 15114 | H43: =SUM(H12:H42) -> 6180 | I43: =AVERAGE(I12:I42) -> 935 | J43: =SUM(J12:J42) -> 17187057 | K43: =SUM(K12:K42) -> 682774.67 | L43: =AVERAGE(L12:L42) -> 22024.989 | M43: =K43/J43 -> 0.039726096 | O43: =SUM(O11:O42) -> 2515 | P43: =SUM(P11:P42) -> 10434 | Q43: =SUM(Q12:Q42) -> 634210.72 | R43: =P43/O43 -> 4.1487078 | S43: =Q43/P43 -> 60.783086 | T43: =SUM(T12:T42) -> 37838.69 | U43: =SUM(U12:U42) -> 37838.69 | V43: =T43/Q43 -> 0.059662647 | X43: =sum(X12:X42) -> 26495 | Y43: =SUM(Y12:Y42) -> 5416585 | Z43: =SUM(Z12:Z42) -> 16552846 | AA43: =AVERAGE(AA12:AA42) -> 271.52844 | AB43: =MEDIAN(AB12:AB42) -> 2.3043615 | AC43: =sum(AC12:AC42) -> 645300.26 | AD43: =SUM(AD12:AD42) -> 645300.26 | AE43: =AC43/Z43 -> 0.038984248
A44: NETCASH | B44: DEPOSITOS | C44: QTD. DEP | D44: TICKET | E44: SAQUES | F44: QTD. SAQUES | G44: CONVERSÃO FTD | I44: MEDIA UAP | J44: TURNOVER | K44: GGR TOTAL | L44: MEDIA GGR | M44: MEDIA % | O44: LTV Sportingbook | P44: =S43*R43*1 -> 252.17126 | X44: LTV Cassino | Y44: =Y45*AA43*1 -> 625.69968
A45: =B43-E43 -> 605094.34 | G45: =H43/G43 -> 0.40889242 | O45: TICKET MÉDIO Sportingbook | P45: =S43 -> 60.783086 | X45: TICKET MÉDIO Cassino | Y45: =AB43 -> 2.3043615
A47: TERMOMETRO GGR
AG994: Análise por Jogo
AG995: game name | AH995: Turnover | AI995: Profit (Lucro) | AJ995: Profit % | AK995: UAP | AL995: Qty. Spin | AM995: Media de apostas por cliente | AN995: ticket Medio por aposta | AO995: LTV Cassino
AG996: Semana 03

Sheet SETEMBRO
A9: TERMÔMETRO | AG9: SETEMBRO
A10: DATA | B10: DEPÓSITO | E10: SAQUES | G10: GERAL | O10: Sportsbook | X10: Cassino
B11: Total | C11: Quantidade | D11: Ticket | E11: Total | F11: Quantidade | G11: REGISTROS | H11: FTD | I11: UAP | J11: TURNOVER | K11: GGR | L11: NGR | M11: GGR% | O11: UAP | P11: Número de Bets | Q11: TURNOVER | R11: Média de Aposta por Usuário | S11: Ticket | T11: GGR | U11: NGR | V11: GGR% | X11: UAP | Y11: Número de Giros | Z11: TURNOVER | AA11: Vezes de start nos jogos por usuário | AB11: Ticket | AC11: GGR | AD11: NGR | AE11: GGR% | AG11: TICKET MÉDIO | AH11: NOVOS CLIENTES | AI11: CLIENTES INATIVOS | AJ11: FTD (Priméiro depósito) | AK11: UAP (Clientes Recorrentes) | AL11: CHURN (taxa de Inativos) | AM11: ARPUR (Receita média por usuário) | AN11: CAC. (Custo Aquisição) | AO11: Total Ações | AP11: Total Investido
A12: 45170 | B12: 45686.71 | C12: 998 | D12: =B12/C12 -> 45.778267 | E12: 41267.63 | F12: 212 | G12: 215 | H12: 121 | I12: 625 | J12: 252237.08 | K12: =T12+AC12 -> 7261.62 | L12: =U12+AD12 -> 7261.62 | M12: 0.0288 | O12: 52 | P12: 172 | Q12: 6433.47 | R12: =P12/O12 -> 3.3076923 | S12: =Q12/P12 -> 37.403895 | T12: 412.85 | U12: 412.85 | V12: 0.0642 | X12: 598 | Y12: 148763 | Z12: 245803.61 | AA12: =Y12/X12 -> 248.76756 | AB12: =Z12/Y12 -> 1.6523168 | AC12: 6848.77 | AD12: 6848.77 | AE12: 0.0279 | AG12: =D42 -> 51.23397 | AH12: =G42 -> 15897 | AI12: =AH12-AJ12 -> 8611 | AJ12: =H42 -> 7286 | AK12: =I42 -> 901.9 | AL12: =AI12/AH12 -> 0.54167453 | AM12: =K42/I42 -> 677.85507 | AN12: =AO12/AJ12 -> 32.21658 | AO12: ='CUSTOS 2023'!AD5 -> 234730 | AP12: ='CUSTOS 2023'!AD3 -> 545280.8
A13: 45171 | B13: 53505.13 | C13: 1161 | D13: =B13/C13 -> 46.085383 | E13: 42522.81 | F13: 212 | G13: 150 | H13: 113 | I13: 704 | J13: 379036.28 | K13: =T13+AC13 -> 2204.5 | L13: =U13+AD13 -> 2204.5 | M13: 0.0058 | O13: 77 | P13: 335 | Q13: 12496.96 | R13: =P13/O13 -> 4.3506494 | S13: =Q13/P13 -> 37.304358 | T13: 3061.38 | U13: 3061.38 | V13: 0.245 | X13: 662 | Y13: 198191 | Z13: 366539.32 | AA13: =Y13/X13 -> 299.38218 | AB13: =Z13/Y13 -> 1.8494246 | AC13: -856.88 | AD13: -856.88 | AE13: -0.0023
A14: 45172 | B14: 44120 | C14: 977 | D14: =B14/C14 -> 45.158649 | E14: 34803.12 | F14: 182 | G14: 134 | H14: 76 | I14: 605 | J14: 303631.49 | K14: =T14+AC14 -> 11556.43 | L14: =U14+AD14 -> 11556.43 | M14: 0.0381 | O14: 73 | P14: 334 | Q14: 12490.82 | R14: =P14/O14 -> 4.5753425 | S14: =Q14/P14 -> 37.397665 | T14: 925.65 | U14: 925.65 | V14: 0.0741 | X14: 564 | Y14: 155316 | Z14: 291140.67 | AA14: =Y14/X14 -> 275.38298 | AB14: =Z14/Y14 -> 1.8745053 | AC14: 10630.78 | AD14: 10630.78 | AE14: 0.0365
A15: 45173 | B15: 52162.48 | C15: 842 | D15: =B15/C15 -> 61.950689 | E15: 31357.81 | F15: 139 | G15: 113 | H15: 64 | I15: 530 | J15: 304785.95 | K15: =T15+AC15 -> 20426.02 | L15: =U15+AD15 -> 20426.02 | M15: 0.067 | O15: 37 | P15: 209 | Q15: 5398.67 | R15: =P15/O15 -> 5.6486486 | S15: =Q15/P15 -> 25.830957 | T15: 390.52 | U15: 390.52 | V15: 0.0723 | X15: 509 | Y15: 145816 | Z15: 299387.28 | AA15: =Y15/X15 -> 286.47544 | AB15: =Z15/Y15 -> 2.0531854 | AC15: 20035.5 | AD15: 20035.5 | AE15: 0.0669
A16: 45174 | B16: 34254.61 | C16: 886 | D16: =B16/C16 -> 38.662088 | E16: 39705.76 | F16: 189 | G16: 169 | H16: 74 | I16: 577 | J16: 282357.21 | K16: =T16+AC16 -> -12698.02 | L16: =U16+AD16 -> -12698.02 | M16: -0.045 | O16: 29 | P16: 127 | Q16: 1892.47 | R16: =P16/O16 -> 4.3793103 | S16: =Q16/P16 -> 14.901339 | T16: 162.8 | U16: 162.8 | V16: 0.086 | X16: 560 | Y16: 157484 | Z16: 280464.74 | AA16: =Y16/X16 -> 281.22143 | AB16: =Z16/Y16 -> 1.7809094 | AC16: -12860.82 | AD16: -12860.82 | AE16: -0.0459
A17: 45175 | B17: 45058.28 | C17: 931 | D17: =B17/C17 -> 48.397723 | E17: 26995.76 | F17: 166 | G17: 220 | H17: 73 | I17: 620 | J17: 291372.99 | K17: =T17+AC17 -> 29174.66 | L17: =U17+AD17 -> 29174.66 | M17: 0.1001 | O17: 36 | P17: 114 | Q17: 2818.11 | R17: =P17/O17 -> 3.1666667 | S17: =Q17/P17 -> 24.720263 | T17: -475.69 | U17: -475.69 | V17: -0.1688 | X17: 600 | Y17: 140411 | Z17: 288554.88 | AA17: =Y17/X17 -> 234.01833 | AB17: =Z17/Y17 -> 2.0550732 | AC17: 29650.35 | AD17: 29650.35 | AE17: 0.1028
A18: 45176 | B18: 46477.8 | C18: 1123 | D18: =B18/C18 -> 41.387177 | E18: 47247.11 | F18: 197 | G18: 253 | H18: 105 | I18: 664 | J18: 323481.1 | K18: =T18+AC18 -> 4729.74 | L18: =U18+AD18 -> 4729.74 | M18: 0.0146 | O18: 43 | P18: 149 | Q18: 3091.67 | R18: =P18/O18 -> 3.4651163 | S18: =Q18/P18 -> 20.749463 | T18: 564.73 | U18: 564.73 | V18: 0.1827 | X18: 641 | Y18: 166863 | Z18: 320389.43 | AA18: =Y18/X18 -> 260.31669 | AB18: =Z18/Y18 -> 1.9200747 | AC18: 4165.01 | AD18: 4165.01 | AE18: 0.013
A19: 45177 | B19: 40565.06 | C19: 940 | D19: =B19/C19 -> 43.154319 | E19: 38305.39 | F19: 165 | G19: 181 | H19: 92 | I19: 603 | J19: 285529.77 | K19: =T19+AC19 -> 2418.91 | L19: =U19+AD19 -> 2418.91 | M19: 0.0085 | O19: 40 | P19: 159 | Q19: 2758.14 | R19: =P19/O19 -> 3.975 | S19: =Q19/P19 -> 17.346792 | T19: -27.77 | U19: -27.77 | V19: -0.0101 | X19: 578 | Y19: 141608 | Z19: 282771.63 | AA19: =Y19/X19 -> 244.99654 | AB19: =Z19/Y19 -> 1.996862 | AC19: 2446.68 | AD19: 2446.68 | AE19: 0.0087
A20: 45178 | B20: 52167.14 | C20: 938 | D20: =B20/C20 -> 55.615288 | E20: 38070.28 | F20: 166 | G20: 174 | H20: 78 | I20: 610 | J20: 244401.41 | K20: =T20+AC20 -> 7314.19 | L20: =U20+AD20 -> 7314.19 | M20: 0.0299 | O20: 50 | P20: 191 | Q20: 16239.32 | R20: =P20/O20 -> 3.82 | S20: =Q20/P20 -> 85.022618 | T20: 4947.63 | U20: 4947.63 | V20: 0.3047 | X20: 582 | Y20: 136044 | Z20: 228162.09 | AA20: =Y20/X20 -> 233.75258 | AB20: =Z20/Y20 -> 1.6771198 | AC20: 2366.56 | AD20: 2366.56 | AE20: 0.0104
A21: 45179 | B21: 40851.23 | C21: 854 | D21: =B21/C21 -> 47.835164 | E21: 39967.29 | F21: 167 | G21: 162 | H21: 68 | I21: 521 | J21: 234894.57 | K21: =T21+AC21 -> -2401.27 | L21: =U21+AD21 -> -2401.27 | M21: -0.0102 | O21: 43 | P21: 163 | Q21: 8823.73 | R21: =P21/O21 -> 3.7906977 | S21: =Q21/P21 -> 54.133313 | T21: -2983.68 | U21: -2983.68 | V21: -0.3381 | X21: 493 | Y21: 124887 | Z21: 226070.84 | AA21: =Y21/X21 -> 253.32049 | AB21: =Z21/Y21 -> 1.8102031 | AC21: 582.41 | AD21: 582.41 | AE21: 0.0026
A22: 45180 | B22: 45634.47 | C22: 786 | D22: =B22/C22 -> 58.059122 | E22: 49959.34 | F22: 141 | G22: 255 | H22: 78 | I22: 510 | J22: 314594.49 | K22: =T22+AC22 -> 9949.39 | L22: =U22+AD22 -> 9949.39 | M22: 0.0332 | O22: 37 | P22: 61 | Q22: 3445.8 | R22: =P22/O22 -> 1.6486486 | S22: =Q22/P22 -> 56.488525 | T22: 541.52 | U22: 541.52 | V22: 0.1572 | X22: 484 | Y22: 126580 | Z22: 311148.69 | AA22: =Y22/X22 -> 261.52893 | AB22: =Z22/Y22 -> 2.4581189 | AC22: 9407.87 | AD22: 9407.87 | AE22: 0.0302
A23: 45181 | B23: 74199.74 | C23: 1269 | D23: =B23/C23 -> 58.471032 | E23: 55120.73 | F23: 222 | G23: 1540 | H23: 435 | I23: 904 | J23: 454184.51 | K23: =T23+AC23 -> 17983.65 | L23: =U23+AD23 -> 17983.65 | M23: 0.0396 | O23: 127 | P23: 313 | Q23: 17190.56 | R23: =P23/O23 -> 2.4645669 | S23: =Q23/P23 -> 54.921917 | T23: 6566.06 | U23: 6566.06 | V23: 0.382 | X23: 834 | Y23: 166507 | Z23: 436993.95 | AA23: =Y23/X23 -> 199.64868 | AB23: =Z23/Y23 -> 2.624478 | AC23: 11417.59 | AD23: 11417.59 | AE23: 0.0261
A24: 45182 | B24: 132384.65 | C24: 2936 | D24: =B24/C24 -> 45.09014 | E24: 111775.07 | F24: 493 | G24: 4138 | H24: 1504 | I24: 2121 | J24: 776972.27 | K24: =T24+AC24 -> -787.7 | L24: =U24+AD24 -> -787.7 | M24: -0.001 | O24: 246 | P24: 604 | Q24: 20741.17 | R24: =P24/O24 -> 2.4552846 | S24: =Q24/P24 -> 34.339685 | T24: 3548.74 | U24: 3548.74 | V24: 0.1711 | X24: 2009 | Y24: 453113 | Z24: 756231.1 | AA24: =Y24/X24 -> 225.54156 | AB24: =Z24/Y24 -> 1.668968 | AC24: -4336.44 | AD24: -4336.44 | AE24: -0.0057
A25: 45183 | B25: 86440.33 | C25: 1823 | D25: =B25/C25 -> 47.416528 | E25: 76594.66 | F25: 363 | G25: 523 | H25: 340 | I25: 1204 | J25: 698605.1 | K25: =T25+AC25 -> 16607.24 | L25: =U25+AD25 -> 16607.24 | M25: 0.0238 | O25: 148 | P25: 542 | Q25: 38944.44 | R25: =P25/O25 -> 3.6621622 | S25: =Q25/P25 -> 71.85321 | T25: 7670.95 | U25: 7670.95 | V25: 0.197 | X25: 1121 | Y25: 364440 | Z25: 659660.66 | AA25: =Y25/X25 -> 325.10259 | AB25: =Z25/Y25 -> 1.8100666 | AC25: 8936.29 | AD25: 8936.29 | AE25: 0.0135
A26: 45184 | B26: 86926.06 | C26: 1618 | D26: =B26/C26 -> 53.724388 | E26: 56322.37 | F26: 330 | G26: 386 | H26: 276 | I26: 1069 | J26: 602357.01 | K26: =T26+AC26 -> 39387.11 | L26: =U26+AD26 -> 39387.11 | M26: 0.0654 | O26: 99 | P26: 285 | Q26: 13241.81 | R26: =P26/O26 -> 2.8787879 | S26: =Q26/P26 -> 46.462491 | T26: -1284.21 | U26: -1284.21 | V26: -0.097 | X26: 1016 | Y26: 262416 | Z26: 589115.2 | AA26: =Y26/X26 -> 258.28346 | AB26: =Z26/Y26 -> 2.2449668 | AC26: 40671.32 | AD26: 40671.32 | AE26: 0.069
A27: 45185 | B27: 121647.16 | C27: 2219 | D27: =B27/C27 -> 54.820712 | E27: 63392.58 | F27: 348 | G27: 1562 | H27: 681 | I27: 1471 | J27: 823754.98 | K27: =T27+AC27 -> 37516.84 | L27: =U27+AD27 -> 37516.84 | M27: 0.0455 | O27: 165 | P27: 543 | Q27: 27073.69 | R27: =P27/O27 -> 3.2909091 | S27: =Q27/P27 -> 49.859466 | T27: 4341.12 | U27: 4341.12 | V27: 0.1603 | X27: 1394 | Y27: 350412 | Z27: 796681.29 | AA27: =Y27/X27 -> 251.37159 | AB27: =Z27/Y27 -> 2.273556 | AC27: 33175.72 | AD27: 33175.72 | AE27: 0.0416
A28: 45186 | B28: 80488.28 | C28: 1417 | D28: =B28/C28 -> 56.801891 | E28: 58896.89 | F28: 287 | G28: 337 | H28: 227 | I28: 1022 | J28: 591142.69 | K28: =T28+AC28 -> 42416.75 | L28: =U28+AD28 -> 42416.75 | M28: 0.0718 | O28: 152 | P28: 458 | Q28: 27103.54 | R28: =P28/O28 -> 3.0131579 | S28: =Q28/P28 -> 59.178035 | T28: 2765.05 | U28: 2765.05 | V28: 0.102 | X28: 945 | Y28: 234714 | Z28: 564039.15 | AA28: =Y28/X28 -> 248.3746 | AB28: =Z28/Y28 -> 2.4030912 | AC28: 39651.7 | AD28: 39651.7 | AE28: 0.0703
A29: 45187 | B29: 78820.29 | C29: 1410 | D29: =B29/C29 -> 55.900915 | E29: 47095.66 | F29: 242 | G29: 543 | H29: 252 | I29: 966 | J29: 415426 | K29: =T29+AC29 -> 33340.55 | L29: =U29+AD29 -> 33340.55 | M29: 0.0803 | O29: 91 | P29: 251 | Q29: 11275.45 | R29: =P29/O29 -> 2.7582418 | S29: =Q29/P29 -> 44.922112 | T29: 1868.64 | U29: 1868.64 | V29: 0.1657 | X29: 917 | Y29: 201981 | Z29: 404150.55 | AA29: =Y29/X29 -> 220.26281 | AB29: =Z29/Y29 -> 2.0009335 | AC29: 31471.91 | AD29: 31471.91 | AE29: 0.0779
... A41: 45199 | B41: 74195.87 | C41: 1523 | D41: =B41/C41 -> 48.716921 | E41: 63744.15 | F41: 238 | G41: 184 | H41: 133 | I41: 915 | J41: 505562.17 | K41: =T41+AC41 -> 60714.45 | L41: =U41+AD41 -> 60714.45 | M41: 0.0508 | O41: 121 | P41: 489 | Q41: 37342.63 | R41: =P41/O41 -> 4.0413223 | S41: =Q41/P41 -> 76.365297 | T41: 37342.63 | U41: 37342.63 | V41: 0.0623 | X41: 843 | Y41: 250606 | Z41: 468219.54 | AA41: =Y41/X41 -> 297.27877 | AB41: =Z41/Y41 -> 1.8683493 | AC41: 23371.82 | AD41: 23371.82 | AE41: 0.0499
A42: TOTAL | B42: =SUM(B12:B41) -> 2098287.3 | C42: =SUM(C11:C41) -> 40955 | D42: =B42/C42 -> 51.23397 | E42: =SUM(E12:E41) -> 1591702.1 | F42: =SUM(F12:F41) -> 7355 | G42: =SUM(G12:G41) -> 15897 | H42: =SUM(H12:H41) -> 7286 | I42: =AVERAGE(I11:I41) -> 901.9 | J42: =SUM(J12:J41) -> 13637688 | K42: =SUM(K12:K41) -> 611357.49 | L42: =AVERAGE(L11:L41) -> 20378.583 | M42: =K42/J42 -> 0.044828529 | O42: =SUM(O11:O41) -> 2912 | P42: =SUM(P11:P41) -> 10051 | Q42: =SUM(Q12:Q41) -> 529326.27 | R42: =P42/O42 -> 3.4515797 | S42: =Q42/P42 -> 52.66404 | T42: =SUM(T12:T41) -> 98033.94 | U42: =SUM(U12:U41) -> 98033.94 | V42: =T42/Q42 -> 0.18520513 | X42: =SUM(X12:X41) -> 25441 | Y42: =SUM(Y12:Y41) -> 5573650 | Z42: =SUM(Z12:Z41) -> 13108362 | AA42: =AVERAGE(AA12:AA41) -> 257.91038 | AB42: =Z42/Y42 -> 2.3518452 | AC42: =SUM(AC12:AC41) -> 513323.55 | AD42: =SUM(AD12:AD41) -> 513323.55 | AE42: =AC42/Z42 -> 0.039160008
A43: NETCASH | B43: DEPOSITOS | C43: QTD. DEP | D43: TICKET | E43: SAQUES | F43: QTD. SAQUES | G43: CONVERSÃO FTD | I43: MEDIA UAP | J43: TURNOVER | K43: GGR TOTAL | L43: MEDIA GGR | M43: MEDIA % | O43: LTV Sportingbook | P43: =S42*R42*1 -> 181.77413 | X43: LTV Cassino | Y43: =Y44*AA42*1 -> 606.56527
A44: =B42-E42 -> 506585.14 | G44: =H42/G42 -> 0.45832547 | O44: TICKET MÉDIO Sportingbook | P44: =S42 -> 52.66404 | X44: TICKET MÉDIO Cassino | Y44: =AB42 -> 2.3518452

Sheet AGOSTO
A9: TERMÔMETRO
A10: DATA | B10: DEPÓSITO | E10: SAQUES | G10: GERAL | O10: Sportsbook | X10: Cassino
B11: Total | C11: Quantidade | D11: Ticket | E11: Total | F11: Quantidade | G11: REGISTROS | H11: FTD | I11: UAP | J11: TURNOVER | K11: GGR | L11: NGR | M11: GGR% | O11: UAP | P11: Número de Bets | Q11: TURNOVER | R11: Média de Aposta por Usuário | S11: Ticket | T11: GGR | U11: NGR | V11: GGR% | X11: UAP | Y11: Número de Giros | Z11: TURNOVER | AA11: Vezes de start nos jogos por usuário | AB11: Ticket | AC11: GGR | AD11: NGR | AE11: GGR%
A12: 45139 | B12: 68923.49 | C12: 1331 | D12: =B12/C12 -> 51.783238 | E12: 52415.78 | F12: 242 | G12: 542 | H12: 333 | I12: 950 | J12: 390657.3 | K12: =T12+AC12 -> 12019.3 | L12: 12019.3 | M12: 0.0308 | O12: 56 | P12: 181 | Q12: 3645.63 | R12: =P12/O12 -> 3.2321429 | S12: =Q12/P12 -> 20.141602 | T12: -2256.6 | U12: -2256.6 | V12: -0.619 | X12: 927 | Y12: 234454 | Z12: 387011.67 | AA12: =Y12/X12 -> 252.91694 | AB12: =Z12/Y12 -> 1.6506934 | AC12: 14275.9 | AD12: 14275.9 | AE12: 0.0369 | AF12: TICKET MÉDIO | AG12: NOVOS CLIENTES | AH12: CLIENTES INATIVOS | AI12: FTD (Priméiro depósito) | AJ12: UAP (Clientes Recorrentes) | AK12: CHURN (taxa de Inativos) | AL12: ARPUR (Receita média por usuário) | AM12: CAC. (Custo Aquisição) | AN12: Total Ações | AO12: Total Investido
A13: 45140 | B13: 56903.08 | C13: 1428 | D13: =B13/C13 -> 39.848095 | E13: 66125.73 | F13: 245 | G13: 845 | H13: 379 | I13: 1044 | J13: 478853.58 | K13: =T13+AC13 -> -8665.62 | L13: -8665.62 | M13: -0.0181 | O13: 93 | P13: 327 | Q13: 6341.89 | R13: =P13/O13 -> 3.516129 | S13: =Q13/P13 -> 19.394159 | T13: -774.78 | U13: -774.78 | V13: -0.1222 | X13: 994 | Y13: 216162 | Z13: 472511.69 | AA13: =Y13/X13 -> 217.4668 | AB13: =Z13/Y13 -> 2.1859147 | AC13: -7890.84 | AD13: -7890.84 | AE13: -0.0167 | AF13: =D43 -> 45.186319 | AG13: =G43 -> 9796 | AH13: =AG13-AI13 -> 4554 | AI13: =H43 -> 5242 | AJ13: =I43 -> 716 | AK13: =AH13/AG13 -> 0.46488363 | AL13: =K43/I43 -> 613.7585 | AM13: =AN13/AI13 -> 57.469096 | AN13: ='CUSTOS 2023'!Y5 -> 301253 | AO13: ='CUSTOS 2023'!Y3 -> 512368.91
A14: 45141 | B14: 86823.92 | C14: 1604 | D14: =B14/C14 -> 54.129626 | E14: 56408.82 | F14: 243 | G14: 727 | H14: 390 | I14: 1039 | J14: 587910.45 | K14: =T14+AC14 -> 39873.53 | L14: 39873.53 | M14: 0.0678 | O14: 78 | P14: 254 | Q14: 4737.9 | R14: =P14/O14 -> 3.2564103 | S14: =Q14/P14 -> 18.65315 | T14: 2196.81 | U14: 2196.81 | V14: 0.4637 | X14: 998 | Y14: 254894 | Z14: 583172.55 | AA14: =Y14/X14 -> 255.40481 | AB14: =Z14/Y14 -> 2.2879022 | AC14: 37676.72 | AD14: 37676.72 | AE14: 0.0646
A15: 45142 | B15: 75001.02 | C15: 1436 | D15: =B15/C15 -> 52.229123 | E15: 50693.82 | F15: 266 | G15: 377 | H15: 220 | I15: 908 | J15: 454092.09 | K15: =T15+AC15 -> 22905.24 | L15: 22905.24 | M15: 0.0504 | O15: 50 | P15: 165 | Q15: 8613.91 | R15: =P15/O15 -> 3.3 | S15: =Q15/P15 -> 52.205515 | T15: -2385.65 | U15: -2385.65 | V15: -0.277 | X15: 884 | Y15: 238673 | Z15: 445478.18 | AA15: =Y15/X15 -> 269.99208 | AB15: =Z15/Y15 -> 1.8664792 | AC15: 25290.89 | AD15: 25290.89 | AE15: 0.0568
A16: 45143 | B16: 81437.78 | C16: 1843 | D16: =B16/C16 -> 44.187618 | E16: 50722.61 | F16: 328 | G16: 514 | H16: 368 | I16: 1173 | J16: 521875.49 | K16: =T16+AC16 -> 33342.98 | L16: 33342.98 | M16: 0.0639 | O16: 113 | P16: 294 | Q16: 13686.82 | R16: =P16/O16 -> 2.6017699 | S16: =Q16/P16 -> 46.55381 | T16: 2027.55 | U16: 2027.55 | V16: 0.1481 | X16: 1124 | Y16: 298903 | Z16: 508188.67 | AA16: =Y16/X16 -> 265.92794 | AB16: =Z16/Y16 -> 1.7001792 | AC16: 31315.43 | AD16: 31315.43 | AE16: 0.0616
A17: 45144 | B17: 62490.89 | C17: 1304 | D17: =B17/C17 -> 47.922462 | E17: 46655.99 | F17: 197 | G17: 327 | H17: 184 | I17: 869 | J17: 568304.57 | K17: =T17+AC17 -> 16991.9 | L17: 16991.9 | M17: 0.0299 | O17: 95 | P17: 258 | Q17: 11382.87 | R17: =P17/O17 -> 2.7157895 | S17: =Q17/P17 -> 44.119651 | T17: 2105.2 | U17: 2105.2 | V17: 0.1849 | X17: 825 | Y17: 233891 | Z17: 556921.7 | AA17: =Y17/X17 -> 283.50424 | AB17: =Z17/Y17 -> 2.3811164 | AC17: 14886.7 | AD17: 14886.7 | AE17: 0.0267
A18: 45145 | B18: 44168.987 | C18: 1195 | D18: =B18/C18 -> 36.961495 | E18: 38384.167 | F18: 220 | G18: 307 | H18: 182 | I18: 806 | J18: 335427.46 | K18: =T18+AC18 -> 10340.843 | L18: 10340.843 | M18: 0.0308 | O18: 44 | P18: 154 | Q18: 4813.8215 | R18: =P18/O18 -> 3.5 | S18: =Q18/P18 -> 31.258581 | T18: 1663.0923 | U18: 1663.0923 | V18: 0.3455 | X18: 777 | Y18: 198667 | Z18: 330613.64 | AA18: =Y18/X18 -> 255.68468 | AB18: =Z18/Y18 -> 1.6641598 | AC18: 8677.7506 | AD18: 8677.7506 | AE18: 0.0262
A19: 45146 | B19: 70724.315 | C19: 1334 | D19: =B19/C19 -> 53.016728 | E19: 61756.232 | F19: 265 | G19: 395 | H19: 213 | I19: 917 | J19: 397753.35 | K19: =T19+AC19 -> 22444.957 | L19: 23964.818 | M19: 0.0603 | O19: 67 | P19: 236 | Q19: 9694.94 | R19: =P19/O19 -> 3.5223881 | S19: =Q19/P19 -> 41.080254 | T19: -3453.19 | U19: -3453.19 | V19: -0.3562 | X19: 881 | Y19: 207705 | Z19: 388060.32 | AA19: =Y19/X19 -> 235.7605 | AB19: =Z19/Y19 -> 1.8683244 | AC19: 25898.147 | AD19: 25898.147 | AE19: 0.0667
A20: 45147 | B20: 53778.93 | C20: 1191 | D20: =B20/C20 -> 45.154433 | E20: 35574.15 | F20: 199 | G20: 266 | H20: 139 | I20: 809 | J20: 323658.34 | K20: =T20+AC20 -> 14432.99 | L20: 14432.99 | M20: 0.0446 | O20: 75 | P20: 261 | Q20: 12412.58 | R20: =P20/O20 -> 3.48 | S20: =Q20/P20 -> 47.557778 | T20: 3194.12 | U20: 3194.12 | V20: 0.2573 | X20: 770 | Y20: 196132 | Z20: 311245.76 | AA20: =Y20/X20 -> 254.71688 | AB20: =Z20/Y20 -> 1.5869198 | AC20: 11238.87 | AD20: 11238.87 | AE20: 0.0361
A21: 45148 | B21: 45984.88 | C21: 1060 | D21: =B21/C21 -> 43.381962 | E21: 29868.08 | F21: 173 | G21: 229 | H21: 116 | I21: 727 | J21: 343252.62 | K21: =T21+AC21 -> 11869.09 | L21: 11869.09 | M21: 0.0346 | O21: 69 | P21: 165 | Q21: 6278.7 | R21: =P21/O21 -> 2.3913043 | S21: =Q21/P21 -> 38.052727 | T21: -937.78 | U21: -937.78 | V21: -0.1494 | X21: 686 | Y21: 177014 | Z21: 336973.92 | AA21: =Y21/X21 -> 258.0379 | AB21: =Z21/Y21 -> 1.9036569 | AC21: 12806.87 | AD21: 12806.87 | AE21: 0.038
A22: 45149 | B22: 52650.09 | C22: 1086 | D22: =B22/C22 -> 48.480746 | E22: 45987.98 | F22: 198 | G22: 217 | H22: 119 | I22: 747 | J22: 355761.35 | K22: =T22+AC22 -> 13247.4 | L22: 13247.4 | M22: 0.0372 | O22: 45 | P22: 159 | Q22: 13436.65 | R22: =P22/O22 -> 3.5333333 | S22: =Q22/P22 -> 84.507233 | T22: 1299.96 | U22: 1299.96 | V22: 0.0967 | X22: 723 | Y22: 155552 | Z22: 342324.7 | AA22: =Y22/X22 -> 215.14799 | AB22: =Z22/Y22 -> 2.2007091 | AC22: 11947.44 | AD22: 11947.44 | AE22: 0.0349
A23: 45150 | B23: 47669.47 | C23: 1110 | D23: =B23/C23 -> 42.945468 | E23: 32942.42 | F23: 197 | G23: 207 | H23: 132 | I23: 716 | J23: 329827.28 | K23: =T23+AC23 -> 15469.15 | L23: 15469.15 | M23: 0.0469 | O23: 45 | P23: 168 | Q23: 9356.52 | R23: =P23/O23 -> 3.7333333 | S23: =Q23/P23 -> 55.693571 | T23: 1451.63 | U23: 1451.63 | V23: 0.1551 | X23: 692 | Y23: 183021 | Z23: 320470.76 | AA23: =Y23/X23 -> 264.48121 | AB23: =Z23/Y23 -> 1.7510054 | AC23: 14017.52 | AD23: 14017.52 | AE23: 0.0437
A24: 45151 | B24: 47134.69 | C24: 1317 | D24: =B24/C24 -> 35.789438 | E24: 35630.55 | F24: 214 | G24: 522 | H24: 283 | I24: 893 | J24: 361501.31 | K24: =T24+AC24 -> 12000.63 | L24: 12000.63 | M24: 0.0332 | O24: 79 | P24: 277 | Q24: 12344.98 | R24: =P24/O24 -> 3.5063291 | S24: =Q24/P24 -> 44.566715 | T24: 1749.27 | U24: 1749.27 | V24: 0.1417 | X24: 852 | Y24: 209081 | Z24: 349156.33 | AA24: =Y24/X24 -> 245.40023 | AB24: =Z24/Y24 -> 1.6699572 | AC24: 10251.36 | AD24: 10251.36 | AE24: 0.0294
A25: 45152 | B25: 44014.21 | C25: 1214 | D25: =B25/C25 -> 36.255527 | E25: 60075.57 | F25: 203 | G25: 474 | H25: 234 | I25: 762 | J25: 374334.05 | K25: =T25+AC25 -> -1019.2 | L25: -1019.2 | M25: -0.0027 | O25: 43 | P25: 118 | Q25: 8933.74 | R25: =P25/O25 -> 2.744186 | S25: =Q25/P25 -> 75.709661 | T25: -829.67 | U25: -829.67 | V25: -0.0929 | X25: 740 | Y25: 193237 | Z25: 365400.31 | AA25: =Y25/X25 -> 261.13108 | AB25: =Z25/Y25 -> 1.8909438 | AC25: -189.53 | AD25: -189.53 | AE25: -0.0005
A26: 45153 | B26: 45786.62 | C26: 1391 | D26: =B26/C26 -> 32.916334 | E26: 37945.5 | F26: 200 | G26: 414 | H26: 238 | I26: 853 | J26: 349674.21 | K26: =T26+AC26 -> 16079.33 | L26: 16079.33 | M26: 0.046 | O26: 58 | P26: 161 | Q26: 9573.66 | R26: =P26/O26 -> 2.7758621 | S26: =Q26/P26 -> 59.463727 | T26: -1372.56 | U26: -1372.56 | V26: -0.1434 | X26: 820 | Y26: 175416 | Z26: 340100.55 | AA26: =Y26/X26 -> 213.92195 | AB26: =Z26/Y26 -> 1.9388229 | AC26: 17451.89 | AD26: 17451.89 | AE26: 0.0513
A27: 45154 | B27: 58005.28 | C27: 1125 | D27: =B27/C27 -> 51.560249 | E27: 35571.21 | F27: 159 | G27: 192 | H27: 90 | I27: 718 | J27: 417983.09 | K27: =T27+AC27 -> 18697.97 | L27: 18697.97 | M27: 0.0447 | O27: 83 | P27: 228 | Q27: 8692.92 | R27: =P27/O27 -> 2.746988 | S27: =Q27/P27 -> 38.126842 | T27: 2763.64 | U27: 2763.64 | V27: 0.3179 | X27: 668 | Y27: 182163 | Z27: 409290.17 | AA27: =Y27/X27 -> 272.6991 | AB27: =Z27/Y27 -> 2.2468348 | AC27: 15934.33 | AD27: 15934.33 | AE27: 0.0389
A28: 45155 | B28: 30920.36 | C28: 990 | D28: =B28/C28 -> 31.232687 | E28: 33951.62 | F28: 168 | G28: 193 | H28: 99 | I28: 629 | J28: 277360.41 | K28: =T28+AC28 -> -2154.21 | L28: -2154.21 | M28: -0.0078 | O28: 54 | P28: 179 | Q28: 7370.88 | R28: =P28/O28 -> 3.3148148 | S28: =Q28/P28 -> 41.178101 | T28: -803.81 | U28: -803.81 | V28: -0.1091 | X28: 597 | Y28: 141456 | Z28: 269989.53 | AA28: =Y28/X28 -> 236.94472 | AB28: =Z28/Y28 -> 1.9086467 | AC28: -1350.4 | AD28: -1350.4 | AE28: -0.005
A29: 45156 | B29: 37081.35 | C29: 955 | D29: =B29/C29 -> 38.828639 | E29: 21936.85 | F29: 180 | G29: 161 | H29: 94 | I29: 661 | J29: 266556.38 | K29: =T29+AC29 -> 32037.64 | L29: 24025.91 | M29: 0.0901 | O29: 54 | P29: 205 | Q29: 11997.85 | R29: =P29/O29 -> 3.7962963 | S29: =Q29/P29 -> 58.526098 | T29: 11997.85 | U29: 11997.85 | V29: 0.3322 | X29: 627 | Y29: 143566 | Z29: 254558.53 | AA29: =Y29/X29 -> 228.97289 | AB29: =Z29/Y29 -> 1.7731115 | AC29: 20039.79 | AD29: 20039.79 | AE29: 0.0787
... A42: 45169 | B42: 45898.86 | C42: 904 | D42: =B42/C42 -> 50.773075 | E42: 36905.87 | F42: 191 | G42: 172 | H42: 95 | I42: 598 | J42: 269622.91 | K42: =T42+AC42 -> 4583.42 | L42: 4583.42 | M42: 0.017 | O42: 48 | P42: 180 | Q42: 10449.45 | R42: =P42/O42 -> 3.75 | S42: =Q42/P42 -> 58.0525 | T42: 1176.92 | U42: 1176.92 | V42: 0.1126 | X42: 567 | Y42: 157922 | Z42: 259173.46 | AA42: =Y42/X42 -> 278.52205 | AB42: =Z42/Y42 -> 1.6411485 | AC42: 3406.5 | AD42: 3406.5 | AE42: 0.0131
A43: TOTAL | B43: =SUM(B12:B42) -> 1562362.2 | C43: =SUM(C12:C42) -> 34576 | D43: =B43/C43 -> 45.186319 | E43: =SUM(E12:E42) -> 1224380.4 | F43: =SUM(F12:F42) -> 5976 | G43: =SUM(G12:G42) -> 9796 | H43: =SUM(H12:H42) -> 5242 | I43: =MEDIAN(I12:I42) -> 716 | J43: =SUM(J12:J42) -> 12896918 | K43: =SUM(K12:K42) -> 439451.09 | L43: =AVERAGE(L11:L42) -> 13067.38 | M43: =K43/J43 -> 0.034074117 | O43: =SUM(O11:O42) -> 1911 | P43: =SUM(P11:P42) -> 5888 | Q43: =SUM(Q12:Q42) -> 301273.81 | R43: =P43/O43 -> 3.0811094 | S43: =Q43/P43 -> 51.167427 | T43: =SUM(T12:T42) -> 57675.842 | U43: =SUM(U12:U42) -> 57675.842 | X43: =SUM(X12:X42) -> 22123 | Y43: =SUM(Y12:Y42) -> 4037983 | Z43: =SUM(Z12:Z42) -> 12595646 | AA43: =AVERAGE(AA12:AA42) -> 249.10457 | AB43: =Z43/Y43 -> 3.1192915 | AC43: =SUM(AC12:AC42) -> 381775.25 | AD43: =SUM(AD12:AD42) -> 381775.25 | AE43: =SUM(AV6:AV37) -> 0
A44: NETCASH | B44: DEPOSITOS | C44: QTD. DEP | D44: TICKET | E44: SAQUES | F44: QTD. SAQUES | G44: CONVERSÃO FTD | I44: MEDIA UAP | J44: TURNOVER | K44: GGR TOTAL | L44: MEDIA GGR | M44: MEDIA % | O44: LTV Sportingbook | P44: =S43*R43*1 -> 157.65244 | X44: LTV Cassino | Y44: =Y45*AA43*1 -> 777.02976
A45: =B43-E43 -> 337981.79 | G45: =H43/G43 -> 0.53511637 | O45: TICKET MÉDIO Sportingbook | P45: =S43 -> 51.167427 | X45: TICKET MÉDIO Cassino | Y45: =AB43 -> 3.1192915
AL1023: SEMANA 4
AI1024: game name | AJ1024: Turnover | AK1024: Profit (Lucro) | AL1024: Profit % | AM1024: UAP | AN1024: Qty. Spin | AO1024: Media de apostas por cliente | AP1024: ticket Medio por aposta | AQ1024: LTV Cassino
AI1025: Aviator | AJ1025: 663865.61 | AK1025: 63682.84 | AL1025: 0.0959 | AM1025: 289 | AN1025: 24618 | AO1025: =AN1025/AM1025 -> 85.183391 | AP1025: =AJ1025/AN1025 -> 26.966675 | AQ1025: =AP1025*AO1025*1 -> 2297.1128
AI1026: Fortune Tiger | AJ1026: 281035 | AK1026: 14211.12 | AL1026: 0.0697 | AM1026: 1267 | AN1026: 294737 | AO1026: =AN1026/AM1026 -> 232.62589 | AP1026: =AJ1026/AN1026 -> 0.9535111 | AQ1026: =AP1026*AO1026*1 -> 221.81137
AI1027: Fortune Rabbit | AJ1027: 180532.5 | AK1027: -110.95 | AL1027: -0.0057 | AM1027: 572 | AN1027: 105531 | AO1027: =AN1027/AM1027 -> 184.49476 | AP1027: =AJ1027/AN1027 -> 1.7107059 | AQ1027: =AP1027*AO1027*1 -> 315.61626
AI1028: Fortune Ox | AJ1028: 132514 | AK1028: 5808.55 | AL1028: 0.0358 | AM1028: 626 | AN1028: 139045 | AO1028: =AN1028/AM1028 -> 222.11661 | AP1028: =AJ1028/AN1028 -> 0.95302959 | AQ1028: =AP1028*AO1028*1 -> 211.68371
AI1029: Mines | AJ1029: 105683.73 | AK1029: 3053.51 | AL1029: 0.0283 | AM1029: 485 | AN1029: 27191 | AO1029: =AN1029/AM1029 -> 56.063918 | AP1029: =AJ1029/AN1029 -> 3.8867173 | AQ1029: =AP1029*AO1029*1 -> 217.9046

Sheet  JULHO
A9: TERMÔMETRO | AF9: JULHO
A10: DATA | B10: DEPÓSITO | E10: SAQUES | G10: GERAL | P10: Sportsbook | X10: Cassino
B11: Total | C11: Quantidade | D11: Ticket | E11: Total | F11: Quantidade | G11: REGISTROS | H11: FTD | I11: UAP | J11: TURNOVER | K11: GGR | L11: NGR | M11: GGR% | O11: UAP | P11: Número de Bets | Q11: TURNOVER | R11: Média de Aposta por Usuário | S11: Ticket | T11: GGR | U11: NGR | V11: GGR% | X11: UAP | Y11: Número de Giros | Z11: TURNOVER | AA11: Vezes de start nos jogos por usuário | AB11: GGR | AC11: NGR | AD11: GGR%
A12: 45108 | B12: 50693.86 | C12: 1275 | D12: =B12/C12 -> 39.75989 | E12: 26179.12 | F12: 228 | G12: 331 | H12: 176 | I12: 789 | J12: 381106.11 | K12: =T12+AB12 -> 3257.65 | L12: 3257.65 | M12: 0.0085 | O12: 100 | P12: 341 | Q12: 19300.09 | R12: =P12/O12 -> 3.41 | T12: -7070.31 | U12: -7070.31 | V12: -0.3663 | X12: 741 | Y12: 153777 | Z12: 361806.02 | AA12: =Y12/X12 -> 207.52632 | AB12: 10327.96 | AC12: 10327.96 | AD12: 0.0285 | AF12: TICKET MÉDIO | AG12: TOTAL DE CLIENTES | AH12: CLIENTES FRIOS | AI12: FTD (Priméiro depósito) | AJ12: CHURN (taxa de Inativos) | AK12: LTV (Valor do tempo de vida do cliente) | AL12: CAC. (Custo Aquisição) | AM12: Total de Investimento | AN12: ROI (Retorno de Investimento
A13: 45109 | B13: 43198.37 | C13: 1188 | D13: =B13/C13 -> 36.362264 | E13: 29058.52 | F13: 213 | G13: 763 | H13: 303 | I13: 871 | J13: 394423.09 | K13: =T13+AB13 -> 17407.24 | L13: 17407.24 | M13: 0.0441 | O13: 134 | P13: 386 | Q13: 26981.09 | R13: =P13/O13 -> 2.880597 | T13: -41.37 | U13: -41.37 | V13: -0.0015 | X13: 803 | Y13: 158221 | Z13: 367442 | AA13: =Y13/X13 -> 197.03736 | AB13: 17448.61 | AC13: 17448.61 | AD13: 0.0475 | AF13: =D43 -> 48.434123 | AG13: =G43 -> 12831 | AH13: =AG13-AI13 -> 6034 | AI13: =H43 -> 6797 | AJ13: =AH13/AG13 -> 0.47026732 | AK13: =AF13*2*1 -> 96.868247 | AL13: =AM13/AI13 -> #REF! | AM13: ='CUSTOS 2023'!T3 -> #REF!
A14: 45110 | B14: 45058.13 | C14: 1029 | D14: =B14/C14 -> 43.78827 | E14: 37281.15 | F14: 191 | G14: 265 | H14: 175 | I14: 729 | J14: 427383.41 | K14: =T14+AB14 -> 8685.24 | L14: 8685.24 | M14: 0.0203 | O14: 57 | P14: 167 | Q14: 14714.55 | R14: =P14/O14 -> 2.9298246 | T14: 4820.28 | U14: 4820.28 | V14: 0.3276 | X14: 699 | Y14: 151917 | Z14: 412668.86 | AA14: =Y14/X14 -> 217.33476 | AB14: 3864.96 | AC14: 3864.96 | AD14: 0.0094
A15: 45111 | B15: 46141.62 | C15: 1001 | D15: =B15/C15 -> 46.095524 | E15: 25644.52 | F15: 186 | G15: 205 | H15: 142 | I15: 687 | J15: 404226.42 | K15: =T15+AB15 -> 31446.92 | L15: 31446.92 | M15: 0.0778 | O15: 54 | P15: 192 | Q15: 26985.91 | R15: =P15/O15 -> 3.5555556 | T15: 9451.74 | U15: 9451.74 | V15: 0.3502 | X15: 658 | Y15: 124604 | Z15: 377240.51 | AA15: =Y15/X15 -> 189.36778 | AB15: 21995.18 | AC15: 21995.18 | AD15: 0.0583
A16: 45112 | B16: 59525.74 | C16: 1097 | D16: =B16/C16 -> 54.262297 | E16: 28297.71 | F16: 165 | G16: 217 | H16: 138 | I16: 757 | J16: 522364.92 | K16: =T16+AB16 -> 23809.2 | L16: 23809.2 | M16: 0.0456 | O16: 96 | P16: 298 | Q16: 31001.11 | R16: =P16/O16 -> 3.1041667 | T16: 6458.19 | U16: 6458.19 | V16: 0.2083 | X16: 704 | Y16: 136318 | Z16: 491363.81 | AA16: =Y16/X16 -> 193.63352 | AB16: 17351.01 | AC16: 17351.01 | AD16: 0.0353
A17: 45113 | B17: 50762.94 | C17: 1103 | D17: =B17/C17 -> 46.022611 | E17: 37858.39 | F17: 195 | G17: 198 | H17: 152 | I17: 772 | J17: 429725.63 | K17: =T17+AB17 -> 15076.28 | L17: 15076.28 | M17: 0.0351 | O17: 70 | P17: 237 | Q17: 50368.46 | R17: =P17/O17 -> 3.3857143 | T17: -3335.27 | U17: -3335.27 | V17: -0.0662 | X17: 732 | Y17: 138078 | Z17: 379357.17 | AA17: =Y17/X17 -> 188.63115 | AB17: 18411.55 | AC17: 18411.55 | AD17: 0.0485
A18: 45114 | B18: 47455.31 | C18: 1161 | D18: =B18/C18 -> 40.874513 | E18: 32747.14 | F18: 201 | G18: 156 | H18: 113 | I18: 753 | J18: 395116.3 | K18: =T18+AB18 -> 18731.72 | L18: 18731.72 | M18: 0.0474 | O18: 59 | P18: 189 | Q18: 13243.76 | R18: =P18/O18 -> 3.2033898 | T18: 2732 | U18: 2732 | V18: 0.2063 | X18: 718 | Y18: 143232 | Z18: 381872.54 | AA18: =Y18/X18 -> 199.48747 | AB18: 15999.72 | AC18: 15999.72 | AD18: 0.0419
A19: 45115 | B19: 65876.19 | C19: 1091 | D19: =B19/C19 -> 60.381476 | E19: 39995.08 | F19: 207 | G19: 167 | H19: 123 | I19: 718 | J19: 449289.08 | K19: =T19+AB19 -> 23117.27 | L19: 23117.27 | M19: 0.0515 | O19: 91 | P19: 316 | Q19: 36489.45 | R19: =P19/O19 -> 3.4725275 | T19: 3517.37 | U19: 3517.37 | V19: 0.0964 | X19: 667 | Y19: 153784 | Z19: 412799.63 | AA19: =Y19/X19 -> 230.56072 | AB19: 19599.9 | AC19: 19599.9 | AD19: 0.0475
A20: 45116 | B20: 46320.62 | C20: 879 | D20: =B20/C20 -> 52.696951 | E20: 32020.89 | F20: 147 | G20: 164 | H20: 110 | I20: 634 | J20: 269151.09 | K20: =T20+AB20 -> 15157.77 | L20: 15157.77 | M20: 0.0563 | O20: 95 | P20: 289 | Q20: 17637.27 | R20: =P20/O20 -> 3.0421053 | T20: -3408.54 | U20: -3408.54 | V20: -0.1933 | X20: 588 | Y20: 127075 | Z20: 251513.82 | AA20: =Y20/X20 -> 216.11395 | AB20: 18566.31 | AC20: 18566.31 | AD20: 0.0738
A21: 45117 | B21: 54420.81 | C21: 941 | D21: =B21/C21 -> 57.832954 | E21: 42321.97 | F21: 144 | G21: 176 | H21: 105 | I21: 616 | J21: 303477.84 | K21: =T21+AB21 -> 10504.89 | L21: 10504.89 | M21: 0.0346 | O21: 46 | P21: 146 | Q21: 19977.15 | R21: =P21/O21 -> 3.173913 | T21: 1837.35 | U21: 1837.35 | V21: 0.092 | X21: 580 | Y21: 123861 | Z21: 283500.69 | AA21: =Y21/X21 -> 213.55345 | AB21: 8667.54 | AC21: 8667.54 | AD21: 0.0306
A22: 45118 | B22: 51358.54 | C22: 895 | D22: =B22/C22 -> 57.383844 | E22: 49617.76 | F22: 168 | G22: 188 | H22: 105 | I22: 620 | J22: 333297.52 | K22: =T22+AB22 -> 11844.35 | L22: 11844.35 | M22: 0.0355 | O22: 57 | P22: 186 | Q22: 16675.29 | R22: =P22/O22 -> 3.2631579 | T22: 1304.63 | U22: 1304.63 | V22: 0.0782 | X22: 584 | Y22: 116849 | Z22: 316622.23 | AA22: =Y22/X22 -> 200.0839 | AB22: 10539.72 | AC22: 10539.72 | AD22: 0.0333
A23: 45119 | B23: 40306.09 | C23: 842 | D23: =B23/C23 -> 47.869466 | E23: 31973.76 | F23: 126 | G23: 120 | H23: 73 | I23: 556 | J23: 247756.71 | K23: =T23+AB23 -> 4762.37 | L23: 4762.37 | M23: 0.0192 | O23: 69 | P23: 179 | Q23: 7101.98 | R23: =P23/O23 -> 2.5942029 | T23: 2968.88 | U23: 2968.88 | V23: 0.418 | X23: 515 | Y23: 110160 | Z23: 240654.73 | AA23: =Y23/X23 -> 213.90291 | AB23: 1793.49 | AC23: 1793.49 | AD23: 0.0075
A24: 45120 | B24: 45471.17 | C24: 815 | D24: =B24/C24 -> 55.792847 | E24: 27086.33 | F24: 159 | G24: 192 | H24: 103 | I24: 573 | J24: 343850.19 | K24: =T24+AB24 -> 20840.26 | L24: 20840.26 | M24: 0.0606 | O24: 57 | P24: 87 | Q24: 10017.54 | R24: =P24/O24 -> 1.5263158 | T24: 2273.09 | U24: 2273.09 | V24: 0.2269 | X24: 544 | Y24: 108553 | Z24: 333832.65 | AA24: =Y24/X24 -> 199.54596 | AB24: 18567.17 | AC24: 18567.17 | AD24: 0.0556
A25: 45121 | B25: 52748.11 | C25: 770 | D25: =B25/C25 -> 68.504039 | E25: 43934.05 | F25: 128 | G25: 131 | H25: 67 | I25: 496 | J25: 248831.96 | K25: =T25+AB25 -> 4918.29 | L25: 4918.29 | M25: 0.0198 | O25: 35 | P25: 137 | Q25: 6847.18 | R25: =P25/O25 -> 3.9142857 | T25: -1027.48 | U25: -1027.48 | V25: -0.1501 | X25: 472 | Y25: 129574 | Z25: 241984.78 | AA25: =Y25/X25 -> 274.52119 | AB25: 5945.77 | AC25: 5945.77 | AD25: 0.0246
A26: 45122 | B26: 59031.59 | C26: 1085 | D26: =B26/C26 -> 54.406995 | E26: 44764.22 | F26: 193 | G26: 894 | H26: 231 | I26: 689 | J26: 274266.6 | K26: =T26+AB26 -> 10721.88 | L26: 10721.88 | M26: 0.0391 | O26: 79 | P26: 222 | Q26: 14719.09 | R26: =P26/O26 -> 2.8101266 | T26: -242.16 | U26: -242.16 | V26: -0.0165 | X26: 647 | Y26: 148141 | Z26: 259547.51 | AA26: =Y26/X26 -> 228.966 | AB26: 10964.04 | AC26: 10964.04 | AD26: 0.0422
A27: 45123 | B27: 43673.95 | C27: 962 | D27: =B27/C27 -> 45.399116 | E27: 31470.11 | F27: 134 | G27: 354 | H27: 167 | I27: 661 | J27: 373739.18 | K27: =T27+AB27 -> 14644.38 | L27: 14644.38 | M27: 0.0392 | O27: 110 | P27: 258 | Q27: 8601.97 | R27: =P27/O27 -> 2.3454545 | T27: 2039.99 | U27: 2039.99 | V27: 0.2372 | X27: 601 | Y27: 144394 | Z27: 365137.21 | AA27: =Y27/X27 -> 240.25624 | AB27: 12604.39 | AC27: 12604.39 | AD27: 0.0345
A28: 45124 | B28: 45304.46 | C28: 1130 | D28: =B28/C28 -> 40.092442 | E28: 34227.23 | F28: 177 | G28: 826 | H28: 303 | I28: 751 | J28: 308445.75 | K28: =T28+AB28 -> 12379.06 | L28: 12379.06 | M28: 0.0401 | O28: 56 | P28: 174 | Q28: 9060.57 | R28: =P28/O28 -> 3.1071429 | T28: 1814.67 | U28: 1814.67 | V28: 0.2003 | X28: 723 | Y28: 156615 | Z28: 299385.18 | AA28: =Y28/X28 -> 216.61826 | AB28: 10564.39 | AC28: 10564.39 | AD28: 0.0353
A29: 45125 | B29: 56492.11 | C29: 1404 | D29: =B29/C29 -> 40.236546 | E29: 41104.58 | F29: 234 | G29: 756 | H29: 382 | I29: 934 | J29: 402205.27 | K29: =T29+AB29 -> 16163.77 | L29: 16163.77 | M29: 0.0402 | O29: 62 | P29: 181 | Q29: 11996.37 | R29: =P29/O29 -> 2.9193548 | T29: -3032.77 | U29: -3032.77 | V29: -0.2528 | X29: 905 | Y29: 198281 | Z29: 390208.9 | AA29: =Y29/X29 -> 219.09503 | AB29: 19196.54 | AC29: 19196.54 | AD29: 0.0492
... A42: 45138 | B42: 71200 | C42: 1361 | D42: =B42/C42 -> 52.314475 | E42: 55256 | F42: 242 | G42: 410 | H42: 233 | I42: 797 | J42: 390267.93 | K42: =T42+AB42 -> 27034.91 | L42: 27034.91 | M42: 0.0693 | O42: 34 | P42: 135 | Q42: 1933.72 | R42: =P42/O42 -> 3.9705882 | T42: 50.86 | U42: 50.86 | V42: 0.0263 | X42: 779 | Y42: 214422 | Z42: 388334.21 | AA42: =Y42/X42 -> 275.25289 | AB42: 26984.05 | AC42: 26984.05 | AD42: 0.0695
A43: TOTAL | B43: =SUM(B12:B42) -> 1709005.2 | C43: =SUM(C12:C42) -> 35869 | D43: =AVERAGE(D12:D42) -> 48.434123 | E43: =SUM(E12:E42) -> 1264825.3 | F43: =SUM(F12:F42) -> 6275 | G43: =SUM(G12:G42) -> 12831 | H43: =SUM(H12:H42) -> 6797 | I43: =AVERAGE(I12:I42) -> 783.6129 | J43: =SUM(J12:J42) -> 12100238 | K43: =SUM(K12:K42) -> 450090.87 | L43: =AVERAGE(L11:L42) -> 14519.06 | M43: =K43/J43 -> 0.03719686 | O43: =SUM(O11:O42) -> 2162 | P43: =SUM(P11:P42) -> 6545 | Q43: =SUM(Q12:Q42) -> 435950.84 | R43: =AVERAGE(R12:R42) -> 3.0864962 | T43: =SUM(T12:T42) -> 24068.09 | U43: =SUM(U12:U42) -> 24068.09 | X43: =SUM(X12:X42) -> 23132 | Y43: 214422 | Z43: =SUM(Z12:Z42) -> 11664287 | AA43: =AVERAGE(AA12:AA42) -> 228.85709 | AB43: =SUM(AB12:AB42) -> 426022.78 | AC43: =SUM(AC12:AC42) -> 426022.78 | AD43: =SUM(AT6:AT37) -> 0
A44: NETCASH | B44: DEPOSITOS | C44: QTD. DEP | D44: TICKET | E44: SAQUES | F44: QTD. SAQUES | G44: CONVERSÃO FTD | I44: MEDIA UAP | J44: TURNOVER | K44: GGR TOTAL | L44: MEDIA GGR | M44: MEDIA % | O44: LTV Sportingbook | P44: 200 | Y44: LTV Cassino | Z44: =Z45*AB43*1 -> 181495409079
A45: =B43-E43 -> 444179.91 | G45: =H43/G43 -> 0.52973268 | O45: TICKET MÉDIO Sportingbook | P45: 70 | Y45: TICKET MÉDIO Cassino | Z45: =AC43 -> 426022.78

Sheet JUNHO
A9: TERMÔMETRO | AE9: JUNHO
A10: DATA | B10: DEPÓSITO | E10: SAQUES | G10: GERAL | P10: Sportsbook | Y10: Cassino
B11: Total | C11: Quantidade | D11: Ticket | E11: Total | F11: Quantidade | G11: REGISTROS | H11: FTD | I11: UAP | J11: TURNOVER | K11: GGR | L11: NGR | M11: GGR% | O11: UAP | P11: Número de Bets | Q11: TURNOVER | R11: Média de Aposta por Usuário | S11: Valor médio de aposta por usuário | T11: GGR | U11: NGR | V11: GGR% | X11: UAP | Y11: Número de Giros | Z11: TURNOVER | AA11: GGR | AB11: NGR | AC11: GGR%
A12: 45078 | B12: 22399.676 | C12: 651 | D12: =B12/C12 -> 34.408104 | E12: 13819.832 | F12: 135 | G12: 457 | H12: 173 | I12: 611 | J12: 130835.38 | K12: 9767.056 | L12: 9767.056 | M12: 0.0747 | O12: 99 | P12: 258 | Q12: 4407.624 | R12: =P12/O12 -> 2.6060606 | S12: =Q12/P12 -> 17.083814 | T12: 841.152 | U12: 841.152 | V12: 0.1908 | X12: 543 | Y12: 56067 | Z12: 126427.76 | AA12: 8925.904 | AB12: 8925.904 | AC12: 0.0706 | AE12: TICKET MÉDIO | AF12: TOTAL DE CLIENTES | AG12: CLIENTES FRIOS | AH12: FTD (Priméiro depósito) | AI12: CHURN (taxa de Inativos) | AJ12: LTV (Valor do tempo de vida do cliente) | AK12: CAC. (Custo Aquisição) | AL12: Total de Investimento | AM12: ROI (Retorno de Investimento
A13: 45079 | B13: 23097.048 | C13: 751 | D13: =B13/C13 -> 30.755057 | E13: 13580.424 | F13: 153 | G13: 165 | H13: 124 | I13: 614 | J13: 178186.32 | K13: 9396.66 | L13: 9396.66 | M13: 0.0527 | O13: 65 | P13: 202 | Q13: 4458.792 | R13: =P13/O13 -> 3.1076923 | S13: =Q13/P13 -> 22.073228 | T13: 1534.26 | U13: 1534.26 | V13: 0.3441 | X13: 434 | Y13: 38859 | Z13: 173727.53 | AA13: 7862.4 | AB13: 7862.4 | AC13: 0.0453 | AE13: =D42 -> 30.201394 | AF13: =G42 -> 15470 | AG13: =AF13-AH13 -> 6562 | AH13: =H42 -> 8908 | AI13: =AG13/AF13 -> 0.42417582 | AJ13: =AE13*2*1 -> 60.402788 | AK13: =AL13/AH13 -> #REF! | AL13: ='CUSTOS 2023'!O3 -> #REF!
A14: 45080 | B14: 34566.844 | C14: 1036 | D14: =B14/C14 -> 33.36568 | E14: 10698.012 | F14: 174 | G14: 686 | H14: 371 | I14: 821 | J14: 238493.11 | K14: 12952.368 | L14: 12952.368 | M14: 0.0543 | O14: 80 | P14: 229 | Q14: 13307.112 | R14: =P14/O14 -> 2.8625 | S14: =Q14/P14 -> 58.109659 | T14: 4580.576 | U14: 4580.576 | V14: 0.3442 | X14: 362 | Y14: 45421 | Z14: 225186 | AA14: 8371.792 | AB14: 8371.792 | AC14: 0.0372
A15: 45081 | B15: 28641.184 | C15: 1180 | D15: =B15/C15 -> 24.27219 | E15: 23310.924 | F15: 226 | G15: 859 | H15: 477 | I15: 954 | J15: 220100.97 | K15: 8530.444 | L15: 8530.444 | M15: 0.0388 | O15: 75 | P15: 227 | Q15: 12111.008 | R15: =P15/O15 -> 3.0266667 | S15: =Q15/P15 -> 53.352458 | T15: 1971.372 | U15: 1971.372 | V15: 0.1628 | X15: 321 | Y15: 30938 | Z15: 207989.96 | AA15: 6559.072 | AB15: 6559.072 | AC15: 0.0315
A16: 45082 | B16: 22830.444 | C16: 1006 | D16: =B16/C16 -> 22.694278 | E16: 16832.712 | F16: 192 | G16: 397 | H16: 284 | I16: 842 | J16: 190477.04 | K16: 8874.476 | L16: 8874.476 | M16: 0.0466 | O16: 56 | P16: 134 | Q16: 5435.404 | R16: =P16/O16 -> 2.3928571 | S16: =Q16/P16 -> 40.562716 | T16: 470.548 | U16: 470.548 | V16: 0.0866 | X16: 339 | Y16: 38012 | Z16: 185041.64 | AA16: 8403.928 | AB16: 8403.928 | AC16: 0.0454
A17: 45083 | B17: 32063.2 | C17: 1416 | D17: =B17/C17 -> 22.643503 | E17: 20601.568 | F17: 250 | G17: 856 | H17: 525 | I17: 1116 | J17: 281815.25 | K17: 9889.36 | L17: 9889.36 | M17: 0.0351 | O17: 77 | P17: 208 | Q17: 4441.32 | R17: =P17/O17 -> 2.7012987 | S17: =Q17/P17 -> 21.3525 | T17: 2019.628 | U17: 2019.628 | V17: 0.4547 | X17: 527 | Y17: 62817 | Z17: 277373.93 | AA17: 7869.732 | AB17: 7869.732 | AC17: 0.0284
A18: 45084 | B18: 33016.1 | C18: 1319 | D18: =B18/C18 -> 25.03116 | E18: 22151.636 | F18: 251 | G18: 488 | H18: 382 | I18: 1060 | J18: 239804.34 | K18: 13352.3 | L18: 13352.3 | M18: 0.0557 | O18: 92 | P18: 265 | Q18: 6599.684 | R18: =P18/O18 -> 2.8804348 | S18: =Q18/P18 -> 24.904468 | T18: 3165.656 | U18: 3165.656 | V18: 0.4797 | X18: 1417 | Y18: 105949 | Z18: 233204.66 | AA18: 10186.644 | AB18: 10186.644 | AC18: 0.0437
A19: 45085 | B19: 35398.792 | C19: 1209 | D19: =B19/C19 -> 29.279398 | E19: 24031.072 | F19: 280 | G19: 315 | H19: 248 | I19: 927 | J19: 328494.24 | K19: -1717.924 | L19: -1717.924 | M19: -0.0052 | O19: 103 | P19: 267 | Q19: 11292.996 | R19: =P19/O19 -> 2.592233 | S19: =Q19/P19 -> 42.295865 | T19: 5051.332 | U19: 5051.332 | V19: 0.4473 | X19: 1595 | Y19: 120281 | Z19: 317201.25 | AA19: -6769.256 | AB19: -6769.256 | AC19: -0.0213
A20: 45086 | B20: 33914.66 | C20: 1037 | D20: =B20/C20 -> 32.70459 | E20: 23535.096 | F20: 243 | G20: 320 | H20: 232 | I20: 764 | J20: 265204.52 | K20: 17148.976 | L20: 17148.976 | M20: 0.0647 | O20: 53 | P20: 143 | Q20: 13725.296 | R20: =P20/O20 -> 2.6981132 | S20: =Q20/P20 -> 95.981091 | T20: 6381.856 | U20: 6381.856 | V20: 0.465 | X20: 1465 | Y20: 102230 | Z20: 251479.23 | AA20: 10767.12 | AB20: 10767.12 | AC20: 0.0428
A21: 45087 | B21: 44821.192 | C21: 1393 | D21: =B21/C21 -> 32.176017 | E21: 31851.664 | F21: 289 | G21: 1005 | H21: 483 | I21: 1056 | J21: 260789.83 | K21: 18025.488 | L21: 18025.488 | M21: 0.0691 | O21: 191 | P21: 425 | Q21: 15552.316 | R21: =P21/O21 -> 2.2251309 | S21: =Q21/P21 -> 36.593685 | T21: 6374.732 | U21: 6374.732 | V21: 0.4099 | X21: 1502 | Y21: 98490 | Z21: 245237.51 | AA21: 11650.756 | AB21: 11650.756 | AC21: 0.0475
A22: 45088 | B22: 39681.668 | C22: 1208 | D22: =B22/C22 -> 32.849063 | E22: 22388.236 | F22: 262 | G22: 655 | H22: 342 | I22: 885 | J22: 239590.99 | K22: 8338.408 | L22: 8338.408 | M22: 0.0348 | O22: 133 | P22: 401 | Q22: 10034.648 | R22: =P22/O22 -> 3.0150376 | S22: =Q22/P22 -> 25.02406 | T22: -3208.816 | U22: -3208.816 | V22: -0.3198 | X22: 1109 | Y22: 94598 | Z22: 229556.34 | AA22: 11547.224 | AB22: 11547.224 | AC22: 0.0503
A23: 45089 | B23: 24457.732 | C23: 1088 | D23: =B23/C23 -> 22.479533 | E23: 21453.484 | F23: 239 | G23: 610 | H23: 342 | I23: 801 | J23: 219895.62 | K23: 5095.428 | L23: 5095.428 | M23: 0.0232 | O23: 42 | P23: 164 | Q23: 4482.816 | R23: =P23/O23 -> 3.9047619 | S23: =Q23/P23 -> 27.334244 | T23: 774.384 | U23: 774.384 | V23: 0.1727 | X23: 1216 | Y23: 85346 | Z23: 215412.81 | AA23: 4321.044 | AB23: 4321.044 | AC23: 0.0201
A24: 45090 | B24: 28122.536 | C24: 1431 | D24: =B24/C24 -> 19.652366 | E24: 21722.74 | F24: 295 | G24: 819 | H24: 474 | I24: 1029 | J24: 226291.31 | K24: 1383.096 | L24: 1383.096 | M24: 0.0061 | O24: 47 | P24: 225 | Q24: 20143.604 | R24: =P24/O24 -> 4.787234 | S24: =Q24/P24 -> 89.527129 | T24: -5244.616 | U24: -5244.616 | V24: -0.2604 | X24: 1507 | Y24: 96708 | Z24: 206147.71 | AA24: 6627.712 | AB24: 6627.712 | AC24: 0.0322
A25: 45091 | B25: 34132.956 | C25: 1306 | D25: =B25/C25 -> 26.135495 | E25: 29317.808 | F25: 260 | G25: 594 | H25: 368 | I25: 964 | J25: 237894.28 | K25: 4895.124 | L25: 4895.124 | M25: 0.0206 | O25: 47 | P25: 194 | Q25: 20451.652 | R25: =P25/O25 -> 4.1276596 | S25: =Q25/P25 -> 105.42089 | T25: -7820.228 | U25: -7820.228 | V25: -0.3824 | X25: 1690 | Y25: 94034 | Z25: 217442.63 | AA25: 12715.352 | AB25: 12715.352 | AC25: 0.0585
... A41: 45107 | B41: 46360.236 | C41: 1317 | D41: =B41/C41 -> 35.201394 | E41: 44533.996 | F41: 342 | G41: 439 | H41: 245 | I41: 818 | J41: 331804.29 | K41: 3754.4 | L41: 3754.4 | M41: 0.0113 | O41: 59 | P41: 166 | Q41: 16212.908 | R41: =P41/O41 -> 2.8135593 | S41: =Q41/P41 -> 97.66812 | T41: -79.222889 | U41: -79.222889 | V41: -0.0049 | X41: 2300 | Y41: 143911 | Z41: 315591.38 | AA41: 19799.728 | AB41: 19799.728 | AC41: 0.012147505
A42: TOTAL | B42: =SUM(B12:B41) -> 1096491.8 | C42: =SUM(C12:C41) -> 36306 | D42: =B42/C42 -> 30.201394 | E42: =SUM(E11:E41) -> 824149.35 | F42: =SUM(F12:F41) -> 8022 | G42: =SUM(G12:G41) -> 15470 | H42: =SUM(H12:H41) -> 8908 | I42: =MEDIAN(I12:I41) -> 840 | J42: =SUM(J12:J41) -> 7565002.8 | K42: =SUM(K12:K41) -> 270045.72 | L42: =AVERAGE(L12:L41) -> 9001.5241 | O42: =SUM(O11:O41) -> 2247 | P42: =SUM(P11:P41) -> 6840 | Q42: =SUM(Q12:Q41) -> 443462.38 | R42: =P42/O42 -> 3.0440587 | S42: =Q42/P42 -> 64.833681 | T42: =SUM(T12:T41) -> 30721.521 | U42: =SUM(AL7:AL37) -> #REF! | X42: =SUM(X12:X41) -> 41270 | Y42: =SUM(Y12:Y41) -> 3112086 | Z42: =SUM(Z12:Z41) -> 7121540.4 | AA42: =SUM(AA12:AA41) -> 255290.31 | AB42: =SUM(AB12:AB41) -> 255290.31 | AC42: =SUM(AS6:AS37) -> 0
A43: NETCASH | B43: DEPOSITOS | C43: QTD. DEP | D43: TICKET | E43: SAQUES | F43: QTD. SAQUES | G43: CONVERSÃO FTD | I43: MEDIA UAP | J43: TURNOVER | K43: GGR TOTAL | L43: MEDIA GGR | M43: MEDIA % | O43: LTV Sportingbook | P43: =S42*R42*1 -> 197.35753 | X43: LTV cassino
A44: =B42-E42 -> 272342.46 | G44: =H42/G42 -> 0.57582418 | O44: TICKET MÉDIO Sportingbook | P44: =S42 -> 64.833681 | X44: TICKET MÉDIO cassino
R60: ='TRÁFEGO'!E44 -> #REF! | S60: =SUM(P60:R60) -> #REF!
K61: Cadastros | R61: =G14 -> 686 | S61: =SUM(L61:R61) -> 686
K62: FTD | P62: =H12 -> 173 | Q62: =H13 -> 124 | R62: =H14 -> 371 | S62: =SUM(P62:R62) -> 668
L63: 4 | M63: 5 | N63: 6 | O63: 7 | P63: 8 | Q63: 9 | R63: 10 | S63: Total da Semana
K64: Promo | S64: =#REF! -> #REF!
K65: Mkt de Influ | S65: ='CUSTOS 2023'!T86 -> 18000
K66: Tráfego - Castelo | L66: ='TRÁFEGO'!E45 -> #REF! | M66: ='TRÁFEGO'!E46 -> #REF! | N66: ='TRÁFEGO'!E47 -> #REF! | O66: ='TRÁFEGO'!E48 -> #REF! | P66: ='TRÁFEGO'!E49 -> #REF! | Q66: ='TRÁFEGO'!E50 -> #REF! | R66: ='TRÁFEGO'!E51 -> #REF! | S66: =SUM(L66:R66) -> #REF!
K67: Cadastros | L67: =G15 -> 859 | M67: =G16 -> 397 | N67: =G17 -> 856 | O67: =G18 -> 488 | P67: =G19 -> 315 | Q67: =G20 -> 320 | R67: =G21 -> 1005 | S67: =SUM(L67:R67) -> 4240
K68: FTD | L68: =H15 -> 477 | M68: =H16 -> 284 | N68: =H17 -> 525 | O68: =H18 -> 382 | P68: =H19 -> 248 | Q68: =H20 -> 232 | R68: =H21 -> 483 | S68: =SUM(L68:R68) -> 2631
L69: 11 | M69: 12 | N69: 13 | O69: 14 | P69: 15 | Q69: 16 | R69: 17 | S69: Total da Semana
K70: Promo
K71: Mkt de Influ
K72: Tráfego - Castelo | L72: ='TRÁFEGO'!E52 -> #REF! | M72: ='TRÁFEGO'!E53 -> #REF! | N72: ='TRÁFEGO'!E54 -> #REF! | O72: ='TRÁFEGO'!E55 -> #REF! | P72: ='TRÁFEGO'!E56 -> #REF! | Q72: ='TRÁFEGO'!E57 -> #REF! | R72: ='TRÁFEGO'!E58 -> #REF! | S72: =SUM(L72:R72) -> #REF!
K73: Cadastros | L73: =G22 -> 655 | M73: =G23 -> 610 | N73: =G24 -> 819 | O73: =G25 -> 594 | P73: =G26 -> 1009 | Q73: =G27 -> 588 | R73: =G28 -> 698 | S73: =SUM(L73:R73) -> 4973
K74: FTD | L74: =H22 -> 342 | M74: =H23 -> 342 | N74: =H24 -> 474 | O74: =H25 -> 368 | P74: =H26 -> 495 | Q74: =H27 -> 352 | R74: =H28 -> 433 | S74: =SUM(L74:R74) -> 2806
L75: 18 | M75: 19 | N75: 20 | O75: 21 | P75: 22 | Q75: 23 | R75: 24 | S75: Total da Semana
K76: Promo
K77: Mkt de Influ
K78: Tráfego - Castelo | L78: ='TRÁFEGO'!E59 -> #REF! | M78: ='TRÁFEGO'!E60 -> #REF! | N78: ='TRÁFEGO'!E61 -> #REF! | O78: ='TRÁFEGO'!E62 -> #REF! | P78: ='TRÁFEGO'!E63 -> #REF! | Q78: ='TRÁFEGO'!E64 -> #REF! | R78: ='TRÁFEGO'!E65 -> #REF! | S78: =SUM(L78:R78) -> #REF!
K79: Cadastros | L79: =G29 -> 316 | M79: =G30 -> 282 | N79: =G31 -> 239 | O79: =G32 -> 276 | P79: =G33 -> 435 | Q79: =G34 -> 455 | R79: =G35 -> 306 | S79: =SUM(L79:R79) -> 2309
K80: FTD | L80: =H29 -> 241 | M80: =H30 -> 187 | N80: =H31 -> 172 | O80: =H32 -> 192 | P80: =H33 -> 270 | Q80: =H34 -> 262 | R80: =H35 -> 204 | S80: =SUM(L80:R80) -> 1528
L81: 25 | M81: 26 | N81: 27 | O81: 28 | P81: 29 | Q81: 30 | S81: Total da Semana
K82: Promo
K83: Mkt de Influ
K84: Tráfego - Castelo | L84: ='TRÁFEGO'!E66 -> #REF! | M84: ='TRÁFEGO'!E67 -> #REF! | N84: ='TRÁFEGO'!E68 -> #REF! | O84: ='TRÁFEGO'!E69 -> #REF! | P84: ='TRÁFEGO'!E70 -> #REF! | S84: =SUM(L84:R84) -> #REF!
K85: Cadastros | L85: =G36 -> 213 | M85: =G37 -> 324 | N85: =G38 -> 820 | O85: =G39 -> 528 | P85: =G40 -> 316 | Q85: =G41 -> 439
K86: FTD | L86: =H36 -> 138 | M86: =H37 -> 176 | N86: =H38 -> 329 | O86: =H39 -> 226 | P86: =H40 -> 161 | Q86: =H41 -> 245 | S86: =SUM(L86:R86) -> 1275

Sheet MAIO
B9: TERMÔMETRO | AG9: MAIO
B10: DEPÓSITO | E10: SAQUES | H10: GERAL | O10: Sportsbook | Y10: Cassino
A11: DATA | B11: Total | C11: Quantidade | D11: Ticket | E11: Total | F11: Quantidade | G11: REGISTROS | H11: FTD | I11: UAP | J11: TURNOVER | K11: GGR | L11: NGR | M11: GGR% | O11: UAP | P11: Número de Bets | Q11: TURNOVER | R11: Média de Aposta por Usuário | S11: Valor médio de aposta por usuário | T11: GGR | U11: NGR | V11: GGR% | X11: UAP | Y11: Número de Giros | Z11: TURNOVER | AA11: Vezes de start nos jogos por usuário | AB11: valor de Start por giro | AC11: GGR | AD11: NGR | AE11: GGR%
A12: 45047 | B12: 0.00 | C12: 0 | D12: 0.00 | E12: 0.00 | F12: 0 | G12: 0 | H12: 0 | I12: 411 | J12: 0 | K12: 0 | L12: 0 | M12: 0.0367 | O12: 0 | P12: 0 | Q12: 0.00 | R12: =P12/O12 -> #DIV/0! | S12: =Q12/P12 -> #VALUE! | T12: 0.00 | U12: 0 | V12: 0.00% | X12: 0 | Y12: 0 | Z12: 0.00 | AA12: =Y12/X12 -> #DIV/0! | AB12: =Z12/Y12 -> #VALUE! | AC12: 0.00 | AD12: 0 | AE12: 0.00% | AG12: TICKET MÉDIO | AH12: TOTAL DE CLIENTES | AI12: CLIENTES FRIOS | AJ12: FTD (Priméiro depósito) | AK12: CHURN (taxa de Inativos) | AL12: LTV (Valor do tempo de vida do cliente) | AM12: CAC. (Custo Aquisição) | AN12: Total de Investimento | AO12: ROI (Retorno de Investimento
A13: 45048 | B13: 0.00 | C13: 0 | D13: 0.00 | E13: 0.00 | F13: 0 | G13: 5 | H13: 0 | I13: 482 | J13: 0 | K13: 0 | L13: 0 | M13: 0.0283 | O13: 0 | P13: 0 | Q13: 0.00 | R13: =P13/O13 -> #DIV/0! | S13: =Q13/P13 -> #VALUE! | T13: 0.00 | U13: 0 | V13: 0.00% | X13: 0 | Y13: 0 | Z13: 0.00 | AA13: =Y13/X13 -> #DIV/0! | AB13: =Z13/Y13 -> #VALUE! | AC13: 0.00 | AD13: 0 | AE13: 0.00% | AG13: =D43 -> 21.667949 | AH13: =SUM(G43) -> 22726 | AI13: =AH13-AJ13 -> 11298 | AJ13: =H43 -> 11428 | AK13: =AI13/AH13 -> 0.49713984 | AL13: =AG13*2*1 -> 43.335898 | AM13: =AN13/AJ13 -> #REF! | AN13: ='CUSTOS 2023'!J3 -> #REF!
A14: 45049 | B14: 178.1 | C14: 6 | D14: =B14/C14 -> 29.683333 | E14: 0 | F14: 0 | G14: 9 | H14: 6 | I14: 643 | J14: 1703.104 | K14: 100.308 | L14: 100.308 | M14: 0.0331 | O14: 0 | P14: 0 | Q14: 0.00 | R14: =P14/O14 -> #DIV/0! | S14: =Q14/P14 -> #VALUE! | T14: 0.00 | U14: 0 | V14: 0.00% | X14: 5 | Y14: 45 | Z14: 1703.104 | AA14: =Y14/X14 -> 9 | AB14: =Z14/Y14 -> 37.846756 | AC14: 100.308 | AD14: 100.308 | AE14: 0.0589
A15: 45050 | B15: 857.428 | C15: 53 | D15: =B15/C15 -> 16.177887 | E15: 135.72 | F15: 4 | G15: 127 | H15: 45 | I15: 725 | J15: 2569.684 | K15: 537.264 | L15: 537.264 | M15: 0.0193 | O15: 1 | P15: 1 | Q15: 1.82 | R15: =P15/O15 -> 1 | S15: =Q15/P15 -> 1.82 | T15: 1.82 | U15: 1.82 | V15: 1 | X15: 44 | Y15: 1162 | Z15: 2567.864 | AA15: =Y15/X15 -> 26.409091 | AB15: =Z15/Y15 -> 2.2098657 | AC15: 535.444 | AD15: 535.444 | AE15: 0.2085
A16: 45051 | B16: 2219.516 | C16: 179 | D16: =B16/C16 -> 12.399531 | E16: 1024.504 | F16: 45 | G16: 271 | H16: 131 | I16: 641 | J16: 15221.856 | K16: 581.828 | L16: 581.828 | M16: 0.0849 | O16: 2 | P16: 2 | Q16: 4.264 | R16: =P16/O16 -> 1 | S16: =Q16/P16 -> 2.132 | T16: 4.264 | U16: 4.264 | V16: 1 | X16: 142 | Y16: 7424 | Z16: 15217.592 | AA16: =Y16/X16 -> 52.28169 | AB16: =Z16/Y16 -> 2.0497834 | AC16: 577.564 | AD16: 577.564 | AE16: 0.038
A17: 45052 | B17: 5887.648 | C17: 460 | D17: =B17/C17 -> 12.799235 | E17: 2628.132 | F17: 95 | G17: 463 | H17: 294 | I17: 939 | J17: 40561.872 | K17: 2574.624 | L17: 2574.624 | M17: 0.0325 | O17: 8 | P17: 17 | Q17: 111.54 | R17: =P17/O17 -> 2.125 | S17: =Q17/P17 -> 6.5611765 | T17: 52.26 | U17: 52.26 | V17: 0.4684 | X17: 334 | Y17: 16231 | Z17: 40450.332 | AA17: =Y17/X17 -> 48.595808 | AB17: =Z17/Y17 -> 2.4921651 | AC17: 2522.364 | AD17: 2522.364 | AE17: 0.0624
A18: 45053 | B18: 8745.828 | C18: 598 | D18: =B18/C18 -> 14.62513 | E18: 5252.416 | F18: 135 | G18: 683 | H18: 345 | I18: 975 | J18: 68567.148 | K18: 2425.956 | L18: 2425.956 | M18: 0.0454 | O18: 9 | P18: 13 | Q18: 85.696 | R18: =P18/O18 -> 1.4444444 | S18: =Q18/P18 -> 6.592 | T18: 58.656 | U18: 58.656 | V18: 0.6845 | X18: 445 | Y18: 23032 | Z18: 68481.452 | AA18: =Y18/X18 -> 51.757303 | AB18: =Z18/Y18 -> 2.9733176 | AC18: 2367.3 | AD18: 2367.3 | AE18: 0.0346
A19: 45054 | B19: 9804.86 | C19: 616 | D19: =B19/C19 -> 15.916981 | E19: 5180.916 | F19: 122 | G19: 671 | H19: 353 | I19: 1003 | J19: 83357.352 | K19: 4310.54 | L19: 4310.54 | M19: 0.0546 | O19: 11 | P19: 24 | Q19: 86.06 | R19: =P19/O19 -> 2.1818182 | S19: =Q19/P19 -> 3.5858333 | T19: 12.012 | U19: 12.012 | V19: 0.1396 | X19: 485 | Y19: 33628 | Z19: 83271.292 | AA19: =Y19/X19 -> 69.336082 | AB19: =Z19/Y19 -> 2.4762487 | AC19: 4298.528 | AD19: 4298.528 | AE19: 0.0516
A20: 45055 | B20: 14721.2 | C20: 950 | D20: =B20/C20 -> 15.496 | E20: 7638.072 | F20: 180 | G20: 824 | H20: 500 | I20: 1087 | J20: 141863.49 | K20: 5283.46 | L20: 5283.46 | M20: 0.0347 | O20: 21 | P20: 44 | Q20: 164.684 | R20: =P20/O20 -> 2.0952381 | S20: =Q20/P20 -> 3.7428182 | T20: 29.12 | U20: 29.12 | V20: 0.1769 | X20: 689 | Y20: 51472 | Z20: 141698.8 | AA20: =Y20/X20 -> 74.70537 | AB20: =Z20/Y20 -> 2.7529298 | AC20: 5254.34 | AD20: 5254.34 | AE20: 0.0371
A21: 45056 | B21: 11804.52 | C21: 787 | D21: =B21/C21 -> 14.99939 | E21: 4920.708 | F21: 131 | G21: 690 | H21: 375 | I21: 987 | J21: 118347.84 | K21: 3872.596 | L21: 3872.596 | M21: 0.0411 | O21: 29 | P21: 61 | Q21: 256.048 | R21: =P21/O21 -> 2.1034483 | S21: =Q21/P21 -> 4.1975082 | T21: -180.18 | U21: -180.18 | V21: -0.7036 | X21: 624 | Y21: 51934 | Z21: 118091.79 | AA21: =Y21/X21 -> 83.227564 | AB21: =Z21/Y21 -> 2.2738821 | AC21: 4052.776 | AD21: 4052.776 | AE21: 0.0343
A22: 45057 | B22: 8813.376 | C22: 645 | D22: =B22/C22 -> 13.664149 | E22: 5048.16 | F22: 123 | G22: 569 | H22: 315 | I22: 954 | J22: 98034.716 | K22: 5968.196 | L22: 5968.196 | M22: 0.0477 | O22: 28 | P22: 62 | Q22: 959.348 | R22: =P22/O22 -> 2.2142857 | S22: =Q22/P22 -> 15.473355 | T22: 0.468 | U22: 0.468 | V22: 0.0005 | X22: 563 | Y22: 36684 | Z22: 97075.368 | AA22: =Y22/X22 -> 65.158082 | AB22: =Z22/Y22 -> 2.6462591 | AC22: 5967.728 | AD22: 5967.728 | AE22: 0.0615
A23: 45058 | B23: 7809.828 | C23: 516 | D23: =B23/C23 -> 15.135326 | E23: 3736.928 | F23: 94 | G23: 393 | H23: 233 | I23: 866 | J23: 84652.984 | K23: 3529.604 | L23: 3529.604 | M23: 0.0575 | O23: 9 | P23: 12 | Q23: 70.616 | R23: =P23/O23 -> 1.3333333 | S23: =Q23/P23 -> 5.8846667 | T23: 55.432 | U23: 55.432 | V23: 0.7851 | X23: 469 | Y23: 36051 | Z23: 84582.368 | AA23: =Y23/X23 -> 76.867804 | AB23: =Z23/Y23 -> 2.3461865 | AC23: 3474.172 | AD23: 3474.172 | AE23: 0.0411
A24: 45059 | B24: 7561.788 | C24: 603 | D24: =B24/C24 -> 12.540279 | E24: 4528.108 | F24: 115 | G24: 525 | H24: 295 | I24: 968 | J24: 86577.868 | K24: 2662.348 | L24: 2662.348 | M24: 0.0342 | O24: 25 | P24: 61 | Q24: 457.08 | R24: =P24/O24 -> 2.44 | S24: =Q24/P24 -> 7.4931148 | T24: 83.98 | U24: 83.98 | V24: 0.1837 | X24: 508 | Y24: 45394 | Z24: 86120.788 | AA24: =Y24/X24 -> 89.358268 | AB24: =Z24/Y24 -> 1.8971844 | AC24: 2578.368 | AD24: 2578.368 | AE24: 0.0299
A25: 45060 | B25: 6755.788 | C25: 530 | D25: =B25/C25 -> 12.74677 | E25: 3008.512 | F25: 93 | G25: 501 | H25: 264 | I25: 889 | J25: 80677.324 | K25: 2658.968 | L25: 2658.968 | M25: 0.008 | O25: 22 | P25: 52 | Q25: 275.652 | R25: =P25/O25 -> 2.3636364 | S25: =Q25/P25 -> 5.301 | T25: 44.356 | U25: 44.356 | V25: 0.1609 | X25: 492 | Y25: 37424 | Z25: 80401.672 | AA25: =Y25/X25 -> 76.065041 | AB25: =Z25/Y25 -> 2.1483987 | AC25: 2614.612 | AD25: 2614.612 | AE25: 0.0325
A26: 45061 | B26: 8743.436 | C26: 620 | D26: =B26/C26 -> 14.102316 | E26: 5086.9 | F26: 115 | G26: 560 | H26: 295 | I26: 913 | J26: 95596.956 | K26: 2526.368 | L26: 2526.368 | M26: 0.0462 | O26: 10 | P26: 29 | Q26: 67.912 | R26: =P26/O26 -> 2.9 | S26: =Q26/P26 -> 2.3417931 | T26: 38.584 | U26: 38.584 | V26: 0.5684 | X26: 548 | Y26: 43077 | Z26: 95529.044 | AA26: =Y26/X26 -> 78.607664 | AB26: =Z26/Y26 -> 2.2176346 | AC26: 2487.784 | AD26: 2487.784 | AE26: 0.026
... A42: 45077 | B42: 30580.212 | C42: 882 | D42: =B42/C42 -> 34.671442 | E42: 10112.336 | F42: 143 | G42: 316 | H42: 178 | I42: 511 | J42: 170520.58 | K42: 19101.68 | L42: 19101.68 | M42: 0.0461 | O42: 91 | P42: 299 | Q42: 15143.908 | R42: =P42/O42 -> 3.2857143 | S42: =Q42/P42 -> 50.648522 | T42: 8315.112 | U42: 8315.112 | V42: 0.5491 | X42: 650 | Y42: 70171 | Z42: 155376.68 | AA42: =Y42/X42 -> 107.95538 | AB42: =Z42/Y42 -> 2.2142577 | AC42: 10786.568 | AD42: 10786.568 | AE42: 0.0694
A43: TOTAL | B43: =SUM(B12:B42,B12,B12) -> 583192.84 | C43: =SUM(C12:C42) -> 26915 | D43: =B43/C43 -> 21.667949 | E43: =SUM(E12:E42) -> 352874.18 | F43: =SUM(F12:F42) -> 5172 | G43: =SUM(G12:G42) -> 22726 | H43: =SUM(H12:H42) -> 11428 | I43: =MEDIAN(I11:I42) -> 764 | J43: =SUM(J12:J42) -> 4936118.2 | K43: =SUM(K12:K42) -> 207193.43 | L43: =AVERAGE(L12:L42) -> 6683.659 | M43: =AVERAGE(M12:M42) -> 0.039319355 | O43: =SUM(O11:O42) -> 1940 | P43: =SUM(P12:P42) -> 5013 | Q43: =SUM(Q12:Q42) -> 116374.54 | R43: =P43/O43 -> 2.5840206 | S43: =Q43/P43 -> 23.214551 | T43: =SUM(T12:T42) -> 17638.348 | U43: =SUM(U12:U42) -> 17638.348 | X43: =SUM(X11:X42) -> 21042 | Y43: =SUM(Y11:Y42) -> 1872553 | Z43: =SUM(Z11:Z42) -> 4819743.7 | AA43: =AVERAGE(AA18:AA42) -> 87.671167 | AB43: =Z43/Y43 -> 2.573889 | AC43: =SUM(AC12:AC42) -> 189555.08 | AD43: =SUM(AD11:AD42) -> 189555.08
A44: NETCASH | B44: DEPOSITOS | C44: QTD. DEP | D44: TICKET | E44: SAQUES | F44: QTD. SAQUES | G44: CONVERSÃO FTD | I44: MEDIA UAP | J44: TURNOVER | K44: GGR TOTAL | L44: MEDIA GGR | M44: MEDIA % | O44: LTV Sportingbook | P44: =R43*S43*1 -> 59.986878 | X44: LTV Cassino | Y44: =AA43*AB43*1 -> 225.65586
A45: =B43-E43 -> 230318.66 | G45: =H43/G43 -> 0.50286016 | O45: TICKET MÉDIO Sportingbook | P45: =U43 -> 17638.348 | X45: TICKET MÉDIO Cassino | Y45: =AD43 -> 189555.08
N61: Tráfego - Castelo | P61: ='TRÁFEGO'!C42 -> #REF! | Q61: ='TRÁFEGO'!C43 -> #REF! | R61: ='TRÁFEGO'!C44 -> #REF! | S61: ='TRÁFEGO'!C45 -> #REF! | T61: ='TRÁFEGO'!C46 -> #REF! | U61: ='TRÁFEGO'!C47 -> #REF! | V61: =SUM(S61:U61) -> #REF!
N62: Cadastros | P62: =G12 -> 0 | Q62: =G13 -> 5 | R62: =G14 -> 9 | S62: =G15 -> 127 | T62: =G16 -> 271 | U62: =G17 -> 463 | V62: =SUM(O62:U62) -> 875
N63: FTD | P63: =H12 -> 0 | Q63: =H13 -> 0 | R63: =H14 -> 6 | S63: =H15 -> 45 | T63: =H16 -> 131 | U63: =H17 -> 294 | V63: =SUM(S63:U63) -> 470
O64: 7 | P64: 8 | Q64: 9 | R64: 10 | S64: 11 | T64: 12 | U64: 13 | V64: Total da Semana
N65: Promo
N66: Mkt de Influ
N67: Tráfego - Castelo | O67: ='TRÁFEGO'!C48 -> #REF! | P67: ='TRÁFEGO'!C49 -> #REF! | Q67: ='TRÁFEGO'!C50 -> #REF! | R67: ='TRÁFEGO'!C51 -> #REF! | S67: ='TRÁFEGO'!C52 -> #REF! | T67: ='TRÁFEGO'!C53 -> #REF! | U67: ='TRÁFEGO'!C54 -> #REF! | V67: =SUM(O67:U67) -> #REF!
N68: Cadastros | O68: =G18 -> 683 | P68: =G19 -> 671 | Q68: =G20 -> 824 | R68: =G21 -> 690 | S68: =G22 -> 569 | T68: =G23 -> 393 | U68: =G24 -> 525 | V68: =SUM(O68:U68) -> 4355
N69: FTD | O69: =H18 -> 345 | P69: =H19 -> 353 | Q69: 623 | R69: =H21 -> 375 | S69: =H22 -> 315 | T69: =H23 -> 233 | U69: =H24 -> 295 | V69: =SUM(O69:U69) -> 2539
O70: 14 | P70: 15 | Q70: 16 | R70: 17 | S70: 18 | T70: 19 | U70: 20 | V70: Total da Semana
N71: Promo
N72: Mkt de Influ
N73: Tráfego - Castelo | O73: ='TRÁFEGO'!C55 -> #REF! | P73: ='TRÁFEGO'!C56 -> #REF! | Q73: ='TRÁFEGO'!C57 -> #REF! | R73: ='TRÁFEGO'!C57 -> #REF! | S73: ='TRÁFEGO'!C58 -> #REF! | T73: ='TRÁFEGO'!C59 -> #REF! | U73: ='TRÁFEGO'!C60 -> #REF! | V73: =SUM(O73:U73) -> #REF!
N74: Cadastros | O74: =G25 -> 501 | P74: =G26 -> 560 | Q74: =G27 -> 2830 | R74: =G28 -> 3615 | S74: =G29 -> 957 | T74: =G30 -> 745 | U74: =G31 -> 660 | V74: =SUM(O74:U74) -> 9868
N75: FTD | O75: =H25 -> 264 | P75: =H26 -> 295 | Q75: =H27 -> 874 | R75: =H28 -> 1279 | S75: =H29 -> 546 | T75: =H30 -> 441 | U75: =H31 -> 428 | V75: =SUM(O75:U75) -> 4127
O76: 21 | P76: 22 | Q76: 23 | R76: 24 | S76: 25 | T76: 26 | U76: 27 | V76: Total da Semana
N77: Promo
N78: Mkt de Influ
N79: Tráfego - Castelo | O79: ='TRÁFEGO'!C61 -> #REF! | P79: ='TRÁFEGO'!C62 -> #REF! | Q79: ='TRÁFEGO'!C63 -> #REF! | R79: ='TRÁFEGO'!C64 -> #REF! | S79: ='TRÁFEGO'!C65 -> #REF! | T79: ='TRÁFEGO'!C66 -> #REF! | U79: ='TRÁFEGO'!C68 -> #REF! | V79: =SUM(O79:U79) -> #REF!
N80: Cadastros | O80: =G32 -> 899 | P80: =G33 -> 1248 | Q80: =G34 -> 854 | R80: =G35 -> 760 | S80: =G36 -> 649 | T80: =G37 -> 692 | U80: =G38 -> 677 | V80: =SUM(O80:U80) -> 5779
N81: FTD | O81: =H32 -> 502 | P81: =H33 -> 708 | Q81: =H34 -> 499 | R81: =H35 -> 435 | S81: =H36 -> 389 | T81: =H37 -> 382 | U81: =H38 -> 423 | V81: =SUM(O81:U81) -> 3338
O82: 28 | P82: 29 | Q82: 30 | R82: 31 | V82: Total da Semana
N83: Promo
N84: Mkt de Influ
N85: Tráfego - Castelo | O85: ='TRÁFEGO'!C69 -> #REF! | P85: ='TRÁFEGO'!C70 -> #REF! | Q85: ='TRÁFEGO'!C71 -> #REF! | R85: ='TRÁFEGO'!C72 -> #REF! | V85: =SUM(O85:U85) -> #REF!
N86: Cadastros | O86: =G39 -> 443 | P86: =G40 -> 586 | Q86: =G41 -> 504 | R86: =G42 -> 316
N87: FTD | O87: =H39 -> 280 | P87: =H40 -> 303 | Q87: =H41 -> 310 | R87: =H42 -> 178 | V87: =SUM(O87:U87) -> 1071

Sheet CUSTOS 2023
B2: Abril | G2: Maio | L2: Junho | Q2: Julho | V2: Agosto | AA2: Setembro | AF2: Outubro | AK2: Novembro | AP2: Dezembro | AT2: Nov | AY2: Dezembro
C3: Total Geral: | E3: =E4+E5 -> 222199.95 | H3: Total Geral: | J3: =J4+J5 -> #REF! | M3: Total Geral: | O3: =O4+O5 -> #REF! | R3: Total Geral: | T3: =T4+T5 -> #REF! | W3: Total Geral: | Y3: =Y4+Y5 -> 512368.91 | AB3: Total Geral: | AD3: =AD4+AD5 -> 545280.8 | AG3: Total Geral: | AI3: =sum(AI6,AI16,AI24,AI36,AI43,AI47,AI52,AI59,AI66,AI85,AI94) -> #REF! | AL3: Total Geral: | AN3: =SUM(AN6,AN16,AN24,AN36,AN43,AN47,AN52,AN59,AN66,AN85,AN94) -> #REF! | AQ3: Total Geral: | AS3: =AS4+AS5 -> #REF! | AT3: =SUM(AT6,AT16,AT24,AT36,AT85,AT94) -> 117249.71 | AW3: Total Geral: | AY3: =SUM(AY6,AY16,AY24,AY36,AY85,AY94) -> 121249.71
C4: Total Operacional | E4: =SUM(E6,E16,E24,E36) -> 31500 | H4: Total Operacional | J4: =SUM(J6,J16,J24,J36) -> 118795.84 | M4: Total Operacional | O4: =SUM(O6,O16,O24,O36) -> 168581.43 | R4: Total Operacional | T4: =SUM(T6,T16,T24,T36) -> 234346.54 | W4: Total Operacional | Y4: =SUM(Y6,Y16,Y24,Y36) -> 211115.91 | AB4: Total Operacional | AD4: =SUM(AD6,AD16,AD24,AD36) -> 310550.8 | AG4: Total Operacional | AI4: =SUM(AI6,AI16,AI24,AI36) -> 327139.59 | AL4: Total Operacional | AN4: =SUM(AN6,AN16,AN24,AN36) -> 486523.02 | AQ4: Total Operacional | AS4: =SUM(AS6,AS16,AS24,AS36,AS85) -> 522414.52 | AT4: =SUM(AT6,AT16,AT24,AT36) -> 117249.71 | AW4: Total Operacional | AY4: =SUM(AY6,AY16,AY24,AY36) -> 121249.71
C5: Total Ações | E5: =SUM(E43,E47,E52,E59,E66,E85) -> 190699.95 | H5: Total Ações | J5: =SUM(J43,J47,J52,J59,J66,J85) -> #REF! | M5: Total Ações | O5: =SUM(O43,O47,O52,O59,O66,O85) -> #REF! | R5: Total Ações | T5: =SUM(T43,T47,T52,T59,T66,T85) -> #REF! | W5: Total Ações | Y5: =SUM(Y43,Y47,Y52,Y59,Y66,Y85) -> 301253 | AB5: Total Ações | AD5: =SUM(AD43,AD47,AD52,AD59,AD66,AD85) -> 234730 | AG5: Total Ações | AI5: =SUM(AI43,AI47,AI52,AI59,AI66,AI85,AI94) -> #REF! | AL5: Total Ações | AN5: =SUM(AN43,AN47,AN52,AN59,AN66,AN85,AN94) -> #REF! | AQ5: Total Ações | AS5: =SUM(AS43,AS47,AS52,AS59,AS66,AS85,AS94) -> #REF! | AT5: =SUM(AT43,AT47,AT52,AT59,AT66,AT85) -> 4650 | AW5: Total Ações | AY5: =SUM(AY43,AY47,AY52,AY59,AY66,AY85) -> 4650
B6: DATA | C6: Total : | D6: Status | E6: =SUM(E7:E15) -> 30000 | G6: DATA | H6: Total : | I6: Status | J6: =SUM(J7:J15) -> 32400 | L6: DATA | M6: Total : | N6: Status | O6: =SUM(O7:O15) -> 40825 | Q6: DATA | R6: Total : | S6: Status | T6: =SUM(T7:T15) -> 42500 | V6: DATA | W6: Total : | X6: Status | Y6: =SUM(Y7:Y15) -> 45500 | AA6: DATA | AB6: Total : | AC6: Status | AD6: =SUM(AD7:AD15) -> 49500 | AF6: DATA | AG6: Total : | AH6: Status | AI6: =SUM(AI7:AI11) -> 59500 | AK6: DATA | AL6: Total : | AM6: Status | AN6: =SUM(AN7:AN15) -> 79000 | AP6: DATA | AQ6: Total : | AR6: Status | AS6: =SUM(AS7:AS15) -> 61500 | AT6: =SUM(AT7:AT15) -> 53000 | AV6: DATA | AW6: Total : | AX6: Status | AY6: =SUM(AY7:AY15) -> 53000
A7: Equipe CASA | B7: 45046 | C7: Harrison - CEO | D7: Ok | E7: 30000 | F7: Equipe CASA | G7: 45051 | H7: Harrison - CEO | I7: Ok | J7: 30000 | K7: Equipe CASA | L7: 45082 | M7: Harrison - CEO | N7: Ok | O7: 30000 | P7: Equipe CASA | Q7: 45112 | R7: Harrison - CEO | S7: Ok | T7: 30000 | U7: Equipe CASA | V7: 45139 | W7: Harrison - CEO | X7: Ok | Y7: 30000 | Z7: Equipe CASA | AA7: 45174 | AB7: Harrison - CEO | AC7: Ok | AD7: 30000 | AE7: Equipe CASA | AF7: 45204 | AG7: Harrison - CEO | AH7: Ok | AI7: 30000 | AJ7: Equipe CASA | AK7: 45235 | AL7: Harrison - CEO | AM7: Ok | AN7: 30000 | AO7: Equipe CASA | AP7: 45265 | AQ7: Harrison - CEO | AR7: Ok | AS7: 30000 | AT7: 30000 | AU7: Equipe CASA | AV7: 45170 | AW7: Harrison | AY7: 30000
G8: 45051 | H8: Apresentadora | I8: Ok | J8: 2000 | L8: 45082 | M8: Joanderson | N8: Ok | O8: 2500 | Q8: 45112 | R8: Joanderson | S8: Ok | T8: 2000 | V8: 45139 | W8: Joanderson - SM | X8: Ok | Y8: 2000 | AA8: 45174 | AB8: Joanderson - SM | AC8: Ok | AD8: 2000 | AF8: 45204 | AG8: Arthur - Design | AH8: Ok | AI8: 3500 | AK8: 45235 | AL8: Letícia - Diretora de mkt | AM8: Ok | AN8: 17000 | AP8: 45265 | AQ8: Letícia - Diretora de mkt | AR8: Ok | AS8: 17000 | AT8: 2000 | AV8: 45171 | AW8: Joanderson | AY8: 2000
B9: - | C9: - | E9: - | G9: 45051 | H9: Joanderson | I9: Ok | J9: 400 | L9: 45082 | M9: Apresentadora | N9: Ok | O9: 2200 | Q9: 45112 | R9: Apresentadora | S9: Ok | T9: 2000 | V9: 45139 | W9: Amanda - Apresentadora | X9: Ok | Y9: 2000 | AA9: 45174 | AB9: Amanda - Apresentadora | AC9: Ok | AD9: 2000 | AF9: 45204 | AG9: Letícia - Diretora de mkt | AH9: Ok | AI9: 17000 | AK9: 45235 | AL9: João Gabriel - Diretor arte | AM9: Ok | AN9: 8500 | AP9: 45265 | AQ9: João Gabriel - Diretor arte | AR9: Ok | AT9: 2000 | AV9: 45172 | AW9: Apresentadora | AY9: 2000
B10: - | C10: - | E10: - | G10: - | H10: - | J10: - | L10: 45082 | M10: Arthur da Silva | N10: Ok | O10: 6125 | Q10: 45112 | R10: Negueba (Lucas) | S10: Ok | T10: 5000 | V10: 45139 | W10: Negueba (Lucas) | X10: Ok | Y10: 5000 | AA10: 45174 | AB10: Arthur - Design | AC10: Ok | AD10: 3500 | AF10: 45204 | AG10: Giovanna - Gestora de Redes | AH10: Ok | AI10: 6000 | AK10: 45235 | AL10: Ewerson - CRM | AM10: Ok | AN10: 7000 | AP10: 45265 | AQ10: Ewerson - CRM | AR10: Ok | AS10: 3000 | AT10: 3500 | AV10: 45173 | AW10: Arthur | AY10: 3500
B11: - | C11: - | E11: - | G11: - | H11: - | J11: - | L11: - | M11: - | O11: - | Q11: 45112 | R11: Arthur da Silva | S11: Ok | T11: 3500 | V11: 45139 | W11: Letícia (proporcional) | X11: Ok | Y11: 3000 | AA11: 45174 | AB11: Letícia - Diretora de mkt | AC11: Ok | AD11: 12000 | AF11: 45204 | AG11: Guilherme - Social | AH11: Ok | AI11: 3000 | AK11: 45235 | AL11: Guilherme - Social | AM11: Ok | AN11: 3000 | AP11: 45265 | AQ11: Guilherme - Social | AR11: Ok | AS11: 3000 | AT11: 12000 | AV11: 45174 | AW11: Letícia | AY11: 12000
B12: - | C12: - | E12: - | G12: - | H12: - | J12: - | L12: - | M12: - | O12: - | Q12: 45124 | R12: Letícia | S12: Ok | T12: R$6.285 | V12: 45139 | W12: Arthur - Design | X12: Ok | Y12: 3500 | AF12: 45204 | AG12: Copy e Criativos - João zero | AH12: Ok | AI12: 5000 | AK12: 45235 | AL12: Giovanna - Gestora de Redes | AM12: Ok | AN12: 3000 | AP12: 45265 | AQ12: Giovanna - Gestora de Redes | AR12: Ok | AS12: 3000 | AT12: 3500 | AV12: 45175 | AW12: Lais | AY12: 3500
AK13: 45235 | AL13: Josyenne - Influ manager | AM13: Ok | AN13: 2000 | AP13: 45265 | AQ13: Josyenne - Influ manager | AR13: Ok | AS13: 2000
AK14: 45235 | AL14: João zero - Copy e Criativos | AM14: Ok | AN14: 5000 | AP14: 45265 | AQ14: João zero - Copy e Criativos | AR14: Ok
B15: - | C15: - | E15: - | G15: - | H15: - | J15: - | L15: - | M15: - | O15: - | Q15: - | R15: - | T15: - | V15: - | W15: - | Y15: - | AK15: 45235 | AL15: Arthur - Design | AM15: Ok | AN15: 3500 | AP15: 45265 | AQ15: Arthur - Design | AR15: Ok | AS15: 3500 | AV15: 45176
B16: DATA | C16: Total : | D16: Status | E16: =SUM(E17:E23) -> 1500 | G16: DATA | H16: Total : | I16: Status | J16: =SUM(J17:J23) -> 11500 | L16: DATA | M16: Total : | N16: Status | O16: =SUM(O17:O23) -> 11500 | Q16: DATA | R16: Total : | S16: Status | T16: =SUM(T17:T23) -> 11500 | V16: DATA | W16: Total : | X16: Status | Y16: =SUM(Y17:Y23) -> 11500 | AA16: DATA | AB16: Total : | AC16: Status | AD16: =SUM(AD17:AD23) -> 22000 | AF16: DATA | AG16: Total : | AH16: Status | AI16: =SUM(AI17:AI23) -> 28500 | AK16: DATA | AL16: Total : | AM16: Status | AN16: =SUM(AN17:AN23) -> 32500 | AP16: DATA | AQ16: Total : | AR16: Status | AS16: =SUM(AS17:AS23) -> 31500 | AT16: =SUM(AT17:AT23) -> 22500 | AV16: DATA | AW16: Total : | AX16: Status | AY16: =SUM(AY17:AY23) -> 26500
A17: Serviço | B17: 45046 | C17: Oddsgate Manager - Fernando Lemos | D17: Ok | E17: 1500 | F17: Serviço | G17: 45051 | H17: SAC - Betassist | I17: Ok | J17: 10000 | K17: Serviço | L17: 45082 | M17: SAC - Betassist | N17: Ok | O17: 10000 | P17: Serviço | Q17: 45112 | R17: Suporte / Maria | S17: Ok | T17: 10000 | U17: Serviço | V17: 45139 | W17: SAC - Betassist | X17: Ok | Y17: 10000 | Z17: Serviço | AA17: 45170 | AB17: SAC - Betassist | AC17: Ok | AD17: 12000 | AE17: Serviço | AF17: 45175 | AG17: SAC - Betassist | AH17: Ok | AI17: 15000 | AJ17: Serviço | AK17: 45235 | AL17: SAC - Betassist | AM17: Ok | AN17: 15000 | AO17: Serviço | AP17: 45265 | AQ17: SAC - Betassist | AR17: Ok | AS17: 15000 | AT17: 20000 | AU17: Serviço | AV17: 45170 | AW17: Suporte / Maria | AY17: 20000
B18: - | C18: - | E18: - | G18: 45051 | H18: Oddsgate Manager - Fernando Lemos | I18: Ok | J18: 1500 | L18: 45082 | M18: Oddsgate Manager - Fernando Lemos | N18: Ok | O18: 1500 | Q18: 45112 | R18: Oddsgate Manager - Fernando Lemos | S18: Ok | T18: 1500 | V18: 45139 | W18: Oddsgate Manager - Fernando Lemos | X18: Ok | Y18: 1500 | AA18: 45170 | AB18: Fernando Lemos - Oddsgate Manager | AC18: Ok | AD18: 1500 | AF18: 45175 | AG18: Fernando Lemos - Oddsgate Manager | AH18: Ok | AI18: 5000 | AK18: 45235 | AL18: Fernando Lemos - Oddsgate Manager | AM18: Ok | AN18: 5000 | AP18: 45265 | AQ18: Fernando Lemos - Oddsgate Manager | AR18: Ok | AS18: 5000 | AT18: 1500 | AV18: 45170 | AW18: Plataforma / Nando | AY18: 1500
B19: - | C19: - | E19: - | G19: - | H19: - | J19: - | L19: - | M19: - | O19: - | Q19: - | R19: - | T19: - | V19: - | W19: - | Y19: - | AA19: 45170 | AB19: Vinicius jacobina - Cellexpert Manager | AC19: Ok | AD19: 5000 | AF19: 45175 | AG19: Vinicius jacobina - Cellexpert Manager | AH19: Ok | AI19: 5000 | AK19: 45235 | AL19: Vinicius jacobina - Cellexpert Manager | AM19: Ok | AN19: 5000 | AP19: 45265 | AQ19: Vinicius jacobina - Cellexpert Manager | AR19: Ok | AS19: 5000 | AT19: 1000 | AV19: 45170 | AW19: Serviço fialiados / Negueba | AY19: 5000
B20: - | C20: - | E20: - | G20: - | H20: - | J20: - | L20: - | M20: - | O20: - | Q20: - | R20: - | T20: - | V20: - | W20: - | Y20: - | AA20: 45170 | AB20: Lais - Afiliados Atendimento | AC20: Ok | AD20: 3500 | AF20: 45204 | AG20: Lais - Afiliados Atendimento | AH20: Ok | AI20: 3500 | AK20: 45235 | AL20: Lais - Afiliados Atendimento | AM20: Ok | AN20: 3500 | AP20: 45265 | AQ20: Lais - Afiliados Atendimento | AR20: Ok | AS20: 2500 | AT20: - | AV20: - | AW20: - | AY20: -
B21: - | C21: - | E21: - | G21: - | H21: - | J21: - | L21: - | M21: - | O21: - | Q21: - | R21: - | T21: - | V21: - | W21: - | Y21: - | AA21: - | AB21: - | AD21: - | AF21: - | AI21: - | AK21: 45235 | AL21: Matheus Dantas - Gestor de Trafego | AM21: Ok | AN21: 4000 | AP21: 45265 | AQ21: Matheus Dantas - Gestor de Trafego | AR21: Ok | AS21: 4000 | AT21: - | AV21: - | AW21: - | AY21: -
B22: - | C22: - | E22: - | G22: - | H22: - | J22: - | L22: - | M22: - | O22: - | Q22: - | R22: - | T22: - | V22: - | W22: - | Y22: - | AA22: - | AB22: - | AD22: - | AF22: - | AI22: - | AK22: - | AL22: - | AN22: - | AP22: - | AQ22: - | AS22: - | AT22: - | AV22: - | AW22: - | AY22: -
B23: - | C23: - | E23: - | G23: - | H23: - | J23: - | L23: - | M23: - | O23: - | Q23: - | R23: - | T23: - | V23: - | W23: - | AA23: - | AB23: - | AD23: - | AF23: - | AI23: - | AK23: - | AL23: - | AN23: - | AP23: - | AQ23: - | AS23: - | AT23: - | AV23: - | AW23: - | AY23: -
B24: DATA | C24: Total : | D24: Status | E24: =SUM(E25:E35) -> 0 | G24: DATA | H24: Total : | I24: Status | J24: =SUM(J25:J35) -> 71695.84 | L24: DATA | M24: Total : | N24: Status | O24: =SUM(O25:O35) -> 113056.43 | Q24: DATA | R24: Total : | S24: Status | T24: =SUM(T25:T35) -> 180346.54 | V24: DATA | W24: Total : | X24: Status | Y24: =SUM(Y25:Y35) -> 154115.91 | AA24: DATA | AB24: Total : | AC24: Status | AD24: =SUM(AD25:AD35) -> 239050.8 | AF24: DATA | AG24: Total : | AH24: Status | AI24: =SUM(AI25:AI35) -> 238175.59 | AK24: DATA | AL24: Total : | AM24: Status | AN24: =SUM(AN25:AN35) -> 347023.02 | AP24: DATA | AQ24: Total : | AR24: Status | AS24: =SUM(AS25:AS35) -> 401432.81 | AT24: =SUM(AT25:AT35) -> 29749.71 | AV24: DATA | AW24: Total : | AX24: Status | AY24: =SUM(AY25:AY35) -> 29749.71
A25: PlataformaS | F25: PlataformaS | G25: 45051 | H25: Sportsbook Revenue Share | I25: Ok | J25: 2897.48 | K25: PlataformaS | L25: 45082 | M25: Sportsbook Revenue Share | N25: Ok | O25: 5791.24 | P25: PlataformaS | Q25: 45112 | R25: Sportsbook Revenue Share | S25: Ok | T25: 3613.2 | U25: PlataformaS | V25: 45139 | W25: Casino Provider Fee | X25: Ok | Y25: 81854.54 | Z25: PlataformaS | AA25: 45189 | AB25: Casino Provider Fee | AC25: Ok | AD25: 135154.09 | AE25: PlataformaS | AF25: 45219 | AG25: Casino Provider Fee | AH25: Ok | AI25: 150692.09 | AJ25: PlataformaS | AK25: 45250 | AL25: Casino Provider Fee | AM25: Ok | AN25: 215142.79 | AO25: PlataformaS | AP25: 45280 | AQ25: Casino Provider Fee | AR25: A Vencer | AS25: 253585 | AU25: PlataformaS | AV25: 45139 | AW25: Casino Provider Fee
G26: 45051 | H26: Casino Provider Fee | I26: Ok | J26: 42049.02 | L26: 45082 | M26: Casino Provider Fee | N26: Ok | O26: 55595.3 | Q26: 45112 | R26: Casino Provider Fee | S26: Ok | T26: 108935.12 | V26: 45139 | W26: Sportsbook Revenue Share | X26: Ok | Y26: 3876.22 | AA26: 45189 | AB26: Sportsbook Revenue Share | AC26: Ok | AD26: 7271.9 | AF26: 45219 | AG26: Sportsbook Revenue Share | AH26: Ok | AI26: 5914.46 | AK26: 45250 | AL26: Sportsbook Revenue Share | AM26: Ok | AN26: 5801 | AP26: 45280 | AQ26: Sportsbook Revenue Share | AR26: A Vencer | AS26: 14747 | AV26: 45139 | AW26: Sportsbook Revenue Share
G27: 45051 | H27: CRM (oddsgate) | I27: Ok | J27: 2523.97 | L27: 45082 | M27: CRM (oddsgate) | N27: Ok | O27: 3404.98 | Q27: 45112 | R27: CRM (oddsgate) | S27: Ok | T27: 4790.09 | V27: 45139 | W27: CRM (oddsgate) | X27: Ok | Y27: 5956.69 | AA27: 45189 | AB27: CRM (oddsgate) | AC27: Ok | AD27: 10768.6 | AF27: 45219 | AG27: CRM (oddsgate) | AH27: Ok | AI27: 12078.6 | AK27: 45250 | AL27: CRM (oddsgate) | AM27: Ok | AN27: 16726 | AP27: 45280 | AQ27: CRM (oddsgate) | AR27: A Vencer | AS27: 8734 | AV27: 45139 | AW27: CRM
G28: 45051 | H28: mailchimp emails | I28: Ok | J28: 277.5 | L28: 45082 | M28: mailchimp emails | N28: Ok | O28: 138.75 | Q28: 45112 | R28: mailchimp emails | S28: Ok | T28: 138.75 | V28: 45139 | W28: mailchimp emails | X28: Ok | Y28: 138.75 | AA28: 45189 | AB28: mailchimp emails | AC28: Ok | AD28: 4162.5 | AF28: 45219 | AG28: Sendgrid Emails | AH28: Ok | AI28: 3000 | AK28: 45250 | AL28: Sendgrid Emails | AM28: Ok | AN28: 3000 | AP28: 45280 | AQ28: Sendgrid Emails | AR28: Ok | AV28: 45139 | AW28: mailchimp emails
G29: 45051 | H29: Starspay | I29: Ok | J29: 23642.16 | L29: 45082 | M29: Starspay | N29: Ok | O29: 47820.45 | Q29: 45112 | R29: Starspay | S29: Ok | T29: 62350.87 | V29: 45139 | W29: Starspay | X29: Ok | Y29: 58290 | AA29: 45189 | AB29: Starspay | AC29: Ok | AD29: 77644 | AF29: 45219 | AG29: Starspay | AH29: Ok | AI29: 61141.98 | AK29: 45250 | AL29: Starspay | AM29: Ok | AN29: =NOVEMBRO!AL15 -> 101004.76 | AP29: 45280 | AQ29: Starspay | AR29: Ok | AS29: =DEZEMBRO!AL15 -> 120267.1 | AV29: 45139 | AW29: Starspay
G30: 45052 | H30: Live Chat | I30: Ok | J30: 249.71 | L30: 45082 | M30: API Afiliados | N30: Ok | O30: 0 | Q30: 45112 | R30: API Afiliados | S30: Ok | T30: 0 | V30: 45139 | W30: API Afiliados | X30: Ok | Y30: 3500 | AA30: 45189 | AB30: API Afiliados | AC30: Ok | AD30: 3500 | AF30: 45219 | AG30: API Afiliados | AH30: Ok | AI30: 3500 | AK30: 45250 | AL30: API Afiliados | AM30: A Vencer | AN30: 3500 | AP30: 45280 | AQ30: API Afiliados | AR30: A Vencer | AS30: 3500 | AT30: 28500 | AV30: 45139 | AW30: API Afiliados | AY30: 28500
G31: 45053 | H31: Workspace | I31: Ok | J31: 56 | L31: 45082 | M31: Live Chat | N31: Ok | O31: 249.71 | Q31: 45112 | R31: Live Chat | S31: Ok | T31: 249.71 | V31: 45139 | W31: Live Chat | X31: Ok | Y31: 249.71 | AA31: 45189 | AB31: Live Chat | AC31: Ok | AD31: 249.71 | AF31: 45219 | AG31: Live Chat | AH31: Ok | AI31: 249.71 | AK31: 45250 | AL31: Live Chat | AM31: Ok | AN31: 249.71 | AP31: 45280 | AQ31: Live Chat | AR31: Ok | AS31: 249.71 | AT31: 249.71 | AV31: 45139 | AW31: Live Chat | AY31: 249.71
I32: Ok | L32: 45082 | M32: Workspace | N32: Ok | O32: 56 | Q32: 45114 | R32: Workspace | S32: Ok | T32: 268.8 | V32: 45139 | W32: Workspace | X32: Ok | Y32: 250 | AA32: 45189 | AB32: Workspace | AC32: Ok | AD32: 300 | AF32: 45219 | AG32: Workspace | AH32: Ok | AI32: 350 | AK32: 45250 | AL32: Workspace | AM32: Ok | AN32: 350 | AP32: 45280 | AQ32: Workspace | AR32: Ok | AS32: 350 | AT32: 1000 | AV32: 45139 | AW32: Workspace | AY32: 1000
Q33: - | R33: - | T33: - | V33: - | W33: - | Y33: - | AA33: - | AB33: - | AD33: - | AF33: - | AG33: mailchimp emails | AH33: Ok | AI33: 1248.75 | AK33: - | AL33: mailchimp emails | AM33: Ok | AN33: 1248.75 | AP33: - | AQ33: - | AS33: - | AT33: - | AV33: - | AW33: - | AY33: -
B36: DATA | C36: Total : | D36: Status | E36: =(SUM(E37:E42)) -> 0 | G36: DATA | H36: Total : | I36: Status | J36: =(SUM(J37:J42)) -> 3200 | L36: DATA | M36: Total : | N36: Status | O36: =(SUM(O37:O42)) -> 3200 | Q36: DATA | R36: Total : | S36: Status | T36: =(SUM(T38:T42)) -> 0 | V36: DATA | W36: Total : | X36: Status | Y36: =(SUM(Y37:Y42)) -> 0 | AA36: DATA | AB36: Total : | AC36: Status | AD36: =(SUM(AD37:AD42)) -> 0 | AF36: DATA | AG36: Total : | AH36: Status | AI36: =(SUM(AI37:AI42)) -> 964 | AK36: DATA | AL36: Total : | AM36: Status | AN36: =(SUM(AN37:AN42)) -> 28000 | AP36: DATA | AQ36: Total : | AR36: Status | AS36: =(SUM(AS37:AS42)) -> 27981.71 | AT36: =(SUM(AT37:AT42)) -> 12000 | AV36: DATA | AW36: Total : | AX36: Status | AY36: =(SUM(AY37:AY42)) -> 12000
A37: Operacional | B37: - | C37: - | E37: - | F37: Operacional | G37: 45051 | H37: Escritório | I37: Ok | J37: 2700 | K37: Operacional | L37: 45082 | M37: Escritório | N37: Ok | O37: 2700 | P37: Operacional | U37: Operacional | X37: Ok | Z37: Operacional | AE37: Operacional | AF37: 45209 | AG37: Transporte equipes | AH37: Ok | AI37: =160+200+160+150+294 -> 964 | AJ37: Operacional | AK37: 45250 | AL37: Caução 3 Meses | AM37: Ok | AN37: 21000 | AO37: Operacional | AP37: 45265 | AQ37: Leds | AR37: Ok | AS37: 2400 | AT37: 12000 | AU37: Operacional | AV37: 45139 | AW37: Aluguel Harri | AY37: 12000
B38: - | C38: - | E38: - | G38: 45051 | H38: Escritório Limpeza | I38: Ok | J38: 500 | L38: 45083 | M38: Escritório Limpeza | N38: Ok | O38: 500 | Q38: - | R38: - | T38: - | AK38: 45250 | AL38: Aluguel Dezembro | AM38: Ok | AN38: 7000 | AP38: 45265 | AQ38: IPTU + Cond. + Bombeiros | AR38: Ok | AS38: =1947.48+884.23 -> 2831.71 | AT38: - | AV38: - | AW38: - | AY38: -
B39: - | C39: - | E39: - | G39: 45051 | L39: 45083 | Q39: - | R39: - | T39: - | V39: - | W39: - | Y39: - | AA39: - | AB39: - | AD39: - | AF39: - | AG39: - | AI39: - | AK39: - | AL39: - | AN39: - | AP39: 45265 | AQ39: Moveis e Eletros | AR39: Ok | AS39: 22750 | AT39: - | AV39: - | AW39: - | AY39: -
B40: - | C40: - | E40: - | L40: 45083 | Q40: - | R40: - | T40: - | V40: - | W40: - | Y40: - | AA40: - | AB40: - | AD40: - | AF40: - | AG40: - | AI40: - | AK40: - | AL40: - | AN40: - | AT40: - | AV40: - | AW40: - | AY40: -
B43: DATA | C43: Total : | D43: Status | E43: =SUM(E44:E46) -> 0 | G43: DATA | H43: Total : | I43: Status | J43: =SUM(J44:J46) -> #REF! | L43: DATA | M43: Total : | N43: Status | O43: =SUM(O44:O46) -> #REF! | Q43: DATA | R43: Total : | S43: Status | T43: =SUM(T44:T46) -> #REF! | V43: DATA | W43: Total : | X43: Status | Y43: =SUM(Y44:Y46) -> 0 | AA43: DATA | AB43: Total : | AC43: Status | AD43: =SUM(AD44:AD46) -> 0 | AF43: DATA | AG43: Total : | AH43: Status | AI43: =SUM(AI44:AI46) -> 0 | AK43: DATA | AL43: Total : | AM43: Status | AN43: =SUM(AN44:AN46) -> #REF! | AP43: DATA | AQ43: Total : | AR43: Status | AS43: =SUM(AS44:AS46) -> 24000 | AT43: =SUM(AT44:AT46) -> 0 | AV43: DATA | AW43: Total : | AX43: Status | AY43: =SUM(AY44:AY46) -> 0
A44: Tráfego | B44: - | C44: - | E44: - | F44: Tráfego | G44: 45077 | H44: Tráfego - Castelo | I44: Ok | J44: ='TRÁFEGO'!C73 -> #REF! | K44: Tráfego | L44: 45107 | M44: Tráfego - Castelo | N44: Ok | O44: ='TRÁFEGO'!E73 -> #REF! | P44: Tráfego | Q44: 45138 | R44: Tráfego - Castelo | T44: ='TRÁFEGO'!G73 -> #REF! | U44: Tráfego | V44: - | W44: - | Y44: - | Z44: Tráfego | AA44: - | AB44: - | AD44: - | AE44: Tráfego | AF44: - | AG44: - | AI44: - | AJ44: Tráfego | AK44: 45238 | AL44: Institucional | AM44: Ok | AN44: ='TRÁFEGO'!O73 -> #REF! | AO44: Tráfego | AP44: 45265 | AQ44: Institucional | AR44: Ok | AS44: 24000 | AT44: - | AU44: Tráfego | AV44: - | AW44: - | AY44: -
B45: - | C45: - | E45: - | G45: - | H45: - | J45: - | L45: - | M45: - | O45: - | Q45: - | R45: - | T45: - | V45: - | W45: - | Y45: - | AA45: - | AB45: - | AD45: - | AF45: - | AG45: - | AI45: - | AT45: - | AV45: - | AW45: - | AY45: -
B46: - | C46: - | E46: - | G46: - | H46: - | J46: - | L46: - | M46: - | O46: - | Q46: - | R46: - | T46: - | V46: - | W46: - | Y46: - | AA46: - | AB46: - | AD46: - | AF46: - | AG46: - | AI46: - | AT46: - | AV46: - | AW46: - | AY46: -
B47: DATA | C47: Total : | D47: Status | E47: =SUM(E48:E51) -> 50000 | G47: DATA | H47: Total : | I47: Status | J47: =SUM(J48:J51) -> 56355 | L47: DATA | M47: Total : | N47: Status | O47: =SUM(O48:O51) -> 50810 | Q47: DATA | R47: Total : | S47: Status | T47: =SUM(T48:T51) -> 61270 | V47: DATA | W47: Total : | X47: Status | Y47: =SUM(Y48:Y51) -> 61200 | AA47: DATA | AB47: Total : | AC47: Status | AD47: =SUM(AD48:AD51) -> 50000 | AF47: DATA | AG47: Total : | AH47: Status | AI47: =SUM(AI48:AI51) -> 76050 | AK47: DATA | AL47: Total : | AM47: Status | AN47: =SUM(AN48:AN51) -> 50000 | AP47: DATA | AQ47: Total : | AR47: Status | AS47: =SUM(AS48:AS51) -> 50000 | AT47: =SUM(AT48:AT51) -> 0 | AV47: DATA | AW47: Total : | AX47: Status | AY47: =SUM(AY48:AY51) -> 0
A48: Marketing | B48: - | C48: - | E48: - | F48: Marketing | G48: 45077 | H48: Promoções | I48: Ok | J48: 6355 | K48: Marketing | L48: 45107 | M48: Promoções | N48: Ok | O48: 810 | P48: Marketing | Q48: 45138 | R48: Promoções | S48: Ok | T48: 11270 | U48: Marketing | V48: 45169 | W48: Promoções | X48: Ok | Y48: 11200 | Z48: Marketing | AA48: 45169 | AB48: Promoções | AE48: Marketing | AF48: 45169 | AG48: Ativações Academias | AH48: Ok | AI48: 19050 | AJ48: Marketing | AK48: 45240 | AL48: Label Mansão Maromba | AM48: Ok | AN48: 50000 | AO48: Marketing | AP48: 45271 | AQ48: Label Mansão Maromba | AR48: Ok | AS48: 50000 | AU48: Marketing | AV48: 45169 | AW48: Promoções
B49: 45046 | C49: Custo da Label maromba | D49: Ok | E49: 50000 | G49: 45076 | H49: Custo da Label maromba | I49: Ok | J49: 50000 | L49: 45107 | M49: Custo da Label maromba | N49: Ok | O49: 50000 | Q49: 45137 | R49: Custo da Label maromba | S49: Ok | T49: 50000 | V49: 45168 | W49: Custo da Label maromba | X49: Ok | Y49: 50000 | AA49: 45199 | AB49: Custo da Label maromba | AC49: Ok | AD49: 50000 | AF49: 45229 | AG49: Custo da Label maromba | AH49: Ok | AI49: 50000
B50: - | C50: - | E50: - | G50: - | H50: - | J50: - | L50: - | M50: - | O50: - | Q50: - | R50: - | T50: - | AF50: 45225 | AG50: Campanha Libertadores | AH50: Ok | AI50: 6000
B51: - | C51: - | E51: - | G51: - | H51: - | J51: - | L51: - | M51: - | O51: - | Q51: - | R51: - | T51: - | AF51: 45225 | AG51: 100 Camisas | AH51: Ok | AI51: 1000
B52: DATA | C52: Total : | D52: Status | E52: =SUM(E53:E58) -> 0 | G52: DATA | H52: Total : | I52: Status | J52: =SUM(J53:J58) -> 0 | L52: DATA | M52: Total : | N52: Status | O52: =SUM(O53:O58) -> 0 | Q52: DATA | R52: Total : | S52: Status | T52: =SUM(T53:T58) -> 1640 | V52: DATA | W52: Total : | X52: Status | Y52: =SUM(Y53:Y58) -> 2900 | AA52: DATA | AB52: Total : | AC52: Status | AD52: =SUM(AD53:AD58) -> 2900 | AF52: DATA | AG52: Total : | AH52: Status | AI52: =SUM(AI53:AI58) -> 0 | AK52: DATA | AL52: Total : | AM52: Status | AN52: =SUM(AN53:AN58) -> 0 | AP52: DATA | AQ52: Total : | AR52: Status | AS52: =SUM(AS53:AS58) -> 0 | AT52: =SUM(AT53:AT58) -> 2900 | AV52: DATA | AW52: Total : | AX52: Status | AY52: =SUM(AY53:AY58) -> 2900
A53: SEO | B53: - | C53: - | E53: - | F53: SEO | G53: - | H53: - | J53: - | K53: SEO | L53: - | M53: - | O53: - | P53: SEO | Q53: 45112 | R53: SEO - Serviço | T53: 1640 | U53: SEO | V53: 45143 | W53: SEO - Serviço | Y53: 2900 | Z53: SEO | AA53: 45143 | AB53: SEO - Serviço | AC53: Ok | AD53: 2900 | AE53: SEO | AF53: 45143 | AG53: SEO - Serviço | AI53: 0 | AJ53: SEO | AK53: 45143 | AL53: SEO - Serviço | AN53: 0 | AO53: SEO | AP53: 45143 | AQ53: SEO - Serviço | AS53: 0 | AT53: 2900 | AU53: SEO | AV53: 45143 | AW53: SEO - Serviço | AY53: 2900
B54: - | C54: - | E54: - | G54: - | H54: - | J54: - | L54: - | M54: - | O54: - | Q54: - | R54: - | T54: - | V54: - | W54: - | Y54: -
B55: - | C55: - | E55: - | G55: - | H55: - | J55: - | L55: - | M55: - | O55: - | Q55: - | R55: - | T55: - | V55: - | W55: - | Y55: -
B56: - | C56: - | E56: - | G56: - | H56: - | J56: - | L56: - | M56: - | O56: - | Q56: - | R56: - | T56: - | V56: - | W56: - | Y56: -
B57: - | C57: - | E57: - | G57: - | H57: - | J57: - | L57: - | M57: - | O57: - | Q57: - | R57: - | T57: - | V57: - | W57: - | Y57: -
B58: - | C58: - | E58: - | G58: - | H58: - | J58: - | L58: - | M58: - | O58: - | Q58: - | R58: - | T58: - | V58: - | W58: - | Y58: -
C59: Total : | D59: Status | E59: =SUM(E60:E65) -> 0 | G59: Total : | I59: Status | J59: =SUM(J60:J65) -> 0 | M59: Total : | N59: Status | O59: =SUM(O60:O65) -> 0 | R59: Total : | S59: Status | T59: =SUM(T60:T65) -> 0 | W59: Total : | X59: Status | Y59: =SUM(Y60:Y65) -> 1750 | AB59: Total : | AC59: Status | AD59: =SUM(AD60:AD65) -> 1750 | AG59: Total : | AH59: Status | AI59: =SUM(AI60:AI65) -> 909 | AL59: Total : | AM59: Status | AN59: =SUM(AN60:AN65) -> 3310 | AQ59: Total : | AR59: Status | AS59: =SUM(AS60:AS65) -> 7838 | AT59: =SUM(AT60:AT65) -> 1750 | AW59: Total : | AX59: Status | AY59: =SUM(AY60:AY65) -> 1750
A60: CRM | F60: CRM | K60: CRM | L60: - | M60: - | O60: - | P60: CRM | R60: Promoções | T60: - | U60: CRM | V60: 45139 | W60: CRM - Serviço | Y60: 1750 | Z60: CRM | AA60: 45139 | AB60: CRM - Serviço | AC60: Ok | AD60: 1750 | AE60: CRM | AF60: 45204 | AG60: Plataforma RD / 20k | AH60: Ok | AI60: 909 | AJ60: CRM | AK60: 45235 | AL60: Plataforma RD/ 100k | AM60: Ok | AN60: 3310 | AO60: CRM | AP60: 45231 | AT60: 1750 | AU60: CRM | AV60: 45139 | AW60: CRM - Serviço | AX60: A Vencer | AY60: 1750
L61: - | M61: - | O61: - | Q61: - | R61: - | T61: - | W61: Promoções | AP61: 45231 | AQ61: Plataforma RD PRO | AR61: Ok | AS61: 7838
L62: - | M62: - | O62: - | Q62: - | R62: - | T62: -
L63: - | M63: - | O63: - | Q63: - | R63: - | T63: -
L64: - | M64: - | O64: - | Q64: - | R64: - | T64: -
L65: - | M65: - | O65: - | Q65: - | R65: - | T65: -
B66: DATA | C66: Total : | D66: Status | E66: =SUM(E67:E84) -> 100000 | G66: DATA | H66: Total : | I66: Status | J66: =SUM(J67:J84) -> 100000 | L66: DATA | M66: Total : | N66: Status | O66: =SUM(O67:O84) -> 256400 | Q66: DATA | R66: Total : | S66: Status | T66: =SUM(T67:T84) -> 185000 | V66: DATA | W66: Total : | X66: Status | Y66: =SUM(Y67:Y84) -> 230080 | AA66: DATA | AB66: Total : | AC66: Status | AD66: =SUM(AD67:AD84) -> 175000 | AF66: DATA | AG66: Total : | AH66: Status | AI66: =SUM(AI67:AI84) -> 100000 | AK66: DATA | AL66: Total : | AM66: Status | AN66: =SUM(AN67:AN84) -> 184319 | AP66: DATA | AQ66: Total : | AR66: Status | AS66: =SUM(AS67:AS84) -> 239109 | AT66: =SUM(AT67:AT84) -> 0 | AV66: DATA | AW66: Total : | AX66: Status | AY66: =SUM(AY67:AY84) -> 0
A67: MKT INFLUENCER | B67: SEMANA 1 | F67: MKT INFLUENCER | G67: SEMANA 1 | K67: MKT INFLUENCER | L67: SEMANA 1 | P67: MKT INFLUENCER | Q67: SEMANA 1 | U67: MKT INFLUENCER | V67: SEMANA 1 | Z67: MKT INFLUENCER | AA67: SEMANA 1 | AE67: MKT INFLUENCER | AF67: SEMANA 1 | AJ67: MKT INFLUENCER & AFILIADOS | AK67: SEMANA 1 | AO67: MKT INFLUENCER & AFILIADOS | AP67: SEMANA 1 | AU67: MKT INFLUENCER | AV67: SEMANA 1
L68: 45087 | M68: Pacote de Publi | N68: Ok | O68: 11400 | Q68: 45110 | R68: Pacote de Publi | S68: Ok | T68: 25000 | V68: 45141 | W68: Pacote de Publi | X68: Ok | Y68: 25000 | AA68: 45181 | AB68: Pacote de Publi | AC68: Ok | AD68: 25000 | AF68: 45205 | AG68: Toguro | AH68: Ok | AI68: 100000 | AK68: 45231 | AL68: Equipe Comercial | AM68: Ok | AN68: 15000 | AP68: 45265 | AQ68: Equipe Comercial | AR68: Ok | AS68: 25000
AA69: 45181 | AB69: Toguro | AC69: Ok | AD69: 100000 | AP69: 45265 | AQ69: Influ - Vini dmenor | AR69: Ok | AS69: 10000
B71: SEMANA 2 | G71: SEMANA 2 | L71: SEMANA 2 | Q71: SEMANA 2 | V71: SEMANA 2 | AA71: SEMANA 2 | AF71: SEMANA 2 | AK71: SEMANA 2 | AP71: SEMANA 2 | AV71: SEMANA 2
B72: 45046 | C72: Toguro | D72: Ok | E72: 100000 | L72: 45087 | M72: Pacote de Publi | N72: Ok | O72: 20000 | Q72: 45121 | R72: Pacote de Publi | S72: Ok | T72: 25000 | V72: 45149 | W72: Pacote de Publi | X72: Ok | Y72: 30080 | AA72: 45184 | AB72: Pacote de Publi | AC72: Ok | AD72: 25000 | AK72: 45237 | AL72: Equipe Comercial | AM72: Ok | AN72: 40000 | AP72: 45272 | AQ72: Equipe Comercial | AR72: Ok | AS72: 32851 | AT72: - | AV72: - | AW72: - | AY72: -
Q73: 45121 | R73: Toguro | S73: Ok | T73: 100000 | AP73: 45272 | AQ73: Influ - Ribitados | AR73: Ok | AS73: 5000
B75: SEMANA 3 | G75: SEMANA 3 | L75: SEMANA 3 | Q75: SEMANA 3 | V75: SEMANA 3 | AA75: SEMANA 3 | AF75: SEMANA 3 | AK75: SEMANA 3 | AP75: SEMANA 3 | AV75: SEMANA 3
L76: 45096 | M76: Toguro | N76: Ok | O76: 100000 | Q76: 45127 | R76: Pacote de Publi | S76: Ok | T76: 25000 | V76: 45157 | W76: Pacote de Publi | X76: Ok | Y76: 25000 | AA76: 45192 | AB76: Pacote de Publi | AC76: Ok | AD76: 25000 | AF76: 45217 | AK76: 45244 | AL76: Equipe Comercial | AM76: Ok | AN76: 22929 | AP76: 45282 | AQ76: Equipe Comercial | AR76: Ok | AS76: 41175
AL77: Toguro | AN77: 50000 | AP77: 45282 | AQ77: Influ - Luquinhasof | AR77: Ok | AS77: 10000
B79: SEMANA 4 | G79: SEMANA 4 | L79: SEMANA 4 | Q79: SEMANA 4 | V79: SEMANA 4 | AA79: SEMANA 4 | AF79: SEMANA 4 | AK79: SEMANA 4 | AP79: SEMANA 4 | AV79: SEMANA 4
G80: 45076 | H80: Toguro | I80: Ok | J80: 100000 | L80: 45104 | M80: Pacote de Publi | N80: Ok | O80: 25000 | Q80: 45134 | R80: Pacote de Publi | S80: Ok | T80: 10000 | V80: 45163 | W80: Pacote de Publi | X80: Ok | Y80: 25000 | AF80: 45229 | AK80: 45257 | AL80: Toguro | AM80: Ok | AN80: 50000 | AP80: 45287 | AQ80: Toguro | AR80: Ok | AS80: 100000
L81: 45104 | M81: Toguro | N81: Ok | O81: 100000 | V81: 45160 | W81: Toguro | Y81: 100000 | AK81: 45252 | AL81: Equipe Comercial | AM81: Ok | AN81: 6390 | AP81: 45289 | AQ81: Equipe Comercial | AR81: Ok | AS81: 15083
V82: SEMANA 5
V83: 45169 | W83: Pacote de Publi | X83: Ok | Y83: 25000
B85: DATA | C85: Total : | D85: Status | E85: =SUM(E86:E93) -> 40699.95 | G85: DATA | H85: Total : | I85: Status | J85: =SUM(J86:J93) -> 78675.04 | L85: DATA | M85: Total : | N85: Status | O85: =SUM(O86:O93) -> 50806.48 | Q85: DATA | R85: Total : | S85: Status | T85: =SUM(T86:T93) -> 19482 | V85: DATA | W85: Total : | X85: Status | Y85: =SUM(Y86:Y93) -> 5323 | AA85: DATA | AB85: Total : | AC85: Status | AD85: =SUM(AD86:AD93) -> 5080 | AF85: DATA | AG85: Total : | AH85: Status | AI85: =SUM(AI86:AI93) -> 15227 | AK85: DATA | AL85: Total : | AM85: Status | AN85: =SUM(AN86:AN93) -> 28095 | AP85: DATA | AQ85: Total : | AR85: Status | AS85: =SUM(AS86:AS93) -> 0 | AT85: =SUM(AT86:AT93) -> 0 | AV85: DATA | AW85: Total : | AX85: Status | AY85: =SUM(AY86:AY93) -> 0
A86: VARIAVEIS | B86: 45046 | C86: Bit,ly - Anual | D86: Ok | E86: 20699.95 | F86: VARIAVEIS | G86: 45046 | H86: Reembolso | I86: Ok | J86: 62832.36 | K86: VARIAVEIS | M86: Registro de Marca | N86: Ok | O86: R$ 2.812,50 | P86: VARIAVEIS | R86: Mudança de Domínio | S86: Ok | T86: 18000 | U86: VARIAVEIS | W86: Passagens / Hospedagens | X86: Ok | Y86: 5323 | Z86: VARIAVEIS | AB86: Reembolso | AC86: Ok | AD86: 5080 | AE86: VARIAVEIS | AF86: 45222 | AG86: Passagens Harrison | AH86: Ok | AI86: 5080 | AJ86: VARIAVEIS | AK86: 45238 | AL86: Bonés | AM86: Ok | AN86: 5000 | AO86: VARIAVEIS | AU86: VARIAVEIS
C87: Reembolso H. | D87: Ok | E87: 20000 | H87: Reembolso Viagem | I87: Ok | J87: 15842.68 | M87: Reembolso H. | N87: Ok | O87: 50806.48 | R87: Registro de Marca | S87: Ok | T87: R$ 2.812,50 | AF87: 45223 | AG87: Passagens Gnomo | AH87: Ok | AI87: 4555.22 | AK87: 45245 | AL87: Bonés | AM87: Ok | AN87: 5000
R88: Passagens / Hospedagens | S88: Ok | T88: 1482 | AF88: 45223 | AG88: Passagens Toguro | AH88: Ok | AI88: 4555.22 | AK88: 45252 | AL88: Bonés | AM88: Ok | AN88: 5500
AF89: 45223 | AG89: Hospedagens | AH89: Ok | AI89: 1036.56 | AK89: 45252 | AL89: 300 fardamentos academias recife | AM89: Ok | AN89: 11000
AK90: 45252 | AL90: 100 camisas recife | AM90: Ok | AN90: 1595
D94: Total : | E94: =SUM(E95:E106) -> 0 | I94: Total : | J94: =SUM(J95:J106) -> 0 | N94: Total : | O94: =SUM(O95:O106) -> 0 | S94: Total : | T94: =SUM(T95:T106) -> 0 | X94: Total : | Y94: =SUM(Y95:Y106) -> 0 | AC94: Total : | AD94: =SUM(AD95:AD106) -> 0 | AH94: Total : | AI94: =SUM(AI95:AI104) -> #REF! | AM94: Total : | AN94: =SUM(AN95:AN105) -> #REF! | AP94: DATA | AR94: Total : | AS94: =sum(AS96+AS99+AS102+AS103+AS105) -> #REF! | AT94: =SUM(AT95:AT106) -> 0 | AV94: DATA | AW94: Total : | AX94: Status | AY94: =SUM(AY95:AY106) -> 0
A95: AFILIADOS | B95: DATA | C95: SEMANA 1 | D95: Status | F95: AFILIADOS | G95: DATA | H95: SEMANA 1 | I95: Status | K95: AFILIADOS | L95: DATA | M95: SEMANA 1 | N95: Status | P95: AFILIADOS | Q95: DATA | R95: SEMANA 1 | S95: Status | U95: AFILIADOS | V95: DATA | W95: SEMANA 1 | X95: Status | Z95: AFILIADOS | AA95: DATA | AB95: SEMANA 1 | AC95: Status | AE95: AFILIADOS | AF95: DATA | AG95: SEMANA 1 | AH95: Status | AJ95: AFILIADOS | AK95: DATA | AL95: SEMANA 1 | AM95: Status | AO95: AFILIADOS | AQ95: SEMANA 1 | AR95: Status | AU95: AFILIADOS | AV95: SEMANA 1
AF96: 45201 | AG96: Grupo geral | AH96: Ok | AI96: =AFILIADOS!D6 -> #REF! | AK96: 45236 | AL96: Grupo geral | AM96: Ok | AN96: =AFILIADOS!D12 -> #REF! | AP96: 45265 | AQ96: Grupo Geral | AR96: Ok | AS96: =AFILIADOS!D18 -> #REF!
AF97: SEMANA 2 | AK97: SEMANA 2
B98: SEMANA 2 | G98: SEMANA 2 | L98: SEMANA 2 | Q98: SEMANA 2 | V98: SEMANA 2 | AA98: SEMANA 2 | AF98: 45208 | AG98: Grupo geral | AH98: Ok | AI98: =AFILIADOS!D7 -> #REF! | AK98: 45243 | AL98: Grupo geral | AM98: Ok | AN98: =AFILIADOS!D13 -> #REF! | AP98: SEMANA 2 | AV98: SEMANA 2
AF99: SEMANA 3 | AP99: 45271 | AQ99: Grupo Geral | AR99: Ok | AS99: =AFILIADOS!D19 -> #REF!
AF100: 45216 | AG100: Grupo geral | AH100: Ok | AI100: =AFILIADOS!D8 -> #REF! | AK100: SEMANA 3
B101: SEMANA 3 | G101: SEMANA 3 | L101: SEMANA 3 | Q101: SEMANA 3 | V101: SEMANA 3 | AA101: SEMANA 3 | AF101: SEMANA 4 | AK101: 45250 | AL101: Grupo geral | AM101: Ok | AN101: =AFILIADOS!D14 -> #REF! | AP101: SEMANA 3 | AV101: SEMANA 3
AF102: 45222 | AG102: Grupo geral | AH102: Ok | AI102: =AFILIADOS!D9 -> #REF! | AK102: 45252 | AL102: Cabeças | AM102: Ok | AN102: =AFILIADOS!D15 -> #REF! | AP102: 45278 | AQ102: Grupo Geral | AR102: Ok | AS102: =AFILIADOS!D20 -> #REF!
AF103: SEMANA 5 | AK103: SEMANA 4 | AP103: 45280 | AQ103: Residual | AR103: Ok | AS103: =AFILIADOS!D21 -> #REF!
B104: SEMANA 4 | G104: SEMANA 4 | L104: SEMANA 4 | Q104: SEMANA 4 | V104: SEMANA 4 | AA104: SEMANA 4 | AF104: 45229 | AG104: Grupo geral | AH104: Ok | AI104: =AFILIADOS!D10 -> #REF! | AK104: 45257 | AL104: Grupo geral | AM104: Ok | AN104: =AFILIADOS!D16 -> #REF! | AP104: SEMANA 4 | AV104: SEMANA 4
AP105: 45286 | AQ105: Grupo Geral | AR105: Ok | AS105: =AFILIADOS!D22 -> #REF!

Sheet CUSTOS 2026
B2: Janeiro | H2: Fevereiro | N2: Março | S2: Abril | X2: Maio | AC2: Junho | AH2: Julho | AM2: Agosto | AR2: Setembro | AW2: Outubro | BB2: Novembro | BG2: Dezembro
C3: Total Geral: | I3: Total Geral: | O3: Total Geral: | T3: Total Geral: | Y3: Total Geral: | AD3: Total Geral: | AI3: Total Geral: | AN3: Total Geral: | AS3: Total Geral: | AX3: Total Geral: | BC3: Total Geral: | BE3: =SUM(BE4:BE5) -> 0 | BH3: Total Geral: | BJ3: =SUM(BJ4:BJ5) -> 0
C4: Total Operacional | I4: Total Operacional | O4: Total Operacional | T4: Total Operacional | Y4: Total Operacional | AD4: Total Operacional | AI4: Total Operacional | AN4: Total Operacional | AS4: Total Operacional | AX4: Total Operacional | BC4: Total Operacional | BE4: =BE6 -> 0 | BH4: Total Operacional | BJ4: =BJ6 -> 0
C5: Total Ações | I5: Total Ações | O5: Total Ações | T5: Total Ações | Y5: Total Ações | AD5: Total Ações | AI5: Total Ações | AN5: Total Ações | AS5: Total Ações | AX5: Total Ações | BC5: Total Ações | BE5: =SUM(BE50,BE67) -> 0 | BH5: Total Ações | BJ5: =SUM(BJ50,BJ67) -> 0
B6: DATA | C6: COLABORADOR | E6: Status | F6: =SUM(F7:F14) -> 8500 | H6: DATA | I6: COLABORADOR | K6: Status | L6: =SUM(L7:L14) -> 14306 | N6: DATA | O6: COLABORADOR | P6: Status | Q6: =SUM(Q7:Q14) -> 15300 | S6: DATA | T6: COLABORADOR | U6: Status | V6: =SUM(V7:V14) -> 0 | X6: DATA | Y6: COLABORADOR | Z6: Status | AA6: =SUM(AA7:AA14) -> 0 | AC6: DATA | AD6: COLABORADOR | AE6: Status | AF6: =SUM(AF7:AF14) -> 0 | AH6: DATA | AI6: COLABORADOR | AJ6: Status | AK6: =SUM(AK7:AK14) -> 0 | AM6: DATA | AN6: COLABORADOR | AO6: Status | AP6: =SUM(AP7:AP14) -> 0 | AR6: DATA | AS6: COLABORADOR | AT6: Status | AU6: =SUM(AU7:AU14) -> 0 | AW6: DATA | AX6: COLABORADOR | AY6: Status | AZ6: =SUM(AZ7:AZ14) -> 0 | BB6: DATA | BC6: COLABORADOR | BD6: Status | BE6: =SUM(BE7:BE14) -> 0 | BG6: DATA | BH6: COLABORADOR | BI6: Status | BJ6: =SUM(BJ7:BJ14) -> 0
A7: Equipe Institucional | C7: Josy | D7: CS | F7: 3000 | I7: Josy | J7: CS | L7: 3000 | M7: Equipe Institucional | O7: Josy | P7: CS | Q7: 3000 | R7: Equipe Institucional | W7: Equipe Institucional | AB7: Equipe Institucional | AG7: Equipe Institucional | AL7: Equipe Institucional | AQ7: Equipe Institucional | AV7: Equipe Institucional | BA7: Equipe Institucional | BC7: Josy - CS | BF7: Equipe Institucional | BH7: Josy - CS
C8: Felipe | D8: CRM | F8: 3000 | I8: Felipe | J8: CRM | L8: 3000 | O8: Felipe | P8: CRM | Q8: 3000 | BC8: Felipe - CRM | BH8: Felipe - CRM
C9: Clara | D9: VIP | F9: 2500 | I9: Clara | J9: VIP | L9: 2500 | O9: Clara | P9: VIP | Q9: 2500
C10: Gabriel | D10: designer | F10: PAGO OPERACAO FOCUS | I10: Paulo Marinho | J10: BO | L10: 5806 | O10: Vitoria Jesus | P10: CS | Q10: 1800
C11: Julia | D11: designer | F11: PAGO OPERACAO FOCUS | O11: Gabriel Lira | P11: Designer | Q11: 1000
C12: Denny | D12: gestor trafego | F12: PAGO OPERACAO FOCUS | O12: Julia rocha | P12: Designer | Q12: 1000
O13: Denny | P13: Gestor Traf. | Q13: 3000
B16: DATA | C16: PLATAFORMAS | E16: Status | F16: =SUM(F17:F45) -> 22818.68 | H16: DATA | I16: PLATAFORMAS | K16: Status | L16: =sum(L17:L48) -> 19536.19 | N16: DATA | O16: PLATAFORMAS | P16: Status | Q16: =SUM(Q17:Q45) -> 3228.19 | S16: DATA | T16: PLATAFORMAS | U16: Status | V16: =SUM(V17:V45) -> 0 | X16: DATA | Y16: PLATAFORMAS | Z16: Status | AA16: =SUM(AA17:AA45) -> 0 | AC16: DATA | AD16: PLATAFORMAS | AE16: Status | AF16: =SUM(AF17:AF45) -> 0 | AH16: DATA | AI16: PLATAFORMAS | AJ16: Status | AK16: =SUM(AK17:AK45) -> 0 | AM16: DATA | AN16: PLATAFORMAS | AO16: Status | AP16: =SUM(AP17:AP45) -> 0 | AR16: DATA | AS16: PLATAFORMAS | AT16: Status | AU16: =SUM(AU17:AU45) -> 0 | AW16: DATA | AX16: PLATAFORMAS | AY16: Status | AZ16: =SUM(AZ17:AZ45) -> 0 | BB16: DATA | BC16: PLATAFORMAS | BD16: Status | BE16: =SUM(BE17:BE45) -> 0 | BG16: DATA | BH16: PLATAFORMAS | BI16: Status | BJ16: =SUM(BJ17:BJ45) -> 0
A17: PlataformaS | C17: SMARTICO | D17: SMARTICO | E17: Reembolsar AFFBR | F17: 11524.82 | G17: PlataformaS | I17: SMARTICO | L17: =11524.81+400 -> 11924.81 | M17: PlataformaS | R17: PlataformaS | AB17: PlataformaS | AG17: PlataformaS | AL17: PlataformaS | AQ17: PlataformaS | AV17: PlataformaS | BA17: PlataformaS | BC17: Smartico | BF17: PlataformaS | BH17: Smartico
C18: IOF SMARTCO | D18: IOF SMARTCO | E18: Reembolsar AFFBR | F18: 410.83 | H18: 46071 | I18: MULTILOGIN.COM | J18: FOCUS DEKO FERRAMENTAS | L18: 1282.24 | N18: 46083 | O18: Google Workspace_mktjo | Q18: R$ 788,29
C19: PG *TURBO CLOUD | D19: JOGO GRANDE DEKO FERRAMENTAS | E19: Reembolsar AFFBR | F19: 100 | H19: 46072 | I19: PG *TURBO CLOUD | J19: FOCUS DEKO FERRAMENTAS | L19: 100 | N19: 46083 | O19: Google Workspace_mktjo | Q19: R$ 763,00
C20: IOF - COMPRA INTERNACIONAL | D20: JOGO GRANDE DEKO FERRAMENTAS | E20: Reembolsar AFFBR | F20: 45.45 | H20: 46072 | I20: IOF - COMPRA INTERNACIONAL | J20: FOCUS DEKO FERRAMENTAS | L20: 44.88 | N20: 46085 | O20: TEXT INC | Q20: R$ 1.966,94
C21: TRACK4YOU | D21: JOGO GRANDE DEKO FERRAMENTAS | E21: Reembolsar AFFBR | F21: 297 | H21: 46072 | I21: PG *TURBO CLOUD | J21: FOCUS DEKO FERRAMENTAS | L21: 35.9 | N21: 46086 | O21: IOF - COMPRA INTERNACIONAL | Q21: R$ 68,84
C22: VTURB | D22: JOGO GRANDE DEKO FERRAMENTAS | E22: Reembolsar AFFBR | F22: 97 | H22: 46076 | I22: EC *REPAROSIL | J22: FOCUS DEKO FERRAMENTAS 2 | L22: 100 | N22: 46098 | O22: PG *COMTELE SMS | Q22: 700.05
C23: JIM.COM* MSM EMPREEND | D23: JOGO GRANDE DEKO FERRAMENTAS | E23: Reembolsar AFFBR | F23: 3131.53 | H23: 46065 | I23: TEXT INC | J23: FOCUS JOGO GRANDE FERRAMENTAS | L23: 325.62 | N23: 46100 | O23: MULTILOGIN.COM | Q23: 1251.72
C24: MULTILOGIN.COM | D24: JOGO GRANDE DEKO FERRAMENTAS | E24: Reembolsar AFFBR | F24: 1298.59 | H24: 46055 | I24: Google Workspace_mktjo | J24: FOCUS JOGO GRANDE FERRAMENTAS | L24: 575.34 | N24: 46101 | O24: IOF - COMPRA INTERNACIONAL | Q24: 43.81
C25: PG *TURBO CLOUD | D25: JOGO GRANDE DEKO FERRAMENTAS | E25: Reembolsar AFFBR | F25: 35.9 | H25: 46056 | I25: TEXT INC | J25: FOCUS JOGO GRANDE FERRAMENTAS | L25: 977.82 | N25: 46103 | O25: SELZY | Q25: 40.1
C26: EC *REPAROSIL | D26: JOGO GRANDE DEKO FERRAMENTAS | E26: Reembolsar AFFBR | F26: 100 | H26: 46056 | I26: SLACK T09R8ECB4P2 | J26: FOCUS JOGO GRANDE FERRAMENTAS | L26: 197.16 | N26: 46104 | O26: EBANX NORD* VPNCOM | Q26: 190.8
C27: MANYCHAT.COM | D27: JOGO GRANDE DEKO FERRAMENTAS | E27: Reembolsar AFFBR | F27: 1076.19 | H27: 46057 | I27: PG *COMTELE SMS | J27: FOCUS JOGO GRANDE FERRAMENTAS | L27: 630 | N27: 46104 | O27: IOF - COMPRA INTERNACIONAL | Q27: 1.4
C28: IOF - COMPRA INTERNACIONAL | D28: FOCUS JOGO GRANDE FERRAMENTAS | E28: Reembolsar AFFBR | F28: 0.39 | H28: 46057 | I28: TWILIO SENDGRID | J28: FOCUS JOGO GRANDE FERRAMENTAS | L28: 443.09 | N28: 46082 | O28: Google Workspace_mktju | Q28: R$ 102,38
C29: MMDSMART LTD | D29: FOCUS JOGO GRANDE FERRAMENTAS | E29: Reembolsar AFFBR | F29: 11.04 | H29: 46059 | I29: TEXT INC | J29: FOCUS JOGO GRANDE FERRAMENTAS | L29: 429.41 | N29: 46084 | O29: TWILIO SENDGRID | Q29: R$ 441,73
C30: SELZY | D30: FOCUS JOGO GRANDE FERRAMENTAS | E30: Reembolsar AFFBR | F30: 33.74 | H30: 46060 | I30: IOF - COMPRA INTERNACIONAL | J30: FOCUS JOGO GRANDE FERRAMENTAS | L30: 15.03 | N30: 46085 | O30: IOF - COMPRA INTERNACIONAL | Q30: R$ 15,46
C31: IOF - COMPRA INTERNACIONAL | D31: FOCUS JOGO GRANDE FERRAMENTAS | E31: Reembolsar AFFBR | F31: 1.18 | H31: 46059 | I31: CASHBACK - Slack | J31: FOCUS JOGO GRANDE FERRAMENTAS | L31: 46.73 | N31: 46085 | O31: FLUKE | Q31: R$ 9,99
C32: IOF - COMPRA INTERNACIONAL | D32: FOCUS JOGO GRANDE FERRAMENTAS | E32: Reembolsar AFFBR | F32: 35.48 | H32: 46057 | I32: IOF - COMPRA INTERNACIONAL | J32: FOCUS JOGO GRANDE FERRAMENTAS | L32: 34.22 | N32: 46101 | O32: TEXT, INC. | Q32: 651.9
C33: TWILIO SENDGRID | D33: FOCUS JOGO GRANDE FERRAMENTAS | E33: Reembolsar AFFBR | F33: 524.16 | H33: 46066 | I33: IOF - COMPRA INTERNACIONAL | J33: FOCUS JOGO GRANDE FERRAMENTAS | L33: 11.4 | N33: 46101 | O33: TEXT, INC. | Q33: 27.62
C34: IOF - COMPRA INTERNACIONAL | D34: FOCUS JOGO GRANDE FERRAMENTAS | E34: Reembolsar AFFBR | F34: 18.35 | H34: 46057 | I34: IOF - COMPRA INTERNACIONAL | J34: FOCUS JOGO GRANDE FERRAMENTAS | L34: 6.9 | N34: 46102 | O34: IOF - COMPRA INTERNACIONAL | Q34: 22.82
C35: CASHBACK - Slack | D35: FOCUS JOGO GRANDE FERRAMENTAS | E35: Reembolsar AFFBR | F35: -30.69 | H35: 46057 | I35: IOF - COMPRA INTERNACIONAL | J35: FOCUS JOGO GRANDE FERRAMENTAS | L35: 15.51 | N35: 46102 | O35: IOF - COMPRA INTERNACIONAL | Q35: 0.97
C36: PG *COMTELE SMS | D36: FOCUS JOGO GRANDE FERRAMENTAS | E36: Reembolsar AFFBR | F36: 756 | H36: 46072 | I36: PG *COMTELE SMS | J36: FOCUS JOGO GRANDE FERRAMENTAS | L36: 630 | N36: 46098 | O36: TRACK4YOU | Q36: 297
C37: PG *COMTELE SMS | D37: FOCUS JOGO GRANDE FERRAMENTAS | E37: Reembolsar AFFBR | F37: 756 | H37: 46072 | I37: SELZY | J37: FOCUS JOGO GRANDE FERRAMENTAS | L37: 32.59
C38: SELZY | D38: FOCUS JOGO GRANDE FERRAMENTAS | E38: Reembolsar AFFBR | F38: 40.68 | H38: 46072 | I38: SELZY | J38: FOCUS JOGO GRANDE FERRAMENTAS | L38: 29.61
C39: PG *COMTELE SMS | D39: FOCUS JOGO GRANDE FERRAMENTAS | E39: Reembolsar AFFBR | F39: 693 | H39: 46073 | I39: IOF - COMPRA INTERNACIONAL | J39: FOCUS JOGO GRANDE FERRAMENTAS | L39: 1.14
C40: Google Workspace_mktjo | D40: FOCUS JOGO GRANDE FERRAMENTAS | E40: Reembolsar AFFBR | F40: 490 | H40: 46073 | I40: IOF - COMPRA INTERNACIONAL | J40: FOCUS JOGO GRANDE FERRAMENTAS | L40: 1.04
C41: TEXT INC | D41: FOCUS JOGO GRANDE FERRAMENTAS | E41: Reembolsar AFFBR | F41: 1013.75 | H41: 46075 | I41: SELZY | J41: FOCUS JOGO GRANDE FERRAMENTAS | L41: 44.46
C42: SLACK T09R8ECB4P2 | D42: FOCUS JOGO GRANDE FERRAMENTAS | E42: Reembolsar AFFBR | F42: 130.19 | H42: 46076 | I42: IOF - COMPRA INTERNACIONAL | J42: FOCUS JOGO GRANDE FERRAMENTAS | L42: 1.56
C43: IOF - COMPRA INTERNACIONAL | D43: FOCUS JOGO GRANDE FERRAMENTAS | E43: Reembolsar AFFBR | F43: 4.56 | H43: 46066 | I43: TRACK4YOU | J43: FOCUS JOGO GRANDE DEKO FERRAMENTAS | L43: 297
C44: IOF - COMPRA INTERNACIONAL | D44: FOCUS JOGO GRANDE FERRAMENTAS | E44: Reembolsar AFFBR | F44: 1.42 | H44: 46070 | I44: VTURB | J44: FOCUS JOGO GRANDE DEKO FERRAMENTAS | L44: 97
C45: DM *GoDaddycomL | D45: FOCUS JOGO GRANDE FERRAMENTAS | E45: Reembolsar AFFBR | F45: 222.12 | H45: 46080 | I45: DM *GoDaddycomL | J45: OP JOGO GRANDE FERRAMENTAS NOVO PROCESSO | L45: 872.4
C46: MANYCHAT.COM | D46: VINI AVIATOR FERRAMENTAS | E46: Reembolsar AFFBR | F46: 249 | H46: 46080 | I46: MMDSMART LTD | J46: OP JOGO GRANDE FERRAMENTAS NOVO PROCESSO | L46: 322.06
C47: TRACK4YOU | D47: VINI AVIATOR FERRAMENTAS | E47: Reembolsar AFFBR | F47: 297 | H47: 46081 | I47: IOF - COMPRA INTERNACIONAL | J47: OP JOGO GRANDE FERRAMENTAS NOVO PROCESSO | L47: 11.27
C48: MANYCHAT.COM | D48: VINI AVIATOR FERRAMENTAS | E48: Reembolsar AFFBR | F48: 249
B50: DATA | C50: CANAL DE AQUISIÇÃO | E50: Status | F50: =SUM(F51:F53) -> 0 | H50: DATA | I50: CANAL DE AQUISIÇÃO | K50: Status | L50: =SUM(L51:L53) -> 0 | N50: DATA | O50: CANAL DE AQUISIÇÃO | P50: Status | Q50: =SUM(Q51:Q53) -> 0 | S50: DATA | T50: CANAL DE AQUISIÇÃO | U50: Status | V50: =SUM(V51:V53) -> 0 | X50: DATA | Y50: CANAL DE AQUISIÇÃO | Z50: Status | AA50: =SUM(AA51:AA53) -> 0 | AC50: DATA | AD50: CANAL DE AQUISIÇÃO | AE50: Status | AF50: =SUM(AF51:AF53) -> 0 | AH50: DATA | AI50: CANAL DE AQUISIÇÃO | AJ50: Status | AK50: =SUM(AK51:AK53) -> 0 | AM50: DATA | AN50: CANAL DE AQUISIÇÃO | AO50: Status | AP50: =SUM(AP51:AP53) -> 0 | AR50: DATA | AS50: CANAL DE AQUISIÇÃO | AT50: Status | AU50: =SUM(AU51:AU53) -> 0 | AW50: DATA | AX50: CANAL DE AQUISIÇÃO | AY50: Status | AZ50: =SUM(AZ51:AZ53) -> 0 | BB50: DATA | BC50: CANAL DE AQUISIÇÃO | BD50: Status | BE50: =SUM(BE51:BE54) -> 0 | BG50: DATA | BH50: CANAL DE AQUISIÇÃO | BI50: Status | BJ50: =SUM(BJ51:BJ53) -> 0
A51: TRAFEGO PAGO | G51: TRAFEGO PAGO | M51: TRAFEGO PAGO | R51: TRAFEGO PAGO | W51: CUSTO AFILIADOS | AB51: CUSTO AFILIADOS | AG51: CUSTO AFILIADOS | AL51: CUSTO AFILIADOS | AQ51: CUSTO AFILIADOS | AV51: CUSTO AFILIADOS | BA51: CUSTO AFILIADOS | BC51: DEKO SEMANA 12/11 A 23/11 | BF51: CUSTO AFILIADOS | BH51: VINI AVIATOR 11/11 A 10/12
BC52: ZELITO SEMANA 24/11 A 30/11 | BH52: MLISBOA 24/11 A 05/12
BC53: DEKO SEMANA 24/11/ A 30/11 | BH53: DEKO 01/12 A 05/12
BC54: MLISBOA SEMANA 15/11 A 23/11
